Workbook
Name DataProveedores: [1]Data!$B$1:$C$59

Sheet 17
K1: 668.077 | AG1: Profit Terminos | AH1: Au Real (con Rec) | AI1: Profit RC | AJ1: Au Comprado | AL1: Valor
I2: =SUBTOTAL(9,I4:I9311) -> 702.8 | K2: =SUBTOTAL(9,K4:K9311) -> 667.44742 | L2: =SUMPRODUCT(L5:L142,K5:K142)/K2 -> 0.36470039 | Q2: =+SUMPRODUCT(Q5:Q94,AH5:AH94)/SUM(AH5:AH94) -> 89.914313 | R2: =+SUMPRODUCT(R5:R94,AH5:AH94)/SUM(AH5:AH94) -> 2662.2923 | AG2: =SUMPRODUCT($AG5:$AG94,$K5:$K94)/SUM($K5:$K94) -> 68.04762 | AI2: 2820
A3: Lote | B3: F emision | C3: F recepcion | D3: Nombre | E3: RUC | F3: Minero | G3: Sacos | I3: TMH | J3: %H2O | K3: TMS | L3: Oz/tc Planta | M3: Oz/tc comercial | N3: Oz/tc Minero | O3: Oz/tc Pomedio | P3: % Rec Liq | Q3: % Rec Planta | R3: Inter US$ | S3: TC US$ x tc | T3: Bono | U3: Riesgo | V3: Factor | W3: Soda | X3: Cianuro | Y3: Gasto acopio x tm | Z3: Insumos planta x tm | AA3: Insumos liq x tm | AB3: Precio x TMS | AC3: profit maquila | AD3: Profit Rec | AE3: Profit Consumo | AF3: Profit Leyes | AG3: Profit Total $/TM | AH3: =SUBTOTAL(9,AH5:AH9312) -> 7503.7465 | AI3: =SUMPRODUCT(K5:K94,AI5:AI94)/K2 -> 92.393031 | AJ3: =SUBTOTAL(9,AJ5:AJ9312) -> 7351.0089 | AL3: =SUBTOTAL(9,AL5:AL9312) -> 499002.41
A5: IP-782 | C5: 45624 | D5: ZICAMP S.A.C. | E5: {=XLOOKUP(D5,RUC!$B$3:$B$79,RUC!$D$3:$D$79)} -> #N/A | F5: Hernan Mamani | H5: LLAMPO | I5: 9.36 | J5: 17.35 | K5: =+I5-(I5*(J5/100)) -> 7.73604 | L5: 0.079 | M5: 0.069 | N5: 0.069 | O5: =+ROUND((M5+N5)/2,3) -> 0.069 | P5: 90 | Q5: 85.3 | R5: 2641.85 | S5: =IF((90+ROUNDDOWN(O5,1)*100)<95,95,(90+ROUNDDOWN(O5,1)*100)) -> 95 | U5: 100 | V5: 1.1023 | Y5: 20 | Z5: =IF(IF(D5="UNTUCA",IF(+((W5-3)*1.5+(X5-3)*3.1)>0,+((W5-3)*1.5+(X5-3)*3.1),0),IF(+((W5-3)*1.5+(X5-3)*3.1)>0,+((W5-3)*1.5+(X5-3)*3.1),0))<30,30,IF(D5="UNTUCA",IF(+((W5-3)*1.5+(X5-3)*3.1)>0,+((W5-3)*1.5+(X5-3)*3.1),0),IF(+((W5-3)*1.5+(X5-3)*3.1)>0,+((W5-3)*1.5+(X5-3)*3.1),0))) -> 30 | AA5: =+Y5+Z5 -> 50 | AB5: 0 | AC5: =+(S5-T5)*V5-'data 1'!$F$4 -> 24.7185 | AD5: =+(Q5-P5)*(R5-U5)*L5*V5/100 -> -10.403385 | AE5: =+(Y5*V5-70)+V5*(Z5-IF(D5="UNTUCA",IF(+((W5-3)*2.5+(X5-3)*3.1)>0,+((W5-3)*1.5+(X5-3)*3.1),0),IF(+((W5-3)*1.5+(X5-3)*3.1)>0,+((W5-3)*1.5+(X5-3)*3.1),0))) -> -14.885 | AF5: =(L5-O5)*(R5-U5)*Q5*V5/100 -> 23.900047 | AG5: =+IF(D5="RONALD WILLIAN GARIBAY ESCUDERO",AC5+AD5+AE5+AF5+70,AC5+AD5+AE5+AF5) -> 23.330162 | AH5: =31.1035*L5*Q5*1.1023*K5/100 -> 17.873265 | AI5: =+((+$AI$2-R5+U5)*L5*Q5*V5)/100 -> 20.661174 | AJ5: =31.1035*1.1023*K5*P5*O5/100 -> 16.470978 | AL5: 0
A6: IP-783 | C6: 45624 | D6: ZICAMP S.A.C. | E6: {=XLOOKUP(D6,RUC!$B$3:$B$79,RUC!$D$3:$D$79)} -> #N/A | F6: Hernan Mamani | H6: LLAMPO | I6: 4.62 | J6: 18.15 | K6: =+I6-(I6*(J6/100)) -> 3.78147 | L6: 0.072 | M6: 0.062 | N6: 0.062 | O6: =+ROUND((M6+N6)/2,3) -> 0.062 | P6: 90 | Q6: 85.42 | R6: 2641.85 | S6: =IF((90+ROUNDDOWN(O6,1)*100)<95,95,(90+ROUNDDOWN(O6,1)*100)) -> 95 | U6: 100 | V6: 1.1023 | Y6: 20 | Z6: =IF(IF(D6="UNTUCA",IF(+((W6-3)*1.5+(X6-3)*3.1)>0,+((W6-3)*1.5+(X6-3)*3.1),0),IF(+((W6-3)*1.5+(X6-3)*3.1)>0,+((W6-3)*1.5+(X6-3)*3.1),0))<30,30,IF(D6="UNTUCA",IF(+((W6-3)*1.5+(X6-3)*3.1)>0,+((W6-3)*1.5+(X6-3)*3.1),0),IF(+((W6-3)*1.5+(X6-3)*3.1)>0,+((W6-3)*1.5+(X6-3)*3.1),0))) -> 30 | AA6: =+Y6+Z6 -> 50 | AB6: 0 | AC6: =+(S6-T6)*V6-'data 1'!$F$4 -> 24.7185 | AD6: =+(Q6-P6)*(R6-U6)*L6*V6/100 -> -9.2394836 | AE6: =+(Y6*V6-70)+V6*(Z6-IF(D6="UNTUCA",IF(+((W6-3)*2.5+(X6-3)*3.1)>0,+((W6-3)*1.5+(X6-3)*3.1),0),IF(+((W6-3)*1.5+(X6-3)*3.1)>0,+((W6-3)*1.5+(X6-3)*3.1),0))) -> -14.885 | AF6: =(L6-O6)*(R6-U6)*Q6*V6/100 -> 23.93367 | AG6: =+IF(D6="RONALD WILLIAN GARIBAY ESCUDERO",AC6+AD6+AE6+AF6+70,AC6+AD6+AE6+AF6) -> 24.527686 | AH6: =31.1035*L6*Q6*1.1023*K6/100 -> 7.9737349 | AI6: =+((+$AI$2-R6+U6)*L6*Q6*V6)/100 -> 18.856928 | AJ6: =31.1035*1.1023*K6*P6*O6/100 -> 7.2344235 | AL6: 0
A7: IP-784 | C7: 45624 | D7: ZICAMP S.A.C. | E7: {=XLOOKUP(D7,RUC!$B$3:$B$79,RUC!$D$3:$D$79)} -> #N/A | F7: Hernan Mamani | H7: LLAMPO | I7: 8.98 | J7: 16 | K7: =+I7-(I7*(J7/100)) -> 7.5432 | L7: 0.078 | M7: 0.068 | N7: 0.068 | O7: =+ROUND((M7+N7)/2,3) -> 0.068 | P7: 90 | Q7: 85.07 | R7: 2641.85 | S7: =IF((90+ROUNDDOWN(O7,1)*100)<95,95,(90+ROUNDDOWN(O7,1)*100)) -> 95 | U7: 100 | V7: 1.1023 | Y7: 20 | Z7: =IF(IF(D7="UNTUCA",IF(+((W7-3)*1.5+(X7-3)*3.1)>0,+((W7-3)*1.5+(X7-3)*3.1),0),IF(+((W7-3)*1.5+(X7-3)*3.1)>0,+((W7-3)*1.5+(X7-3)*3.1),0))<30,30,IF(D7="UNTUCA",IF(+((W7-3)*1.5+(X7-3)*3.1)>0,+((W7-3)*1.5+(X7-3)*3.1),0),IF(+((W7-3)*1.5+(X7-3)*3.1)>0,+((W7-3)*1.5+(X7-3)*3.1),0))) -> 30 | AA7: =+Y7+Z7 -> 50 | AB7: 0 | AC7: =+(S7-T7)*V7-'data 1'!$F$4 -> 24.7185 | AD7: =+(Q7-P7)*(R7-U7)*L7*V7/100 -> -10.774354 | AE7: =+(Y7*V7-70)+V7*(Z7-IF(D7="UNTUCA",IF(+((W7-3)*2.5+(X7-3)*3.1)>0,+((W7-3)*1.5+(X7-3)*3.1),0),IF(+((W7-3)*1.5+(X7-3)*3.1)>0,+((W7-3)*1.5+(X7-3)*3.1),0))) -> -14.885 | AF7: =(L7-O7)*(R7-U7)*Q7*V7/100 -> 23.835604 | AG7: =+IF(D7="RONALD WILLIAN GARIBAY ESCUDERO",AC7+AD7+AE7+AF7+70,AC7+AD7+AE7+AF7) -> 22.89475 | AH7: =31.1035*L7*Q7*1.1023*K7/100 -> 17.160729 | AI7: =+((+$AI$2-R7+U7)*L7*Q7*V7)/100 -> 20.344635 | AJ7: =31.1035*1.1023*K7*P7*O7/100 -> 15.827638 | AL7: 0
A8: IP-785 | C8: 45624 | D8: ZICAMP S.A.C. | E8: {=XLOOKUP(D8,RUC!$B$3:$B$79,RUC!$D$3:$D$79)} -> #N/A | F8: Hernan Mamani | H8: LLAMPO | I8: 4.48 | J8: 17.5 | K8: =+I8-(I8*(J8/100)) -> 3.696 | L8: 0.084 | M8: 0.074 | N8: 0.074 | O8: =+ROUND((M8+N8)/2,3) -> 0.074 | P8: 90 | Q8: 85.7 | R8: 2641.85 | S8: =IF((90+ROUNDDOWN(O8,1)*100)<95,95,(90+ROUNDDOWN(O8,1)*100)) -> 95 | U8: 100 | V8: 1.1023 | Y8: 20 | Z8: =IF(IF(D8="UNTUCA",IF(+((W8-3)*1.5+(X8-3)*3.1)>0,+((W8-3)*1.5+(X8-3)*3.1),0),IF(+((W8-3)*1.5+(X8-3)*3.1)>0,+((W8-3)*1.5+(X8-3)*3.1),0))<30,30,IF(D8="UNTUCA",IF(+((W8-3)*1.5+(X8-3)*3.1)>0,+((W8-3)*1.5+(X8-3)*3.1),0),IF(+((W8-3)*1.5+(X8-3)*3.1)>0,+((W8-3)*1.5+(X8-3)*3.1),0))) -> 30 | AA8: =+Y8+Z8 -> 50 | AB8: 0 | AC8: =+(S8-T8)*V8-'data 1'!$F$4 -> 24.7185 | AD8: =+(Q8-P8)*(R8-U8)*L8*V8/100 -> -10.120395 | AE8: =+(Y8*V8-70)+V8*(Z8-IF(D8="UNTUCA",IF(+((W8-3)*2.5+(X8-3)*3.1)>0,+((W8-3)*1.5+(X8-3)*3.1),0),IF(+((W8-3)*1.5+(X8-3)*3.1)>0,+((W8-3)*1.5+(X8-3)*3.1),0))) -> -14.885 | AF8: =(L8-O8)*(R8-U8)*Q8*V8/100 -> 24.012122 | AG8: =+IF(D8="RONALD WILLIAN GARIBAY ESCUDERO",AC8+AD8+AE8+AF8+70,AC8+AD8+AE8+AF8) -> 23.725227 | AH8: =31.1035*L8*Q8*1.1023*K8/100 -> 9.1222326 | AI8: =+((+$AI$2-R8+U8)*L8*Q8*V8)/100 -> 22.071862 | AJ8: =31.1035*1.1023*K8*P8*O8/100 -> 8.4394717 | AL8: 0
A9: IP-969 | B9: 45666 | C9: 45649 | D9: SOTOMAYOR CORAZAO WISTHERMUNDO | E9: {=XLOOKUP(D9,RUC!$B$3:$B$79,RUC!$D$3:$D$79)} -> 10416085884 | G9: AGRANEL | H9: MINERAL | I9: 33.74 | J9: 6.1 | K9: =+I9-(I9*(J9/100)) -> 31.68186 | L9: 0.1505 | M9: 0.1407175 | N9: 0.163 | O9: =+ROUND((M9+N9)/2,3) -> 0.152 | P9: 90 | Q9: 89.74 | R9: 2613.8 | S9: 85 | U9: 90 | V9: 1.1023 | Z9: 15 | AA9: =+Y9+Z9 -> 15 | AB9: =+((O9*P9*(R9-U9)/100)-S9-AA9+T9)*V9 -> 270.34551 | AC9: =+(S9-T9)*V9-'data 1'!$F$4 -> 13.6955 | AD9: =+(Q9-P9)*(R9-U9)*L9*V9/100 -> -1.0885906 | AE9: =+(Y9*V9-70)+V9*(Z9-IF(D9="UNTUCA",IF(+((W9-3)*2.5+(X9-3)*3.1)>0,+((W9-3)*1.5+(X9-3)*3.1),0),IF(+((W9-3)*1.5+(X9-3)*3.1)>0,+((W9-3)*1.5+(X9-3)*3.1),0))) -> -53.4655 | AF9: =(L9-O9)*(R9-U9)*Q9*V9/100 -> -3.7448297 | AG9: =+IF(D9="RONALD WILLIAN GARIBAY ESCUDERO",AC9+AD9+AE9+AF9+70,AC9+AD9+AE9+AF9)+70-10 -> 15.39658 | AH9: =31.1035*L9*Q9*1.1023*K9/100 -> 146.70412 | AI9: =+((+$AI$2-R9+U9)*L9*Q9*V9)/100 -> 44.096836 | AJ9: =31.1035*1.1023*K9*P9*O9/100 -> 148.59556 | AL9: =+IF(AB9*K9>0,AB9*K9,0) -> 8565.0487
A10: IP-970 | B10: 45666 | C10: 45649 | D10: SOTOMAYOR CORAZAO WISTHERMUNDO | E10: {=XLOOKUP(D10,RUC!$B$3:$B$79,RUC!$D$3:$D$79)} -> 10416085884 | G10: 26 | H10: MINERAL | I10: 1.5 | J10: 7.45 | K10: =+I10-(I10*(J10/100)) -> 1.38825 | L10: 0.3205 | M10: 0.30768 | N10: 0.355 | O10: =+ROUND((M10+N10)/2,3) -> 0.331 | P10: 90 | Q10: 89.62 | R10: 2613.8 | S10: 100 | U10: 90 | V10: 1.1023 | Z10: 15 | AA10: =+Y10+Z10 -> 15 | AB10: =+((O10*P10*(R10-U10)/100)-S10-AA10+T10)*V10 -> 701.98875 | AC10: =+(S10-T10)*V10-'data 1'!$F$4 -> 30.23 | AD10: =+(Q10-P10)*(R10-U10)*L10*V10/100 -> -3.3881792 | AE10: =+(Y10*V10-70)+V10*(Z10-IF(D10="UNTUCA",IF(+((W10-3)*2.5+(X10-3)*3.1)>0,+((W10-3)*1.5+(X10-3)*3.1),0),IF(+((W10-3)*1.5+(X10-3)*3.1)>0,+((W10-3)*1.5+(X10-3)*3.1),0))) -> -53.4655 | AF10: =(L10-O10)*(R10-U10)*Q10*V10/100 -> -26.178755 | AG10: =+IF(D10="RONALD WILLIAN GARIBAY ESCUDERO",AC10+AD10+AE10+AF10+70,AC10+AD10+AE10+AF10)+70-10 -> 7.1975662 | AH10: =31.1035*L10*Q10*1.1023*K10/100 -> 13.671297 | AI10: =+((+$AI$2-R10+U10)*L10*Q10*V10)/100 -> 93.781643 | AJ10: =31.1035*1.1023*K10*P10*O10/100 -> 14.179054 | AL10: =+IF(AB10*K10>0,AB10*K10,0) -> 974.53589
A11: IP-973 | B11: 45657 | C11: 45649 | D11: SOTOMAYOR CORAZAO WISTHERMUNDO | E11: {=XLOOKUP(D11,RUC!$B$3:$B$79,RUC!$D$3:$D$79)} -> 10416085884 | G11: AGRANEL | H11: MINERAL | I11: 26.91 | J11: 3.9 | K11: =+I11-(I11*(J11/100)) -> 25.86051 | L11: 0.1025 | M11: 0.097 | N11: 0.108 | O11: =+ROUND((M11+N11)/2,3) -> 0.103 | P11: 80 | Q11: 89.39 | R11: 2613.8 | S11: 110 | U11: 90 | V11: 1.1023 | Z11: =IF(IF(D11="UNTUCA",IF(+((W11-3)*1.5+(X11-3)*3.1)>0,+((W11-3)*1.5+(X11-3)*3.1),0),IF(+((W11-3)*1.5+(X11-3)*3.1)>0,+((W11-3)*1.5+(X11-3)*3.1),0))<30,30,IF(D11="UNTUCA",IF(+((W11-3)*1.5+(X11-3)*3.1)>0,+((W11-3)*1.5+(X11-3)*3.1),0),IF(+((W11-3)*1.5+(X11-3)*3.1)>0,+((W11-3)*1.5+(X11-3)*3.1),0))) -> 30 | AA11: =+Y11+Z11 -> 30 | AB11: =+((O11*P11*(R11-U11)/100)-S11-AA11+T11)*V11 -> 74.913543 | AC11: =+(S11-T11)*V11-'data 1'!$F$4 -> 41.253 | AD11: =+(Q11-P11)*(R11-U11)*L11*V11/100 -> 26.775908 | AE11: =+(Y11*V11-70)+V11*(Z11-IF(D11="UNTUCA",IF(+((W11-3)*2.5+(X11-3)*3.1)>0,+((W11-3)*1.5+(X11-3)*3.1),0),IF(+((W11-3)*1.5+(X11-3)*3.1)>0,+((W11-3)*1.5+(X11-3)*3.1),0))) -> -36.931 | AF11: =(L11-O11)*(R11-U11)*Q11*V11/100 -> -1.2434081 | AG11: =+IF(D11="RONALD WILLIAN GARIBAY ESCUDERO",AC11+AD11+AE11+AF11+70,AC11+AD11+AE11+AF11)+70-53 -> 46.8545 | AH11: =31.1035*L11*Q11*1.1023*K11/100 -> 81.23795 | AI11: =+((+$AI$2-R11+U11)*L11*Q11*V11)/100 -> 29.915596 | AJ11: =31.1035*1.1023*K11*P11*O11/100 -> 73.05894 | AL11: =+IF(AB11*K11>0,AB11*K11,0) -> 1937.3024
A12: IP-1004 | B12: 45657 | C12: 45654 | D12: RONALD WILLIAN GARIBAY ESCUDERO | E12: {=XLOOKUP(D12,RUC!$B$3:$B$79,RUC!$D$3:$D$79)} -> #N/A | G12: AGRANEL | H12: MINERAL | I12: 9.58 | J12: 1.2 | K12: =+I12-(I12*(J12/100)) -> 9.46504 | L12: 0.414 | M12: 0.397 | N12: 0.456 | O12: =+ROUND((M12+N12)/2,3) -> 0.427 | P12: 90 | Q12: 89.79 | R12: 2615.95 | S12: 120 | U12: 100 | V12: 1.1023 | Y12: 0 | Z12: =IF(IF(D12="UNTUCA",IF(+((W12-3)*1.5+(X12-3)*3.1)>0,+((W12-3)*1.5+(X12-3)*3.1),0),IF(+((W12-3)*1.5+(X12-3)*3.1)>0,+((W12-3)*1.5+(X12-3)*3.1),0))<30,30,IF(D12="UNTUCA",IF(+((W12-3)*1.5+(X12-3)*3.1)>0,+((W12-3)*1.5+(X12-3)*3.1),0),IF(+((W12-3)*1.5+(X12-3)*3.1)>0,+((W12-3)*1.5+(X12-3)*3.1),0))) -> 30 | AA12: =+Y12+Z12 -> 30 | AB12: =+((O12*P12*(R12-U12)/100)-S12-AA12+T12)*V12 -> 900.44637 | AC12: =+(S12-T12)*V12-'data 1'!$F$4 -> 52.276 | AD12: =+(Q12-P12)*(R12-U12)*L12*V12/100 -> -2.4111346 | AE12: =+(Y12*V12-70)+V12*(Z12-IF(D12="UNTUCA",IF(+((W12-3)*2.5+(X12-3)*3.1)>0,+((W12-3)*1.5+(X12-3)*3.1),0),IF(+((W12-3)*1.5+(X12-3)*3.1)>0,+((W12-3)*1.5+(X12-3)*3.1),0))) -> -36.931 | AF12: =(L12-O12)*(R12-U12)*Q12*V12/100 -> -32.372269 | AG12: =+IF(D12="RONALD WILLIAN GARIBAY ESCUDERO",AC12+AD12+AE12+AF12+70,AC12+AD12+AE12+AF12) -> 50.561597 | AH12: =31.1035*L12*Q12*1.1023*K12/100 -> 120.63125 | AI12: =+((+$AI$2-R12+U12)*L12*Q12*V12)/100 -> 124.58711 | AJ12: =31.1035*1.1023*K12*P12*O12/100 -> 124.71018 | AL12: =+IF(AB12*K12>0,AB12*K12,0) -> 8522.7609
A13: IP-1006 | B13: 45660 | C13: 45655 | D13: QUISPE MARTINEZ IZEQUIEL | E13: {=XLOOKUP(D13,RUC!$B$3:$B$79,RUC!$D$3:$D$79)} -> 10457401928 | F13: Dario Sanchez | G13: 80 | H13: MINERAL | I13: 33.91 | J13: 15.4 | K13: =+I13-(I13*(J13/100)) -> 28.68786 | L13: 0.585 | M13: 0.561 | N13: 0.598 | O13: =+ROUND((M13+N13)/2,3) -> 0.58 | P13: 90 | Q13: 89.66 | R13: 2615.95 | S13: 130 | U13: 100 | V13: 1.1023 | Z13: =IF(IF(D13="UNTUCA",IF(+((W13-3)*1.5+(X13-3)*3.1)>0,+((W13-3)*1.5+(X13-3)*3.1),0),IF(+((W13-3)*1.5+(X13-3)*3.1)>0,+((W13-3)*1.5+(X13-3)*3.1),0))<30,30,IF(D13="UNTUCA",IF(+((W13-3)*1.5+(X13-3)*3.1)>0,+((W13-3)*1.5+(X13-3)*3.1),0),IF(+((W13-3)*1.5+(X13-3)*3.1)>0,+((W13-3)*1.5+(X13-3)*3.1),0))) -> 30 | AA13: =+Y13+Z13 -> 30 | AB13: =+((O13*P13*(R13-U13)/100)-S13-AA13+T13)*V13 -> 1271.3111 | AC13: =+(S13-T13)*V13-'data 1'!$F$4 -> 63.299 | AD13: =+(Q13-P13)*(R13-U13)*L13*V13/100 -> -5.5161567 | AE13: =+(Y13*V13-70)+V13*(Z13-IF(D13="UNTUCA",IF(+((W13-3)*2.5+(X13-3)*3.1)>0,+((W13-3)*1.5+(X13-3)*3.1),0),IF(+((W13-3)*1.5+(X13-3)*3.1)>0,+((W13-3)*1.5+(X13-3)*3.1),0))) -> -36.931 | AF13: =(L13-O13)*(R13-U13)*Q13*V13/100 -> 12.432846 | AG13: =+IF(D13="RONALD WILLIAN GARIBAY ESCUDERO",AC13+AD13+AE13+AF13+70,AC13+AD13+AE13+AF13) -> 33.284689 | AH13: =31.1035*L13*Q13*1.1023*K13/100 -> 515.8956 | AI13: =+((+$AI$2-R13+U13)*L13*Q13*V13)/100 -> 175.79212 | AJ13: =31.1035*1.1023*K13*P13*O13/100 -> 513.42584 | AL13: =+IF(AB13*K13>0,AB13*K13,0) -> 36471.196
A14: IP-1007 | B14: 45660 | C14: 45655 | D14: QUISPE MARTINEZ IZEQUIEL | E14: {=XLOOKUP(D14,RUC!$B$3:$B$79,RUC!$D$3:$D$79)} -> 10457401928 | F14: Dario Sanchez | G14: 90 | H14: MINERAL | I14: 34.66 | J14: 16.35 | K14: =+I14-(I14*(J14/100)) -> 28.99309 | L14: 0.576 | M14: 0.553 | N14: 0.574 | O14: =+ROUND((M14+N14)/2,3) -> 0.564 | P14: 90 | Q14: 89.71 | R14: 2615.95 | S14: 130 | U14: 100 | V14: 1.1023 | Z14: =IF(IF(D14="UNTUCA",IF(+((W14-3)*1.5+(X14-3)*3.1)>0,+((W14-3)*1.5+(X14-3)*3.1),0),IF(+((W14-3)*1.5+(X14-3)*3.1)>0,+((W14-3)*1.5+(X14-3)*3.1),0))<30,30,IF(D14="UNTUCA",IF(+((W14-3)*1.5+(X14-3)*3.1)>0,+((W14-3)*1.5+(X14-3)*3.1),0),IF(+((W14-3)*1.5+(X14-3)*3.1)>0,+((W14-3)*1.5+(X14-3)*3.1),0))) -> 30 | AA14: =+Y14+Z14 -> 30 | AB14: =+((O14*P14*(R14-U14)/100)-S14-AA14+T14)*V14 -> 1231.3752 | AC14: =+(S14-T14)*V14-'data 1'!$F$4 -> 63.299 | AD14: =+(Q14-P14)*(R14-U14)*L14*V14/100 -> -4.6325732 | AE14: =+(Y14*V14-70)+V14*(Z14-IF(D14="UNTUCA",IF(+((W14-3)*2.5+(X14-3)*3.1)>0,+((W14-3)*1.5+(X14-3)*3.1),0),IF(+((W14-3)*1.5+(X14-3)*3.1)>0,+((W14-3)*1.5+(X14-3)*3.1),0))) -> -36.931 | AF14: =(L14-O14)*(R14-U14)*Q14*V14/100 -> 29.85547 | AG14: =+IF(D14="RONALD WILLIAN GARIBAY ESCUDERO",AC14+AD14+AE14+AF14+70,AC14+AD14+AE14+AF14) -> 51.590897 | AH14: =31.1035*L14*Q14*1.1023*K14/100 -> 513.64955 | AI14: =+((+$AI$2-R14+U14)*L14*Q14*V14)/100 -> 173.18416 | AJ14: =31.1035*1.1023*K14*P14*O14/100 -> 504.57437 | AL14: =+IF(AB14*K14>0,AB14*K14,0) -> 35701.371
A15: IP-1008 | B15: 45660 | C15: 45655 | D15: INVERSIONES Y SERVICIOS MULTIPLES SANTA LUCIA E.I.R.L | E15: {=XLOOKUP(D15,RUC!$B$3:$B$79,RUC!$D$3:$D$79)} -> 20610873309 | G15: 144 | H15: MINERAL | I15: 11.96 | J15: 1 | K15: =+I15-(I15*(J15/100)) -> 11.8404 | L15: 0.559 | M15: 0.537 | N15: 0.647 | O15: =+ROUND((M15+N15)/2,3) -> 0.592 | P15: 90 | Q15: 89.46 | R15: 2615.95 | S15: =IF((90+ROUNDDOWN(O15,1)*100)<95,95,(90+ROUNDDOWN(O15,1)*100)) -> 140 | U15: 120 | V15: 1.1023 | Y15: 20 | Z15: =IF(IF(D15="UNTUCA",IF(+((W15-3)*1.5+(X15-3)*3.1)>0,+((W15-3)*1.5+(X15-3)*3.1),0),IF(+((W15-3)*1.5+(X15-3)*3.1)>0,+((W15-3)*1.5+(X15-3)*3.1),0))<30,30,IF(D15="UNTUCA",IF(+((W15-3)*1.5+(X15-3)*3.1)>0,+((W15-3)*1.5+(X15-3)*3.1),0),IF(+((W15-3)*1.5+(X15-3)*3.1)>0,+((W15-3)*1.5+(X15-3)*3.1),0))) -> 30 | AA15: =+Y15+Z15 -> 50 | AB15: =+((O15*P15*(R15-U15)/100)-S15-AA15+T15)*V15 -> 1256.448 | AC15: =+(S15-T15)*V15-'data 1'!$F$4 -> 74.322 | AD15: =+(Q15-P15)*(R15-U15)*L15*V15/100 -> -8.305031 | AE15: =+(Y15*V15-70)+V15*(Z15-IF(D15="UNTUCA",IF(+((W15-3)*2.5+(X15-3)*3.1)>0,+((W15-3)*1.5+(X15-3)*3.1),0),IF(+((W15-3)*1.5+(X15-3)*3.1)>0,+((W15-3)*1.5+(X15-3)*3.1),0))) -> -14.885 | AF15: =(L15-O15)*(R15-U15)*Q15*V15/100 -> -81.222906 | AG15: =+IF(D15="RONALD WILLIAN GARIBAY ESCUDERO",AC15+AD15+AE15+AF15+70,AC15+AD15+AE15+AF15)+70-53 -> -13.090937 | AH15: =31.1035*L15*Q15*1.1023*K15/100 -> 203.0094 | AI15: =+((+$AI$2-R15+U15)*L15*Q15*V15)/100 -> 178.62923 | AJ15: =31.1035*1.1023*K15*P15*O15/100 -> 216.2916 | AL15: =+IF(AB15*K15>0,AB15*K15,0) -> 14876.847
A16: IP-1009 | B16: 45657 | C16: 45655 | D16: RONALD WILLIAN GARIBAY ESCUDERO | E16: {=XLOOKUP(D16,RUC!$B$3:$B$79,RUC!$D$3:$D$79)} -> #N/A | G16: 94 | H16: LLAMPO | I16: 7.16 | J16: 1.5 | K16: =+I16-(I16*(J16/100)) -> 7.0526 | L16: 0.389 | M16: 0.373 | N16: 0.459 | O16: =+ROUND((M16+N16)/2,3) -> 0.416 | P16: 90 | Q16: 89.84 | R16: 2615.95 | S16: 120 | U16: 100 | V16: 1.1023 | Y16: 0 | Z16: =IF(IF(D16="UNTUCA",IF(+((W16-3)*1.5+(X16-3)*3.1)>0,+((W16-3)*1.5+(X16-3)*3.1),0),IF(+((W16-3)*1.5+(X16-3)*3.1)>0,+((W16-3)*1.5+(X16-3)*3.1),0))<30,30,IF(D16="UNTUCA",IF(+((W16-3)*1.5+(X16-3)*3.1)>0,+((W16-3)*1.5+(X16-3)*3.1),0),IF(+((W16-3)*1.5+(X16-3)*3.1)>0,+((W16-3)*1.5+(X16-3)*3.1),0))) -> 30 | AA16: =+Y16+Z16 -> 30 | AB16: =+((O16*P16*(R16-U16)/100)-S16-AA16+T16)*V16 -> 872.99038 | AC16: =+(S16-T16)*V16-'data 1'!$F$4 -> 52.276 | AD16: =+(Q16-P16)*(R16-U16)*L16*V16/100 -> -1.7261216 | AE16: =+(Y16*V16-70)+V16*(Z16-IF(D16="UNTUCA",IF(+((W16-3)*2.5+(X16-3)*3.1)>0,+((W16-3)*1.5+(X16-3)*3.1),0),IF(+((W16-3)*1.5+(X16-3)*3.1)>0,+((W16-3)*1.5+(X16-3)*3.1),0))) -> -36.931 | AF16: =(L16-O16)*(R16-U16)*Q16*V16/100 -> -67.272152 | AG16: =+IF(D16="RONALD WILLIAN GARIBAY ESCUDERO",AC16+AD16+AE16+AF16+70,AC16+AD16+AE16+AF16) -> 16.346726 | AH16: =31.1035*L16*Q16*1.1023*K16/100 -> 84.504078 | AI16: =+((+$AI$2-R16+U16)*L16*Q16*V16)/100 -> 117.12893 | AJ16: =31.1035*1.1023*K16*P16*O16/100 -> 90.530342 | AL16: =+IF(AB16*K16>0,AB16*K16,0) -> 6156.852
A17: IP-1010 | B17: 45661 | C17: 45655 | D17: INVERSIONES Y SERVICIOS MULTIPLES SANTA LUCIA E.I.R.L | E17: {=XLOOKUP(D17,RUC!$B$3:$B$79,RUC!$D$3:$D$79)} -> 20610873309 | G17: 80 | H17: MINERAL | I17: 7.66 | J17: 1.6 | K17: =+I17-(I17*(J17/100)) -> 7.53744 | L17: 0.199 | M17: 0.189 | N17: 0.189 | O17: =+ROUND((M17+N17)/2,3) -> 0.189 | P17: 90 | Q17: 89.77 | R17: 2615.95 | S17: =IF((90+ROUNDDOWN(O17,1)*100)<95,95,(90+ROUNDDOWN(O17,1)*100)) -> 100 | U17: 120 | V17: 1.1023 | Y17: 10 | Z17: =IF(IF(D17="UNTUCA",IF(+((W17-3)*1.5+(X17-3)*3.1)>0,+((W17-3)*1.5+(X17-3)*3.1),0),IF(+((W17-3)*1.5+(X17-3)*3.1)>0,+((W17-3)*1.5+(X17-3)*3.1),0))<30,30,IF(D17="UNTUCA",IF(+((W17-3)*1.5+(X17-3)*3.1)>0,+((W17-3)*1.5+(X17-3)*3.1),0),IF(+((W17-3)*1.5+(X17-3)*3.1)>0,+((W17-3)*1.5+(X17-3)*3.1),0))) -> 30 | AA17: =+Y17+Z17 -> 40 | AB17: =+((O17*P17*(R17-U17)/100)-S17-AA17+T17)*V17 -> 313.67169 | AC17: =+(S17-T17)*V17-'data 1'!$F$4 -> 30.23 | AD17: =+(Q17-P17)*(R17-U17)*L17*V17/100 -> -1.2592635 | AE17: =+(Y17*V17-70)+V17*(Z17-IF(D17="UNTUCA",IF(+((W17-3)*2.5+(X17-3)*3.1)>0,+((W17-3)*1.5+(X17-3)*3.1),0),IF(+((W17-3)*1.5+(X17-3)*3.1)>0,+((W17-3)*1.5+(X17-3)*3.1),0))) -> -25.908 | AF17: =(L17-O17)*(R17-U17)*Q17*V17/100 -> 24.698292 | AG17: =+IF(D17="RONALD WILLIAN GARIBAY ESCUDERO",AC17+AD17+AE17+AF17+70,AC17+AD17+AE17+AF17)+70-53 -> 44.761028 | AH17: =31.1035*L17*Q17*1.1023*K17/100 -> 46.165468 | AI17: =+((+$AI$2-R17+U17)*L17*Q17*V17)/100 -> 63.811086 | AJ17: =31.1035*1.1023*K17*P17*O17/100 -> 43.957932 | AL17: =+IF(AB17*K17>0,AB17*K17,0) -> 2364.2816
A18: IP-1011 | B18: 45660 | C18: 45655 | D18: EMPRESA MINERA MARKATA CAS S.A.C. | E18: {=XLOOKUP(D18,RUC!$B$3:$B$79,RUC!$D$3:$D$79)} -> 20606526599 | G18: 110 | H18: MINERAL | I18: 9.23 | J18: 1.1 | K18: =+I18-(I18*(J18/100)) -> 9.12847 | L18: 0.334 | M18: 0.32 | N18: 0.32 | O18: =+ROUND((M18+N18)/2,3) -> 0.32 | P18: 90 | Q18: 89.56 | R18: 2615.95 | S18: =IF((90+ROUNDDOWN(O18,1)*100)<95,95,(90+ROUNDDOWN(O18,1)*100)) -> 120 | U18: 120 | V18: 1.1023 | Y18: 20 | Z18: =IF(IF(D18="UNTUCA",IF(+((W18-3)*1.5+(X18-3)*3.1)>0,+((W18-3)*1.5+(X18-3)*3.1),0),IF(+((W18-3)*1.5+(X18-3)*3.1)>0,+((W18-3)*1.5+(X18-3)*3.1),0))<30,30,IF(D18="UNTUCA",IF(+((W18-3)*1.5+(X18-3)*3.1)>0,+((W18-3)*1.5+(X18-3)*3.1),0),IF(+((W18-3)*1.5+(X18-3)*3.1)>0,+((W18-3)*1.5+(X18-3)*3.1),0))) -> 30 | AA18: =+Y18+Z18 -> 50 | AB18: =+((O18*P18*(R18-U18)/100)-S18-AA18+T18)*V18 -> 604.97928 | AC18: =+(S18-T18)*V18-'data 1'!$F$4 -> 52.276 | AD18: =+(Q18-P18)*(R18-U18)*L18*V18/100 -> -4.0432894 | AE18: =+(Y18*V18-70)+V18*(Z18-IF(D18="UNTUCA",IF(+((W18-3)*2.5+(X18-3)*3.1)>0,+((W18-3)*1.5+(X18-3)*3.1),0),IF(+((W18-3)*1.5+(X18-3)*3.1)>0,+((W18-3)*1.5+(X18-3)*3.1),0))) -> -14.885 | AF18: =(L18-O18)*(R18-U18)*Q18*V18/100 -> 34.49672 | AG18: =+IF(D18="RONALD WILLIAN GARIBAY ESCUDERO",AC18+AD18+AE18+AF18+70,AC18+AD18+AE18+AF18)+70-53 -> 84.844431 | AH18: =31.1035*L18*Q18*1.1023*K18/100 -> 93.619779 | AI18: =+((+$AI$2-R18+U18)*L18*Q18*V18)/100 -> 106.84947 | AJ18: =31.1035*1.1023*K18*P18*O18/100 -> 90.136263 | AL18: =+IF(AB18*K18>0,AB18*K18,0) -> 5522.5352
A19: IP-1012 | B19: 45660 | C19: 45656 | D19: LLASA YUCRA YOLANDA | E19: {=XLOOKUP(D19,RUC!$B$3:$B$79,RUC!$D$3:$D$79)} -> #N/A | G19: 12 | H19: MINERAL | I19: 1.07 | J19: 1.3 | K19: =+I19-(I19*(J19/100)) -> 1.05609 | L19: 0.234 | M19: 0.224 | N19: 0.224 | O19: =+ROUND((M19+N19)/2,3) -> 0.224 | P19: 90 | Q19: 89.56 | R19: 2609.1 | S19: =IF((90+ROUNDDOWN(O19,1)*100)<95,95,(90+ROUNDDOWN(O19,1)*100)) -> 110 | U19: 110 | V19: 1.1023 | Y19: 20 | Z19: =IF(IF(D19="UNTUCA",IF(+((W19-3)*1.5+(X19-3)*3.1)>0,+((W19-3)*1.5+(X19-3)*3.1),0),IF(+((W19-3)*1.5+(X19-3)*3.1)>0,+((W19-3)*1.5+(X19-3)*3.1),0))<30,30,IF(D19="UNTUCA",IF(+((W19-3)*1.5+(X19-3)*3.1)>0,+((W19-3)*1.5+(X19-3)*3.1),0),IF(+((W19-3)*1.5+(X19-3)*3.1)>0,+((W19-3)*1.5+(X19-3)*3.1),0))) -> 30 | AA19: =+Y19+Z19 -> 50 | AB19: =+((O19*P19*(R19-U19)/100)-S19-AA19+T19)*V19 -> 378.9912 | AC19: =+(S19-T19)*V19-'data 1'!$F$4 -> 41.253 | AD19: =+(Q19-P19)*(R19-U19)*L19*V19/100 -> -2.8362988 | AE19: =+(Y19*V19-70)+V19*(Z19-IF(D19="UNTUCA",IF(+((W19-3)*2.5+(X19-3)*3.1)>0,+((W19-3)*1.5+(X19-3)*3.1),0),IF(+((W19-3)*1.5+(X19-3)*3.1)>0,+((W19-3)*1.5+(X19-3)*3.1),0))) -> -14.885 | AF19: =(L19-O19)*(R19-U19)*Q19*V19/100 -> 24.671612 | AG19: =+IF(D19="RONALD WILLIAN GARIBAY ESCUDERO",AC19+AD19+AE19+AF19+70,AC19+AD19+AE19+AF19)+70-53 -> 65.203313 | AH19: =31.1035*L19*Q19*1.1023*K19/100 -> 7.5882205 | AI19: =+((+$AI$2-R19+U19)*L19*Q19*V19)/100 -> 74.130933 | AJ19: =31.1035*1.1023*K19*P19*O19/100 -> 7.2996246 | AL19: =+IF(AB19*K19>0,AB19*K19,0) -> 400.24881
A20: IP-1013 | B20: 45660 | C20: 45656 | D20: LLASA YUCRA YOLANDA | E20: {=XLOOKUP(D20,RUC!$B$3:$B$79,RUC!$D$3:$D$79)} -> #N/A | G20: 22 | H20: MINERAL | I20: 1.92 | J20: 1.4 | K20: =+I20-(I20*(J20/100)) -> 1.89312 | L20: 0.158 | M20: 0.148 | N20: 0.148 | O20: =+ROUND((M20+N20)/2,3) -> 0.148 | P20: 90 | Q20: 89.79 | R20: 2609.1 | S20: =IF((90+ROUNDDOWN(O20,1)*100)<95,95,(90+ROUNDDOWN(O20,1)*100)) -> 100 | U20: 110 | V20: 1.1023 | Y20: 20 | Z20: =IF(IF(D20="UNTUCA",IF(+((W20-3)*1.5+(X20-3)*3.1)>0,+((W20-3)*1.5+(X20-3)*3.1),0),IF(+((W20-3)*1.5+(X20-3)*3.1)>0,+((W20-3)*1.5+(X20-3)*3.1),0))<30,30,IF(D20="UNTUCA",IF(+((W20-3)*1.5+(X20-3)*3.1)>0,+((W20-3)*1.5+(X20-3)*3.1),0),IF(+((W20-3)*1.5+(X20-3)*3.1)>0,+((W20-3)*1.5+(X20-3)*3.1),0))) -> 30 | AA20: =+Y20+Z20 -> 50 | AB20: =+((O20*P20*(R20-U20)/100)-S20-AA20+T20)*V20 -> 201.58876 | AC20: =+(S20-T20)*V20-'data 1'!$F$4 -> 30.23 | AD20: =+(Q20-P20)*(R20-U20)*L20*V20/100 -> -0.91402868 | AE20: =+(Y20*V20-70)+V20*(Z20-IF(D20="UNTUCA",IF(+((W20-3)*2.5+(X20-3)*3.1)>0,+((W20-3)*1.5+(X20-3)*3.1),0),IF(+((W20-3)*1.5+(X20-3)*3.1)>0,+((W20-3)*1.5+(X20-3)*3.1),0))) -> -14.885 | AF20: =(L20-O20)*(R20-U20)*Q20*V20/100 -> 24.734971 | AG20: =+IF(D20="RONALD WILLIAN GARIBAY ESCUDERO",AC20+AD20+AE20+AF20+70,AC20+AD20+AE20+AF20)+70-53 -> 56.165943 | AH20: =31.1035*L20*Q20*1.1023*K20/100 -> 9.2081476 | AI20: =+((+$AI$2-R20+U20)*L20*Q20*V20)/100 -> 50.182765 | AJ20: =31.1035*1.1023*K20*P20*O20/100 -> 8.6455263 | AL20: =+IF(AB20*K20>0,AB20*K20,0) -> 381.63171
A21: IP-1014 | B21: 45660 | C21: 45656 | D21: LLASA YUCRA YOLANDA | E21: {=XLOOKUP(D21,RUC!$B$3:$B$79,RUC!$D$3:$D$79)} -> #N/A | G21: 22 | H21: MINERAL | I21: 1.97 | J21: 1.5 | K21: =+I21-(I21*(J21/100)) -> 1.94045 | L21: 0.171 | M21: 0.161 | N21: 0.161 | O21: =+ROUND((M21+N21)/2,3) -> 0.161 | P21: 90 | Q21: 89.72 | R21: 2609.1 | S21: =IF((90+ROUNDDOWN(O21,1)*100)<95,95,(90+ROUNDDOWN(O21,1)*100)) -> 100 | U21: 110 | V21: 1.1023 | Y21: 20 | Z21: =IF(IF(D21="UNTUCA",IF(+((W21-3)*1.5+(X21-3)*3.1)>0,+((W21-3)*1.5+(X21-3)*3.1),0),IF(+((W21-3)*1.5+(X21-3)*3.1)>0,+((W21-3)*1.5+(X21-3)*3.1),0))<30,30,IF(D21="UNTUCA",IF(+((W21-3)*1.5+(X21-3)*3.1)>0,+((W21-3)*1.5+(X21-3)*3.1),0),IF(+((W21-3)*1.5+(X21-3)*3.1)>0,+((W21-3)*1.5+(X21-3)*3.1),0))) -> 30 | AA21: =+Y21+Z21 -> 50 | AB21: =+((O21*P21*(R21-U21)/100)-S21-AA21+T21)*V21 -> 233.81942 | AC21: =+(S21-T21)*V21-'data 1'!$F$4 -> 30.23 | AD21: =+(Q21-P21)*(R21-U21)*L21*V21/100 -> -1.3189781 | AE21: =+(Y21*V21-70)+V21*(Z21-IF(D21="UNTUCA",IF(+((W21-3)*2.5+(X21-3)*3.1)>0,+((W21-3)*1.5+(X21-3)*3.1),0),IF(+((W21-3)*1.5+(X21-3)*3.1)>0,+((W21-3)*1.5+(X21-3)*3.1),0))) -> -14.885 | AF21: =(L21-O21)*(R21-U21)*Q21*V21/100 -> 24.715688 | AG21: =+IF(D21="RONALD WILLIAN GARIBAY ESCUDERO",AC21+AD21+AE21+AF21+70,AC21+AD21+AE21+AF21)+70-53 -> 55.74171 | AH21: =31.1035*L21*Q21*1.1023*K21/100 -> 10.206971 | AI21: =+((+$AI$2-R21+U21)*L21*Q21*V21)/100 -> 54.269385 | AJ21: =31.1035*1.1023*K21*P21*O21/100 -> 9.6400639 | AL21: =+IF(AB21*K21>0,AB21*K21,0) -> 453.7149
A22: IP-1015 | B22: 45664 | C22: 45656 | D22: GRUPO EL CAZADOR GOLD E.I.R.L | E22: {=XLOOKUP(D22,RUC!$B$3:$B$79,RUC!$D$3:$D$79)} -> 20606094010 | G22: 30 | H22: MINERAL | I22: 2.66 | J22: 1.6 | K22: =+I22-(I22*(J22/100)) -> 2.61744 | L22: 0.157 | M22: 0.147 | N22: 0.188 | O22: =+ROUND((M22+N22)/2,3) -> 0.168 | P22: 90 | Q22: 89.79 | R22: 2609.1 | S22: =IF((90+ROUNDDOWN(O22,1)*100)<95,95,(90+ROUNDDOWN(O22,1)*100)) -> 100 | U22: 120 | V22: 1.1023 | Y22: 20 | Z22: =IF(IF(D22="UNTUCA",IF(+((W22-3)*1.5+(X22-3)*3.1)>0,+((W22-3)*1.5+(X22-3)*3.1),0),IF(+((W22-3)*1.5+(X22-3)*3.1)>0,+((W22-3)*1.5+(X22-3)*3.1),0))<30,30,IF(D22="UNTUCA",IF(+((W22-3)*1.5+(X22-3)*3.1)>0,+((W22-3)*1.5+(X22-3)*3.1),0),IF(+((W22-3)*1.5+(X22-3)*3.1)>0,+((W22-3)*1.5+(X22-3)*3.1),0))) -> 30 | AA22: =+Y22+Z22 -> 50 | AB22: =+((O22*P22*(R22-U22)/100)-S22-AA22+T22)*V22 -> 249.50772 | AC22: =+(S22-T22)*V22-'data 1'!$F$4 -> 30.23 | AD22: =+(Q22-P22)*(R22-U22)*L22*V22/100 -> -0.90460941 | AE22: =+(Y22*V22-70)+V22*(Z22-IF(D22="UNTUCA",IF(+((W22-3)*2.5+(X22-3)*3.1)>0,+((W22-3)*1.5+(X22-3)*3.1),0),IF(+((W22-3)*1.5+(X22-3)*3.1)>0,+((W22-3)*1.5+(X22-3)*3.1),0))) -> -14.885 | AF22: =(L22-O22)*(R22-U22)*Q22*V22/100 -> -27.099596 | AG22: =+IF(D22="RONALD WILLIAN GARIBAY ESCUDERO",AC22+AD22+AE22+AF22+70,AC22+AD22+AE22+AF22)+70-53 -> 4.3407951 | AH22: =31.1035*L22*Q22*1.1023*K22/100 -> 12.650667 | AI22: =+((+$AI$2-R22+U22)*L22*Q22*V22)/100 -> 51.419068 | AJ22: =31.1035*1.1023*K22*P22*O22/100 -> 13.56868 | AL22: =+IF(AB22*K22>0,AB22*K22,0) -> 653.07149
A23: IP-1016 | B23: 45660 | C23: 45656 | D23: EMPRESA MINERA MARKATA CAS S.A.C. | E23: {=XLOOKUP(D23,RUC!$B$3:$B$79,RUC!$D$3:$D$79)} -> 20606526599 | G23: 65 | H23: MINERAL | I23: 5.03 | J23: 1.9 | K23: =+I23-(I23*(J23/100)) -> 4.93443 | L23: 0.278 | M23: 0.266 | N23: 0.266 | O23: =+ROUND((M23+N23)/2,3) -> 0.266 | P23: 90 | Q23: 89.82 | R23: 2609.1 | S23: =IF((90+ROUNDDOWN(O23,1)*100)<95,95,(90+ROUNDDOWN(O23,1)*100)) -> 110 | U23: 120 | V23: 1.1023 | Y23: 20 | Z23: =IF(IF(D23="UNTUCA",IF(+((W23-3)*1.5+(X23-3)*3.1)>0,+((W23-3)*1.5+(X23-3)*3.1),0),IF(+((W23-3)*1.5+(X23-3)*3.1)>0,+((W23-3)*1.5+(X23-3)*3.1),0))<30,30,IF(D23="UNTUCA",IF(+((W23-3)*1.5+(X23-3)*3.1)>0,+((W23-3)*1.5+(X23-3)*3.1),0),IF(+((W23-3)*1.5+(X23-3)*3.1)>0,+((W23-3)*1.5+(X23-3)*3.1),0))) -> 30 | AA23: =+Y23+Z23 -> 50 | AB23: =+((O23*P23*(R23-U23)/100)-S23-AA23+T23)*V23 -> 480.48214 | AC23: =+(S23-T23)*V23-'data 1'!$F$4 -> 41.253 | AD23: =+(Q23-P23)*(R23-U23)*L23*V23/100 -> -1.372965 | AE23: =+(Y23*V23-70)+V23*(Z23-IF(D23="UNTUCA",IF(+((W23-3)*2.5+(X23-3)*3.1)>0,+((W23-3)*1.5+(X23-3)*3.1),0),IF(+((W23-3)*1.5+(X23-3)*3.1)>0,+((W23-3)*1.5+(X23-3)*3.1),0))) -> -14.885 | AF23: =(L23-O23)*(R23-U23)*Q23*V23/100 -> 29.573073 | AG23: =+IF(D23="RONALD WILLIAN GARIBAY ESCUDERO",AC23+AD23+AE23+AF23+70,AC23+AD23+AE23+AF23)+70-53 -> 71.568108 | AH23: =31.1035*L23*Q23*1.1023*K23/100 -> 42.243891 | AI23: =+((+$AI$2-R23+U23)*L23*Q23*V23)/100 -> 91.078196 | AJ23: =31.1035*1.1023*K23*P23*O23/100 -> 40.501416 | AL23: =+IF(AB23*K23>0,AB23*K23,0) -> 2370.9055
A24: IP-1017 | B24: 45663 | C24: 45657 | D24: METAL EXTRACTION COMPANY S.A.C. | E24: {=XLOOKUP(D24,RUC!$B$3:$B$79,RUC!$D$3:$D$79)} -> 20606527439 | G24: 94 | H24: M.LLAMPO | I24: 10.48 | J24: 1.1 | K24: =+I24-(I24*(J24/100)) -> 10.36472 | L24: 0.072 | M24: 0.062 | N24: 0.062 | O24: =+ROUND((M24+N24)/2,3) -> 0.062 | P24: 90 | Q24: 87.8 | R24: 2609.1 | S24: =IF((90+ROUNDDOWN(O24,1)*100)<95,95,(90+ROUNDDOWN(O24,1)*100)) -> 95 | U24: 120 | V24: 1.1023 | Y24: 20 | Z24: =IF(IF(D24="UNTUCA",IF(+((W24-3)*1.5+(X24-3)*3.1)>0,+((W24-3)*1.5+(X24-3)*3.1),0),IF(+((W24-3)*1.5+(X24-3)*3.1)>0,+((W24-3)*1.5+(X24-3)*3.1),0))<30,30,IF(D24="UNTUCA",IF(+((W24-3)*1.5+(X24-3)*3.1)>0,+((W24-3)*1.5+(X24-3)*3.1),0),IF(+((W24-3)*1.5+(X24-3)*3.1)>0,+((W24-3)*1.5+(X24-3)*3.1),0))) -> 30 | AA24: =+Y24+Z24 -> 50 | AB24: 0 | AC24: =+(S24-T24)*V24-'data 1'!$F$4 -> 24.7185 | AD24: =+(Q24-P24)*(R24-U24)*L24*V24/100 -> -4.3460761 | AE24: =+(Y24*V24-70)+V24*(Z24-IF(D24="UNTUCA",IF(+((W24-3)*2.5+(X24-3)*3.1)>0,+((W24-3)*1.5+(X24-3)*3.1),0),IF(+((W24-3)*1.5+(X24-3)*3.1)>0,+((W24-3)*1.5+(X24-3)*3.1),0))) -> -14.885 | AF24: =(L24-O24)*(R24-U24)*Q24*V24/100 -> 24.089993 | AG24: =+IF(D24="RONALD WILLIAN GARIBAY ESCUDERO",AC24+AD24+AE24+AF24+70,AC24+AD24+AE24+AF24)+70-53 -> 46.577417 | AH24: =31.1035*L24*Q24*1.1023*K24/100 -> 22.46434 | AI24: =+((+$AI$2-R24+U24)*L24*Q24*V24)/100 -> 23.058104 | AJ24: =31.1035*1.1023*K24*P24*O24/100 -> 19.829001 | AL24: =+IF(AB24*K24>0,AB24*K24,0) -> 0
A25: IP-1018 | B25: 45663 | C25: 45657 | D25: METAL EXTRACTION COMPANY S.A.C. | E25: {=XLOOKUP(D25,RUC!$B$3:$B$79,RUC!$D$3:$D$79)} -> 20606527439 | G25: 32 | H25: MINERAL | I25: 2.52 | J25: 1.2 | K25: =+I25-(I25*(J25/100)) -> 2.48976 | L25: 0.145 | M25: 0.135 | N25: 0.166 | O25: 0.15 | P25: 90 | Q25: 89.7 | R25: 2609.1 | S25: =IF((90+ROUNDDOWN(O25,1)*100)<95,95,(90+ROUNDDOWN(O25,1)*100)) -> 100 | U25: 90 | V25: 1.1023 | Y25: 20 | Z25: =IF(IF(D25="UNTUCA",IF(+((W25-3)*1.5+(X25-3)*3.1)>0,+((W25-3)*1.5+(X25-3)*3.1),0),IF(+((W25-3)*1.5+(X25-3)*3.1)>0,+((W25-3)*1.5+(X25-3)*3.1),0))<30,30,IF(D25="UNTUCA",IF(+((W25-3)*1.5+(X25-3)*3.1)>0,+((W25-3)*1.5+(X25-3)*3.1),0),IF(+((W25-3)*1.5+(X25-3)*3.1)>0,+((W25-3)*1.5+(X25-3)*3.1),0))) -> 30 | AA25: =+Y25+Z25 -> 50 | AB25: =+((O25*P25*(R25-U25)/100)-S25-AA25+T25)*V25 -> 209.52353 | AC25: =+(S25-T25)*V25-'data 1'!$F$4 -> 30.23 | AD25: =+(Q25-P25)*(R25-U25)*L25*V25/100 -> -1.2079097 | AE25: =+(Y25*V25-70)+V25*(Z25-IF(D25="UNTUCA",IF(+((W25-3)*2.5+(X25-3)*3.1)>0,+((W25-3)*1.5+(X25-3)*3.1),0),IF(+((W25-3)*1.5+(X25-3)*3.1)>0,+((W25-3)*1.5+(X25-3)*3.1),0))) -> -14.885 | AF25: =(L25-O25)*(R25-U25)*Q25*V25/100 -> -12.453966 | AG25: =+IF(D25="RONALD WILLIAN GARIBAY ESCUDERO",AC25+AD25+AE25+AF25+70,AC25+AD25+AE25+AF25)+70-53 -> 18.683125 | AH25: =31.1035*L25*Q25*1.1023*K25/100 -> 11.102659 | AI25: =+((+$AI$2-R25+U25)*L25*Q25*V25)/100 -> 43.140228 | AJ25: =31.1035*1.1023*K25*P25*O25/100 -> 11.523922 | AL25: =+IF(AB25*K25>0,AB25*K25,0) -> 521.66331
A26: IP-1020 | B26: 45660 | C26: 45657 | D26: MELCHOR AGUSTIN VERA PACHECO | E26: {=XLOOKUP(D26,RUC!$B$3:$B$79,RUC!$D$3:$D$79)} -> 10082235774 | G26: 68 | H26: MINERAL | I26: 7.1 | J26: 1.5 | K26: =+I26-(I26*(J26/100)) -> 6.9935 | L26: 0.662 | M26: 0.652 | N26: 0.652 | O26: =+ROUND((M26+N26)/2,3) -> 0.652 | P26: 90 | Q26: 89.72 | R26: 2609.1 | S26: 125 | U26: 80 | V26: 1.1023 | Z26: 10 | AA26: =+Y26+Z26 -> 10 | AB26: =+((O26*P26*(R26-U26)/100)-S26-AA26+T26)*V26 -> 1487.0863 | AC26: =+(S26-T26)*V26-'data 1'!$F$4 -> 57.7875 | AD26: =+(Q26-P26)*(R26-U26)*L26*V26/100 -> -5.167516 | AE26: =+(Y26*V26-70)+V26*(Z26-IF(D26="UNTUCA",IF(+((W26-3)*2.5+(X26-3)*3.1)>0,+((W26-3)*1.5+(X26-3)*3.1),0),IF(+((W26-3)*1.5+(X26-3)*3.1)>0,+((W26-3)*1.5+(X26-3)*3.1),0))) -> -58.977 | AF26: =(L26-O26)*(R26-U26)*Q26*V26/100 -> 25.012383 | AG26: =+IF(D26="RONALD WILLIAN GARIBAY ESCUDERO",AC26+AD26+AE26+AF26+70,AC26+AD26+AE26+AF26)+70 -> 88.655367 | AH26: =31.1035*L26*Q26*1.1023*K26/100 -> 142.41342 | AI26: =+((+$AI$2-R26+U26)*L26*Q26*V26)/100 -> 190.4543 | AJ26: =31.1035*1.1023*K26*P26*O26/100 -> 140.69989 | AL26: =+IF(AB26*K26>0,AB26*K26,0) -> 10399.938
A27: IP-1025 | B27: 45683 | C27: 45657 | D27: RONALD WILLIAN GARIBAY ESCUDERO | E27: {=XLOOKUP(D27,RUC!$B$3:$B$79,RUC!$D$3:$D$79)} -> #N/A | H27: MINERAL | I27: 7.53 | J27: 1.6 | K27: =+I27-(I27*(J27/100)) -> 7.40952 | L27: 0.062 | M27: 0.05208 | N27: 0.213 | O27: =+ROUND((M27+N27)/2,3) -> 0.133 | P27: 88 | Q27: 88.29 | R27: 2609.1 | S27: =IF((90+ROUNDDOWN(O27,1)*100)<95,95,(90+ROUNDDOWN(O27,1)*100)) -> 100 | U27: 100 | V27: 1.1023 | Z27: =IF(IF(D27="UNTUCA",IF(+((W27-3)*1.5+(X27-3)*3.1)>0,+((W27-3)*1.5+(X27-3)*3.1),0),IF(+((W27-3)*1.5+(X27-3)*3.1)>0,+((W27-3)*1.5+(X27-3)*3.1),0))<30,30,IF(D27="UNTUCA",IF(+((W27-3)*1.5+(X27-3)*3.1)>0,+((W27-3)*1.5+(X27-3)*3.1),0),IF(+((W27-3)*1.5+(X27-3)*3.1)>0,+((W27-3)*1.5+(X27-3)*3.1),0))) -> 30 | AA27: =+Y27+Z27 -> 30 | AB27: =+((O27*P27*(R27-U27)/100)-S27-AA27+T27)*V27 -> 180.408 | AC27: =+(S27-T27)*V27-'data 1'!$F$4 -> 30.23 | AD27: =+(Q27-P27)*(R27-U27)*L27*V27/100 -> 0.49728741 | AE27: =+(Y27*V27-70)+V27*(Z27-IF(D27="UNTUCA",IF(+((W27-3)*2.5+(X27-3)*3.1)>0,+((W27-3)*1.5+(X27-3)*3.1),0),IF(+((W27-3)*1.5+(X27-3)*3.1)>0,+((W27-3)*1.5+(X27-3)*3.1),0))) -> -36.931 | AF27: =(L27-O27)*(R27-U27)*Q27*V27/100 -> -173.37547 | AG27: =+IF(D27="RONALD WILLIAN GARIBAY ESCUDERO",AC27+AD27+AE27+AF27+70,AC27+AD27+AE27+AF27)+70-53 -> -92.579179 | AH27: =31.1035*L27*Q27*1.1023*K27/100 -> 13.906004 | AI27: =+((+$AI$2-R27+U27)*L27*Q27*V27)/100 -> 18.759607 | AJ27: =31.1035*1.1023*K27*P27*O27/100 -> 29.732639 | AL27: =+IF(AB27*K27>0,AB27*K27,0) -> 1336.7367
A28: IP-1026 | B28: 45683 | C28: 45657 | D28: RONALD WILLIAN GARIBAY ESCUDERO | E28: {=XLOOKUP(D28,RUC!$B$3:$B$79,RUC!$D$3:$D$79)} -> #N/A | H28: MINERAL | I28: 14.73 | J28: 1.7 | K28: =+I28-(I28*(J28/100)) -> 14.47959 | L28: 0.0965 | M28: 0.08685 | N28: 0.133 | O28: =+ROUND((M28+N28)/2,3) -> 0.11 | P28: 88 | Q28: 89.12 | R28: 2609.1 | S28: =IF((90+ROUNDDOWN(O28,1)*100)<95,95,(90+ROUNDDOWN(O28,1)*100)) -> 100 | U28: 100 | V28: 1.1023 | Z28: =IF(IF(D28="UNTUCA",IF(+((W28-3)*1.5+(X28-3)*3.1)>0,+((W28-3)*1.5+(X28-3)*3.1),0),IF(+((W28-3)*1.5+(X28-3)*3.1)>0,+((W28-3)*1.5+(X28-3)*3.1),0))<30,30,IF(D28="UNTUCA",IF(+((W28-3)*1.5+(X28-3)*3.1)>0,+((W28-3)*1.5+(X28-3)*3.1),0),IF(+((W28-3)*1.5+(X28-3)*3.1)>0,+((W28-3)*1.5+(X28-3)*3.1),0))) -> 30 | AA28: =+Y28+Z28 -> 30 | AB28: =+((O28*P28*(R28-U28)/100)-S28-AA28+T28)*V28 -> 124.42859 | AC28: =+(S28-T28)*V28-'data 1'!$F$4 -> 30.23 | AD28: =+(Q28-P28)*(R28-U28)*L28*V28/100 -> 2.989256 | AE28: =+(Y28*V28-70)+V28*(Z28-IF(D28="UNTUCA",IF(+((W28-3)*2.5+(X28-3)*3.1)>0,+((W28-3)*1.5+(X28-3)*3.1),0),IF(+((W28-3)*1.5+(X28-3)*3.1)>0,+((W28-3)*1.5+(X28-3)*3.1),0))) -> -36.931 | AF28: =(L28-O28)*(R28-U28)*Q28*V28/100 -> -33.275664 | AG28: =+IF(D28="RONALD WILLIAN GARIBAY ESCUDERO",AC28+AD28+AE28+AF28+70,AC28+AD28+AE28+AF28)+70-53 -> 50.012592 | AH28: =31.1035*L28*Q28*1.1023*K28/100 -> 42.694096 | AI28: =+((+$AI$2-R28+U28)*L28*Q28*V28)/100 -> 29.47291 | AJ28: =31.1035*1.1023*K28*P28*O28/100 -> 48.055233 | AL28: =+IF(AB28*K28>0,AB28*K28,0) -> 1801.675
A29: IP-1029 | B29: 45674 | C29: 45660 | D29: SOTOMAYOR CORAZAO WISTHERMUNDO | E29: {=XLOOKUP(D29,RUC!$B$3:$B$79,RUC!$D$3:$D$79)} -> 10416085884 | G29: AGRANEL | H29: MINERAL | I29: 30.58 | J29: 5.05 | K29: =+I29-(I29*(J29/100)) -> 29.03571 | L29: 0.168 | M29: 0.158 | N29: 0.158 | O29: =+ROUND((M29+N29)/2,3) -> 0.158 | P29: 90 | Q29: 89.75 | R29: 2616.45 | S29: 85 | U29: 90 | V29: 1.1023 | Z29: 15 | AA29: 15 | AB29: =+((O29*P29*(R29-U29)/100)-S29-AA29+T29)*V29 -> 285.78361 | AC29: =+(S29-T29)*V29-'data 1'!$F$4 -> 13.6955 | AD29: =+(Q29-P29)*(R29-U29)*L29*V29/100 -> -1.1696605 | AE29: =+(Y29*V29-70)+V29*(Z29-IF(D29="UNTUCA",IF(+((W29-3)*2.5+(X29-3)*3.1)>0,+((W29-3)*1.5+(X29-3)*3.1),0),IF(+((W29-3)*1.5+(X29-3)*3.1)>0,+((W29-3)*1.5+(X29-3)*3.1),0))) -> -53.4655 | AF29: =(L29-O29)*(R29-U29)*Q29*V29/100 -> 24.99453 | AG29: =+IF(D29="RONALD WILLIAN GARIBAY ESCUDERO",AC29+AD29+AE29+AF29+70,AC29+AD29+AE29+AF29)+70-10 -> 44.054869 | AH29: =31.1035*L29*Q29*1.1023*K29/100 -> 150.10158 | AI29: =+((+$AI$2-R29+U29)*L29*Q29*V29)/100 -> 48.789417 | AJ29: =31.1035*1.1023*K29*P29*O29/100 -> 141.56018 | AL29: =+IF(AB29*K29>0,AB29*K29,0) -> 8297.93
A30: IP-1030 | B30: 45674 | C30: 45660 | D30: SOTOMAYOR CORAZAO MORAYMA | E30: {=XLOOKUP(D30,RUC!$B$3:$B$79,RUC!$D$3:$D$79)} -> 10421580605 | G30: AGRANEL | H30: MINERAL | I30: 29.75 | J30: 10.2 | K30: =+I30-(I30*(J30/100)) -> 26.7155 | L30: 0.164 | M30: 0.154 | N30: 0.154 | O30: =+ROUND((M30+N30)/2,3) -> 0.154 | P30: 90 | Q30: 89.84 | R30: 2616.45 | S30: 85 | U30: 90 | V30: 1.1023 | Y30: 30 | Z30: 15 | AA30: 15 | AB30: =+((O30*P30*(R30-U30)/100)-S30-AA30+T30)*V30 -> 275.75795 | AC30: =+(S30-T30)*V30-'data 1'!$F$4 -> 13.6955 | AD30: =+(Q30-P30)*(R30-U30)*L30*V30/100 -> -0.73075929 | AE30: =+(Y30*V30-70)+V30*(Z30-IF(D30="UNTUCA",IF(+((W30-3)*2.5+(X30-3)*3.1)>0,+((W30-3)*1.5+(X30-3)*3.1),0),IF(+((W30-3)*1.5+(X30-3)*3.1)>0,+((W30-3)*1.5+(X30-3)*3.1),0))) -> -20.3965 | AF30: =(L30-O30)*(R30-U30)*Q30*V30/100 -> 25.019594 | AG30: =+IF(D30="RONALD WILLIAN GARIBAY ESCUDERO",AC30+AD30+AE30+AF30+70,AC30+AD30+AE30+AF30)+70-10 -> 77.587835 | AH30: =31.1035*L30*Q30*1.1023*K30/100 -> 134.95406 | AI30: =+((+$AI$2-R30+U30)*L30*Q30*V30)/100 -> 47.675525 | AJ30: =31.1035*1.1023*K30*P30*O30/100 -> 126.95085 | AL30: =+IF(AB30*K30>0,AB30*K30,0) -> 7367.0115
A31: IP-1032 | B31: 45667 | C31: 45661 | D31: EMPRESA MINERA MARKATA CAS S.A.C. | E31: {=XLOOKUP(D31,RUC!$B$3:$B$79,RUC!$D$3:$D$79)} -> 20606526599 | G31: 180 | H31: MINERAL | I31: 14.74 | J31: 1.5 | K31: =+I31-(I31*(J31/100)) -> 14.5189 | L31: 0.368 | M31: 0.353 | N31: 0.353 | O31: =+ROUND((M31+N31)/2,3) -> 0.353 | P31: 90 | Q31: 89.86 | R31: 2646.8 | S31: =IF((90+ROUNDDOWN(O31,1)*100)<95,95,(90+ROUNDDOWN(O31,1)*100)) -> 120 | U31: 120 | V31: 1.1023 | Y31: 20 | Z31: =IF(IF(D31="UNTUCA",IF(+((W31-3)*1.5+(X31-3)*3.1)>0,+((W31-3)*1.5+(X31-3)*3.1),0),IF(+((W31-3)*1.5+(X31-3)*3.1)>0,+((W31-3)*1.5+(X31-3)*3.1),0))<30,30,IF(D31="UNTUCA",IF(+((W31-3)*1.5+(X31-3)*3.1)>0,+((W31-3)*1.5+(X31-3)*3.1),0),IF(+((W31-3)*1.5+(X31-3)*3.1)>0,+((W31-3)*1.5+(X31-3)*3.1),0))) -> 30 | AA31: =+Y31+Z31 -> 50 | AB31: =+((O31*P31*(R31-U31)/100)-S31-AA31+T31)*V31 -> 697.49615 | AC31: =+(S31-T31)*V31-'data 1'!$F$4 -> 52.276 | AD31: =+(Q31-P31)*(R31-U31)*L31*V31/100 -> -1.4349823 | AE31: =+(Y31*V31-70)+V31*(Z31-IF(D31="UNTUCA",IF(+((W31-3)*2.5+(X31-3)*3.1)>0,+((W31-3)*1.5+(X31-3)*3.1),0),IF(+((W31-3)*1.5+(X31-3)*3.1)>0,+((W31-3)*1.5+(X31-3)*3.1),0))) -> -14.885 | AF31: =(L31-O31)*(R31-U31)*Q31*V31/100 -> 37.542946 | AG31: =+IF(D31="RONALD WILLIAN GARIBAY ESCUDERO",AC31+AD31+AE31+AF31+70,AC31+AD31+AE31+AF31)+70-53 -> 90.498964 | AH31: =31.1035*L31*Q31*1.1023*K31/100 -> 164.6103 | AI31: =+((+$AI$2-R31+U31)*L31*Q31*V31)/100 -> 106.87546 | AJ31: =31.1035*1.1023*K31*P31*O31/100 -> 158.14665 | AL31: =+IF(AB31*K31>0,AB31*K31,0) -> 10126.877
A32: IP-1033 | B32: 45673 | C32: 45666 | D32: EXPLORACIONES CLAUDIA Y KAREN E.I.R.L. | E32: {=XLOOKUP(D32,RUC!$B$3:$B$79,RUC!$D$3:$D$79)} -> 20601620147 | G32: 51 | H32: M.LLAMPO | I32: 4.06 | J32: 1.1 | K32: =+I32-(I32*(J32/100)) -> 4.01534 | L32: 0.457 | M32: 0.438 | N32: 0.438 | O32: =+ROUND((M32+N32)/2,3) -> 0.438 | P32: 90 | Q32: 90.25 | R32: 2650.85 | S32: 100 | U32: 90 | V32: 1.1023 | Y32: 10 | Z32: =IF(IF(D32="UNTUCA",IF(+((W32-3)*1.5+(X32-3)*3.1)>0,+((W32-3)*1.5+(X32-3)*3.1),0),IF(+((W32-3)*1.5+(X32-3)*3.1)>0,+((W32-3)*1.5+(X32-3)*3.1),0))<30,30,IF(D32="UNTUCA",IF(+((W32-3)*1.5+(X32-3)*3.1)>0,+((W32-3)*1.5+(X32-3)*3.1),0),IF(+((W32-3)*1.5+(X32-3)*3.1)>0,+((W32-3)*1.5+(X32-3)*3.1),0))) -> 30 | AA32: =+Y32+Z32 -> 40 | AB32: =+((O32*P32*(R32-U32)/100)-S32-AA32+T32)*V32 -> 958.4356 | AC32: =+(S32-T32)*V32-'data 1'!$F$4 -> 30.23 | AD32: =+(Q32-P32)*(R32-U32)*L32*V32/100 -> 3.2250775 | AE32: =+(Y32*V32-70)+V32*(Z32-IF(D32="UNTUCA",IF(+((W32-3)*2.5+(X32-3)*3.1)>0,+((W32-3)*1.5+(X32-3)*3.1),0),IF(+((W32-3)*1.5+(X32-3)*3.1)>0,+((W32-3)*1.5+(X32-3)*3.1),0))) -> -25.908 | AF32: =(L32-O32)*(R32-U32)*Q32*V32/100 -> 48.404391 | AG32: =+IF(D32="RONALD WILLIAN GARIBAY ESCUDERO",AC32+AD32+AE32+AF32+70,AC32+AD32+AE32+AF32)+70-53 -> 72.951468 | AH32: =31.1035*L32*Q32*1.1023*K32/100 -> 56.779924 | AI32: =+((+$AI$2-R32+U32)*L32*Q32*V32)/100 -> 117.81876 | AJ32: =31.1035*1.1023*K32*P32*O32/100 -> 54.268525 | AL32: =+IF(AB32*K32>0,AB32*K32,0) -> 3848.4448
A33: IP-1034 | B33: 45673 | C33: 45666 | D33: EXPLORACIONES CLAUDIA Y KAREN E.I.R.L. | E33: {=XLOOKUP(D33,RUC!$B$3:$B$79,RUC!$D$3:$D$79)} -> 20601620147 | G33: 11 | H33: M.LLAMPO | I33: 0.78 | J33: 1.2 | K33: =+I33-(I33*(J33/100)) -> 0.77064 | L33: 0.574 | M33: 0.551 | N33: 0.61 | O33: =+ROUND((M33+N33)/2,3) -> 0.581 | P33: 90 | Q33: 90.4 | R33: 2650.85 | S33: 110 | U33: 90 | V33: 1.1023 | Y33: 10 | Z33: =IF(IF(D33="UNTUCA",IF(+((W33-3)*1.5+(X33-3)*3.1)>0,+((W33-3)*1.5+(X33-3)*3.1),0),IF(+((W33-3)*1.5+(X33-3)*3.1)>0,+((W33-3)*1.5+(X33-3)*3.1),0))<30,30,IF(D33="UNTUCA",IF(+((W33-3)*1.5+(X33-3)*3.1)>0,+((W33-3)*1.5+(X33-3)*3.1),0),IF(+((W33-3)*1.5+(X33-3)*3.1)>0,+((W33-3)*1.5+(X33-3)*3.1),0))) -> 30 | AA33: =+Y33+Z33 -> 40 | AB33: =+((O33*P33*(R33-U33)/100)-S33-AA33+T33)*V33 -> 1310.7102 | AC33: =+(S33-T33)*V33-'data 1'!$F$4 -> 41.253 | AD33: =+(Q33-P33)*(R33-U33)*L33*V33/100 -> 6.4812061 | AE33: =+(Y33*V33-70)+V33*(Z33-IF(D33="UNTUCA",IF(+((W33-3)*2.5+(X33-3)*3.1)>0,+((W33-3)*1.5+(X33-3)*3.1),0),IF(+((W33-3)*1.5+(X33-3)*3.1)>0,+((W33-3)*1.5+(X33-3)*3.1),0))) -> -25.908 | AF33: =(L33-O33)*(R33-U33)*Q33*V33/100 -> -17.862836 | AG33: =+IF(D33="RONALD WILLIAN GARIBAY ESCUDERO",AC33+AD33+AE33+AF33+70,AC33+AD33+AE33+AF33)+70-53 -> 20.96337 | AH33: =31.1035*L33*Q33*1.1023*K33/100 -> 13.71011 | AI33: =+((+$AI$2-R33+U33)*L33*Q33*V33)/100 -> 148.22837 | AJ33: =31.1035*1.1023*K33*P33*O33/100 -> 13.815902 | AL33: =+IF(AB33*K33>0,AB33*K33,0) -> 1010.0857
A34: IP-1035 | B34: 45673 | C34: 45666 | D34: EXPLORACIONES CLAUDIA Y KAREN E.I.R.L. | E34: {=XLOOKUP(D34,RUC!$B$3:$B$79,RUC!$D$3:$D$79)} -> 20601620147 | G34: AGRANEL | H34: MINERAL | I34: 8.45 | J34: 6.85 | K34: =+I34-(I34*(J34/100)) -> 7.871175 | L34: 0.105 | M34: 0.095 | N34: 0.116 | O34: =+ROUND((M34+N34)/2,3) -> 0.106 | P34: 85 | Q34: 90.12 | R34: 2650.85 | S34: 110 | U34: 90 | V34: 1.1023 | Z34: =IF(IF(D34="UNTUCA",IF(+((W34-3)*1.5+(X34-3)*3.1)>0,+((W34-3)*1.5+(X34-3)*3.1),0),IF(+((W34-3)*1.5+(X34-3)*3.1)>0,+((W34-3)*1.5+(X34-3)*3.1),0))<30,30,IF(D34="UNTUCA",IF(+((W34-3)*1.5+(X34-3)*3.1)>0,+((W34-3)*1.5+(X34-3)*3.1),0),IF(+((W34-3)*1.5+(X34-3)*3.1)>0,+((W34-3)*1.5+(X34-3)*3.1),0))) -> 30 | AA34: =+Y34+Z34 -> 30 | AB34: =+((O34*P34*(R34-U34)/100)-S34-AA34+T34)*V34 -> 100.01453 | AC34: =+(S34-T34)*V34-'data 1'!$F$4 -> 41.253 | AD34: =+(Q34-P34)*(R34-U34)*L34*V34/100 -> 15.175507 | AE34: =+(Y34*V34-70)+V34*(Z34-IF(D34="UNTUCA",IF(+((W34-3)*2.5+(X34-3)*3.1)>0,+((W34-3)*1.5+(X34-3)*3.1),0),IF(+((W34-3)*1.5+(X34-3)*3.1)>0,+((W34-3)*1.5+(X34-3)*3.1),0))) -> -36.931 | AF34: =(L34-O34)*(R34-U34)*Q34*V34/100 -> -2.5439298 | AG34: =+IF(D34="RONALD WILLIAN GARIBAY ESCUDERO",AC34+AD34+AE34+AF34+70,AC34+AD34+AE34+AF34)+70-53 -> 33.953577 | AH34: =31.1035*L34*Q34*1.1023*K34/100 -> 25.536367 | AI34: =+((+$AI$2-R34+U34)*L34*Q34*V34)/100 -> 27.030962 | AJ34: =31.1035*1.1023*K34*P34*O34/100 -> 24.314953 | AL34: =+IF(AB34*K34>0,AB34*K34,0) -> 787.23186
A35: IP-1036 | B35: 45673 | C35: 45666 | D35: EXPLORACIONES CLAUDIA Y KAREN E.I.R.L. | E35: {=XLOOKUP(D35,RUC!$B$3:$B$79,RUC!$D$3:$D$79)} -> 20601620147 | G35: 85 | H35: MINERAL | I35: 0.75 | J35: 10.1 | K35: =+I35-(I35*(J35/100)) -> 0.67425 | L35: 0.165 | M35: 0.141 | N35: 0.141 | O35: =+ROUND((M35+N35)/2,3) -> 0.141 | P35: 85 | Q35: 90.33 | R35: 2650.85 | S35: 110 | U35: 90 | V35: 1.1023 | Z35: =IF(IF(D35="UNTUCA",IF(+((W35-3)*1.5+(X35-3)*3.1)>0,+((W35-3)*1.5+(X35-3)*3.1),0),IF(+((W35-3)*1.5+(X35-3)*3.1)>0,+((W35-3)*1.5+(X35-3)*3.1),0))<30,30,IF(D35="UNTUCA",IF(+((W35-3)*1.5+(X35-3)*3.1)>0,+((W35-3)*1.5+(X35-3)*3.1),0),IF(+((W35-3)*1.5+(X35-3)*3.1)>0,+((W35-3)*1.5+(X35-3)*3.1),0))) -> 30 | AA35: =+Y35+Z35 -> 30 | AB35: =+((O35*P35*(R35-U35)/100)-S35-AA35+T35)*V35 -> 183.99357 | AC35: =+(S35-T35)*V35-'data 1'!$F$4 -> 41.253 | AD35: =+(Q35-P35)*(R35-U35)*L35*V35/100 -> 24.825334 | AE35: =+(Y35*V35-70)+V35*(Z35-IF(D35="UNTUCA",IF(+((W35-3)*2.5+(X35-3)*3.1)>0,+((W35-3)*1.5+(X35-3)*3.1),0),IF(+((W35-3)*1.5+(X35-3)*3.1)>0,+((W35-3)*1.5+(X35-3)*3.1),0))) -> -36.931 | AF35: =(L35-O35)*(R35-U35)*Q35*V35/100 -> 61.196587 | AG35: =+IF(D35="RONALD WILLIAN GARIBAY ESCUDERO",AC35+AD35+AE35+AF35+70,AC35+AD35+AE35+AF35)+70-53 -> 107.34392 | AH35: =31.1035*L35*Q35*1.1023*K35/100 -> 3.4454502 | AI35: =+((+$AI$2-R35+U35)*L35*Q35*V35)/100 -> 42.576208 | AJ35: =31.1035*1.1023*K35*P35*O35/100 -> 2.7705632 | AL35: =+IF(AB35*K35>0,AB35*K35,0) -> 124.05767
A36: IP-1037 | B36: 45671 | C36: 45666 | D36: EXPLORACIONES CLAUDIA Y KAREN E.I.R.L. | E36: {=XLOOKUP(D36,RUC!$B$3:$B$79,RUC!$D$3:$D$79)} -> 20601620147 | G36: AGRANEL | H36: MINERAL | I36: 10.65 | J36: 11.1 | K36: =+I36-(I36*(J36/100)) -> 9.46785 | L36: 0.161 | M36: 0.151 | N36: 0.162 | O36: =+ROUND((M36+N36)/2,3) -> 0.157 | P36: 90 | Q36: 91.22 | R36: 2650.85 | S36: =IF((90+ROUNDDOWN(O36,1)*100)<95,95,(90+ROUNDDOWN(O36,1)*100)) -> 100 | U36: 90 | V36: 1.1023 | Z36: =IF(IF(D36="UNTUCA",IF(+((W36-3)*1.5+(X36-3)*3.1)>0,+((W36-3)*1.5+(X36-3)*3.1),0),IF(+((W36-3)*1.5+(X36-3)*3.1)>0,+((W36-3)*1.5+(X36-3)*3.1),0))<30,30,IF(D36="UNTUCA",IF(+((W36-3)*1.5+(X36-3)*3.1)>0,+((W36-3)*1.5+(X36-3)*3.1),0),IF(+((W36-3)*1.5+(X36-3)*3.1)>0,+((W36-3)*1.5+(X36-3)*3.1),0))) -> 30 | AA36: =+Y36+Z36 -> 30 | AB36: =+((O36*P36*(R36-U36)/100)-S36-AA36+T36)*V36 -> 255.56617 | AC36: =+(S36-T36)*V36-'data 1'!$F$4 -> 30.23 | AD36: =+(Q36-P36)*(R36-U36)*L36*V36/100 -> 5.5445928 | AE36: =+(Y36*V36-70)+V36*(Z36-IF(D36="UNTUCA",IF(+((W36-3)*2.5+(X36-3)*3.1)>0,+((W36-3)*1.5+(X36-3)*3.1),0),IF(+((W36-3)*1.5+(X36-3)*3.1)>0,+((W36-3)*1.5+(X36-3)*3.1),0))) -> -36.931 | AF36: =(L36-O36)*(R36-U36)*Q36*V36/100 -> 10.299924 | AG36: =+IF(D36="RONALD WILLIAN GARIBAY ESCUDERO",AC36+AD36+AE36+AF36+70,AC36+AD36+AE36+AF36)+70-53 -> 26.143516 | AH36: =31.1035*L36*Q36*1.1023*K36/100 -> 47.673428 | AI36: =+((+$AI$2-R36+U36)*L36*Q36*V36)/100 -> 41.953381 | AJ36: =31.1035*1.1023*K36*P36*O36/100 -> 45.867239 | AL36: =+IF(AB36*K36>0,AB36*K36,0) -> 2419.6621
A37: IP-1038 | B37: 45672 | C37: 45666 | D37: MINERA AURIFERA 2 DE DICIEMBRE CALPA RENACE S.A. | E37: {=XLOOKUP(D37,RUC!$B$3:$B$79,RUC!$D$3:$D$79)} -> #N/A | G37: 50 | H37: MINERAL | I37: 6.27 | J37: 1 | K37: =+I37-(I37*(J37/100)) -> 6.2073 | L37: 0.523 | M37: 0.502 | N37: 0.547 | O37: =+ROUND((M37+N37)/2,3) -> 0.525 | P37: 90 | Q37: 90.23 | R37: 2674.6 | S37: =IF((90+ROUNDDOWN(O37,1)*100)<95,95,(90+ROUNDDOWN(O37,1)*100))-5 -> 135 | U37: 90 | V37: 1.1023 | Z37: 25 | AA37: =+Y37+Z37 -> 25 | AB37: =+((O37*P37*(R37-U37)/100)-S37-AA37+T37)*V37 -> 1169.7867 | AC37: =+(S37-T37)*V37-'data 1'!$F$4 -> 68.8105 | AD37: =+(Q37-P37)*(R37-U37)*L37*V37/100 -> 3.4270676 | AE37: =+(Y37*V37-70)+V37*(Z37-IF(D37="UNTUCA",IF(+((W37-3)*2.5+(X37-3)*3.1)>0,+((W37-3)*1.5+(X37-3)*3.1),0),IF(+((W37-3)*1.5+(X37-3)*3.1)>0,+((W37-3)*1.5+(X37-3)*3.1),0))) -> -42.4425 | AF37: =(L37-O37)*(R37-U37)*Q37*V37/100 -> -5.1413137 | AG37: =+IF(D37="RONALD WILLIAN GARIBAY ESCUDERO",AC37+AD37+AE37+AF37+70,AC37+AD37+AE37+AF37)+70-30-5-3 -> 56.653754 | AH37: =31.1035*L37*Q37*1.1023*K37/100 -> 100.43023 | AI37: =+((+$AI$2-R37+U37)*L37*Q37*V37)/100 -> 122.45003 | AJ37: =31.1035*1.1023*K37*P37*O37/100 -> 100.5573 | AL37: =+IF(AB37*K37>0,AB37*K37,0) -> 7261.2168
A38: IP-1039 | B38: 45672 | C38: 45666 | D38: MINERA AURIFERA 2 DE DICIEMBRE CALPA RENACE S.A. | E38: {=XLOOKUP(D38,RUC!$B$3:$B$79,RUC!$D$3:$D$79)} -> #N/A | G38: 50 | H38: MINERAL | I38: 6.54 | J38: 0.95 | K38: =+I38-(I38*(J38/100)) -> 6.47787 | L38: 0.703 | M38: 0.674 | N38: 0.747 | O38: =+ROUND((M38+N38)/2,3) -> 0.711 | P38: 90 | Q38: 90.15 | R38: 2674.6 | S38: =IF((90+ROUNDDOWN(O38,1)*100)<95,95,(90+ROUNDDOWN(O38,1)*100))-5 -> 155 | U38: 90 | V38: 1.1023 | Z38: 25 | AA38: =+Y38+Z38 -> 25 | AB38: =+((O38*P38*(R38-U38)/100)-S38-AA38+T38)*V38 -> 1624.664 | AC38: =+(S38-T38)*V38-'data 1'!$F$4 -> 90.8565 | AD38: =+(Q38-P38)*(R38-U38)*L38*V38/100 -> 3.0042753 | AE38: =+(Y38*V38-70)+V38*(Z38-IF(D38="UNTUCA",IF(+((W38-3)*2.5+(X38-3)*3.1)>0,+((W38-3)*1.5+(X38-3)*3.1),0),IF(+((W38-3)*1.5+(X38-3)*3.1)>0,+((W38-3)*1.5+(X38-3)*3.1),0))) -> -42.4425 | AF38: =(L38-O38)*(R38-U38)*Q38*V38/100 -> -20.547021 | AG38: =+IF(D38="RONALD WILLIAN GARIBAY ESCUDERO",AC38+AD38+AE38+AF38+70,AC38+AD38+AE38+AF38)+70-30-5-3 -> 62.871254 | AH38: =31.1035*L38*Q38*1.1023*K38/100 -> 140.75452 | AI38: =+((+$AI$2-R38+U38)*L38*Q38*V38)/100 -> 164.44752 | AJ38: =31.1035*1.1023*K38*P38*O38/100 -> 142.11941 | AL38: =+IF(AB38*K38>0,AB38*K38,0) -> 10524.362
A39: IP-1040 | B39: 45672 | C39: 45666 | D39: MINERA AURIFERA 2 DE DICIEMBRE CALPA RENACE S.A. | E39: {=XLOOKUP(D39,RUC!$B$3:$B$79,RUC!$D$3:$D$79)} -> #N/A | G39: 50 | H39: MINERAL | I39: 6.92 | J39: 1 | K39: =+I39-(I39*(J39/100)) -> 6.8508 | L39: 0.712 | M39: 0.684 | N39: 0.684 | O39: =+ROUND((M39+N39)/2,3) -> 0.684 | P39: 90 | Q39: 90.09 | R39: 2674.6 | S39: =IF((90+ROUNDDOWN(O39,1)*100)<95,95,(90+ROUNDDOWN(O39,1)*100))-5 -> 145 | U39: 90 | V39: 1.1023 | Z39: 25 | AA39: =+Y39+Z39 -> 25 | AB39: =+((O39*P39*(R39-U39)/100)-S39-AA39+T39)*V39 -> 1566.4562 | AC39: =+(S39-T39)*V39-'data 1'!$F$4 -> 79.8335 | AD39: =+(Q39-P39)*(R39-U39)*L39*V39/100 -> 1.8256421 | AE39: =+(Y39*V39-70)+V39*(Z39-IF(D39="UNTUCA",IF(+((W39-3)*2.5+(X39-3)*3.1)>0,+((W39-3)*1.5+(X39-3)*3.1),0),IF(+((W39-3)*1.5+(X39-3)*3.1)>0,+((W39-3)*1.5+(X39-3)*3.1),0))) -> -42.4425 | AF39: =(L39-O39)*(R39-U39)*Q39*V39/100 -> 71.86671 | AG39: =+IF(D39="RONALD WILLIAN GARIBAY ESCUDERO",AC39+AD39+AE39+AF39+70,AC39+AD39+AE39+AF39)+70-30-5-3 -> 143.08335 | AH39: =31.1035*L39*Q39*1.1023*K39/100 -> 150.66311 | AI39: =+((+$AI$2-R39+U39)*L39*Q39*V39)/100 -> 166.44197 | AJ39: =31.1035*1.1023*K39*P39*O39/100 -> 144.59357 | AL39: =+IF(AB39*K39>0,AB39*K39,0) -> 10731.478
A40: IP-1041 | B40: 45672 | C40: 45666 | D40: MINERA AURIFERA 2 DE DICIEMBRE CALPA RENACE S.A. | E40: {=XLOOKUP(D40,RUC!$B$3:$B$79,RUC!$D$3:$D$79)} -> #N/A | G40: 50 | H40: MINERAL | I40: 6.49 | J40: 0.91 | K40: =+I40-(I40*(J40/100)) -> 6.430941 | L40: 0.738 | M40: 0.708 | N40: 0.708 | O40: =+ROUND((M40+N40)/2,3) -> 0.708 | P40: 90 | Q40: 90.28 | R40: 2674.6 | S40: =IF((90+ROUNDDOWN(O40,1)*100)<95,95,(90+ROUNDDOWN(O40,1)*100))-5 -> 155 | U40: 90 | V40: 1.1023 | Z40: 25 | AA40: =+Y40+Z40 -> 25 | AB40: =+((O40*P40*(R40-U40)/100)-S40-AA40+T40)*V40 -> 1616.9717 | AC40: =+(S40-T40)*V40-'data 1'!$F$4 -> 90.8565 | AD40: =+(Q40-P40)*(R40-U40)*L40*V40/100 -> 5.8871831 | AE40: =+(Y40*V40-70)+V40*(Z40-IF(D40="UNTUCA",IF(+((W40-3)*2.5+(X40-3)*3.1)>0,+((W40-3)*1.5+(X40-3)*3.1),0),IF(+((W40-3)*1.5+(X40-3)*3.1)>0,+((W40-3)*1.5+(X40-3)*3.1),0))) -> -42.4425 | AF40: =(L40-O40)*(R40-U40)*Q40*V40/100 -> 77.16244 | AG40: =+IF(D40="RONALD WILLIAN GARIBAY ESCUDERO",AC40+AD40+AE40+AF40+70,AC40+AD40+AE40+AF40)+70-30-5-3 -> 163.46362 | AH40: =31.1035*L40*Q40*1.1023*K40/100 -> 146.90328 | AI40: =+((+$AI$2-R40+U40)*L40*Q40*V40)/100 -> 172.88375 | AJ40: =31.1035*1.1023*K40*P40*O40/100 -> 140.49451 | AL40: =+IF(AB40*K40>0,AB40*K40,0) -> 10398.65
A41: IP-1042 | B41: 45672 | C41: 45666 | D41: MINERA AURIFERA 2 DE DICIEMBRE CALPA RENACE S.A. | E41: {=XLOOKUP(D41,RUC!$B$3:$B$79,RUC!$D$3:$D$79)} -> #N/A | G41: 50 | H41: MINERAL | I41: 6.97 | J41: 0.87 | K41: =+I41-(I41*(J41/100)) -> 6.909361 | L41: 0.725 | M41: 0.696 | N41: 0.771 | O41: =+ROUND((M41+N41)/2,3) -> 0.734 | P41: 90 | Q41: 90.17 | R41: 2674.6 | S41: =IF((90+ROUNDDOWN(O41,1)*100)<95,95,(90+ROUNDDOWN(O41,1)*100))-5 -> 155 | U41: 90 | V41: 1.1023 | Z41: 25 | AA41: =+Y41+Z41 -> 25 | AB41: =+((O41*P41*(R41-U41)/100)-S41-AA41+T41)*V41 -> 1683.6384 | AC41: =+(S41-T41)*V41-'data 1'!$F$4 -> 90.8565 | AD41: =+(Q41-P41)*(R41-U41)*L41*V41/100 -> 3.5113981 | AE41: =+(Y41*V41-70)+V41*(Z41-IF(D41="UNTUCA",IF(+((W41-3)*2.5+(X41-3)*3.1)>0,+((W41-3)*1.5+(X41-3)*3.1),0),IF(+((W41-3)*1.5+(X41-3)*3.1)>0,+((W41-3)*1.5+(X41-3)*3.1),0))) -> -42.4425 | AF41: =(L41-O41)*(R41-U41)*Q41*V41/100 -> -23.120527 | AG41: =+IF(D41="RONALD WILLIAN GARIBAY ESCUDERO",AC41+AD41+AE41+AF41+70,AC41+AD41+AE41+AF41)+70-30-5-3 -> 60.804871 | AH41: =31.1035*L41*Q41*1.1023*K41/100 -> 154.86277 | AI41: =+((+$AI$2-R41+U41)*L41*Q41*V41)/100 -> 169.63144 | AJ41: =31.1035*1.1023*K41*P41*O41/100 -> 156.48962 | AL41: =+IF(AB41*K41>0,AB41*K41,0) -> 11632.866
A42: IP-1043 | B42: 45672 | C42: 45666 | D42: MINERA AURIFERA 2 DE DICIEMBRE CALPA RENACE S.A. | E42: {=XLOOKUP(D42,RUC!$B$3:$B$79,RUC!$D$3:$D$79)} -> #N/A | G42: 50 | H42: MINERAL | I42: 6.95 | J42: 0.93 | K42: =+I42-(I42*(J42/100)) -> 6.885365 | L42: 0.934 | M42: 0.897 | N42: 0.958 | O42: =+ROUND((M42+N42)/2,3) -> 0.928 | P42: 90 | Q42: 90.21 | R42: 2674.6 | S42: =IF((90+ROUNDDOWN(O42,1)*100)<95,95,(90+ROUNDDOWN(O42,1)*100))-5 -> 175 | U42: 90 | V42: 1.1023 | Z42: 25 | AA42: =+Y42+Z42 -> 25 | AB42: =+((O42*P42*(R42-U42)/100)-S42-AA42+T42)*V42 -> 2159.0286 | AC42: =+(S42-T42)*V42-'data 1'!$F$4 -> 112.9025 | AD42: =+(Q42-P42)*(R42-U42)*L42*V42/100 -> 5.5880376 | AE42: =+(Y42*V42-70)+V42*(Z42-IF(D42="UNTUCA",IF(+((W42-3)*2.5+(X42-3)*3.1)>0,+((W42-3)*1.5+(X42-3)*3.1),0),IF(+((W42-3)*1.5+(X42-3)*3.1)>0,+((W42-3)*1.5+(X42-3)*3.1),0))) -> -42.4425 | AF42: =(L42-O42)*(R42-U42)*Q42*V42/100 -> 15.420522 | AG42: =+IF(D42="RONALD WILLIAN GARIBAY ESCUDERO",AC42+AD42+AE42+AF42+70,AC42+AD42+AE42+AF42)+70-30-5-3 -> 123.46856 | AH42: =31.1035*L42*Q42*1.1023*K42/100 -> 198.90129 | AI42: =+((+$AI$2-R42+U42)*L42*Q42*V42)/100 -> 218.62903 | AJ42: =31.1035*1.1023*K42*P42*O42/100 -> 197.1635 | AL42: =+IF(AB42*K42>0,AB42*K42,0) -> 14865.7
A43: IP-1044 | B43: 45672 | C43: 45666 | D43: MINERA AURIFERA 2 DE DICIEMBRE CALPA RENACE S.A. | E43: {=XLOOKUP(D43,RUC!$B$3:$B$79,RUC!$D$3:$D$79)} -> #N/A | G43: 50 | H43: MINERAL | I43: 6.51 | J43: 0.95 | K43: =+I43-(I43*(J43/100)) -> 6.448155 | L43: 0.572 | M43: 0.549 | N43: 0.549 | O43: =+ROUND((M43+N43)/2,3) -> 0.549 | P43: 90 | Q43: 90.07 | R43: 2674.6 | S43: =IF((90+ROUNDDOWN(O43,1)*100)<95,95,(90+ROUNDDOWN(O43,1)*100))-5 -> 135 | U43: 90 | V43: 1.1023 | Z43: 25 | AA43: =+Y43+Z43 -> 25 | AB43: =+((O43*P43*(R43-U43)/100)-S43-AA43+T43)*V43 -> 1231.3252 | AC43: =+(S43-T43)*V43-'data 1'!$F$4 -> 68.8105 | AD43: =+(Q43-P43)*(R43-U43)*L43*V43/100 -> 1.1407414 | AE43: =+(Y43*V43-70)+V43*(Z43-IF(D43="UNTUCA",IF(+((W43-3)*2.5+(X43-3)*3.1)>0,+((W43-3)*1.5+(X43-3)*3.1),0),IF(+((W43-3)*1.5+(X43-3)*3.1)>0,+((W43-3)*1.5+(X43-3)*3.1),0))) -> -42.4425 | AF43: =(L43-O43)*(R43-U43)*Q43*V43/100 -> 59.020264 | AG43: =+IF(D43="RONALD WILLIAN GARIBAY ESCUDERO",AC43+AD43+AE43+AF43+70,AC43+AD43+AE43+AF43)+70-30-5-3 -> 118.52901 | AH43: =31.1035*L43*Q43*1.1023*K43/100 -> 113.89921 | AI43: =+((+$AI$2-R43+U43)*L43*Q43*V43)/100 -> 133.68493 | AJ43: =31.1035*1.1023*K43*P43*O43/100 -> 109.23439 | AL43: =+IF(AB43*K43>0,AB43*K43,0) -> 7939.7755
A44: IP-1045 | B44: 45672 | C44: 45666 | D44: MINERA AURIFERA 2 DE DICIEMBRE CALPA RENACE S.A. | E44: {=XLOOKUP(D44,RUC!$B$3:$B$79,RUC!$D$3:$D$79)} -> #N/A | G44: 50 | H44: MINERAL | I44: 5.48 | J44: 1 | K44: =+I44-(I44*(J44/100)) -> 5.4252 | L44: 0.52 | M44: 0.499 | N44: 0.541 | O44: =+ROUND((M44+N44)/2,3) -> 0.52 | P44: 90 | Q44: 90.3 | R44: 2674.6 | S44: =IF((90+ROUNDDOWN(O44,1)*100)<95,95,(90+ROUNDDOWN(O44,1)*100))-5 -> 135 | U44: 90 | V44: 1.1023 | Z44: 25 | AA44: =+Y44+Z44 -> 25 | AB44: =+((O44*P44*(R44-U44)/100)-S44-AA44+T44)*V44 -> 1156.9661 | AC44: =+(S44-T44)*V44-'data 1'!$F$4 -> 68.8105 | AD44: =+(Q44-P44)*(R44-U44)*L44*V44/100 -> 4.4444471 | AE44: =+(Y44*V44-70)+V44*(Z44-IF(D44="UNTUCA",IF(+((W44-3)*2.5+(X44-3)*3.1)>0,+((W44-3)*1.5+(X44-3)*3.1),0),IF(+((W44-3)*1.5+(X44-3)*3.1)>0,+((W44-3)*1.5+(X44-3)*3.1),0))) -> -42.4425 | AF44: =(L44-O44)*(R44-U44)*Q44*V44/100 -> 0 | AG44: =+IF(D44="RONALD WILLIAN GARIBAY ESCUDERO",AC44+AD44+AE44+AF44+70,AC44+AD44+AE44+AF44)+70-30-5-3 -> 62.812447 | AH44: =31.1035*L44*Q44*1.1023*K44/100 -> 87.340549 | AI44: =+((+$AI$2-R44+U44)*L44*Q44*V44)/100 -> 121.8421 | AJ44: =31.1035*1.1023*K44*P44*O44/100 -> 87.050381 | AL44: =+IF(AB44*K44>0,AB44*K44,0) -> 6276.7727
A45: IP-1046 | B45: 45670 | C45: 45667 | D45: MELCHOR AGUSTIN VERA PACHECO | E45: {=XLOOKUP(D45,RUC!$B$3:$B$79,RUC!$D$3:$D$79)} -> 10082235774 | G45: 50 | H45: MINERAL | I45: 6.3 | J45: 1.7 | K45: =+I45-(I45*(J45/100)) -> 6.1929 | L45: 0.25 | M45: 0.246 | N45: 0.246 | O45: =+ROUND((M45+N45)/2,3) -> 0.246 | P45: 85 | Q45: 90.25 | R45: 2687.45 | S45: 105 | U45: 80 | V45: 1.1023 | Z45: 10 | AA45: =+Y45+Z45 -> 10 | AB45: =+((O45*P45*(R45-U45)/100)-S45-AA45+T45)*V45 -> 474.22908 | AC45: =+(S45-T45)*V45-'data 1'!$F$4 -> 35.7415 | AD45: =+(Q45-P45)*(R45-U45)*L45*V45/100 -> 37.723772 | AE45: =+(Y45*V45-70)+V45*(Z45-IF(D45="UNTUCA",IF(+((W45-3)*2.5+(X45-3)*3.1)>0,+((W45-3)*1.5+(X45-3)*3.1),0),IF(+((W45-3)*1.5+(X45-3)*3.1)>0,+((W45-3)*1.5+(X45-3)*3.1),0))) -> -58.977 | AF45: =(L45-O45)*(R45-U45)*Q45*V45/100 -> 10.375834 | AG45: =+IF(D45="RONALD WILLIAN GARIBAY ESCUDERO",AC45+AD45+AE45+AF45+70,AC45+AD45+AE45+AF45)+70 -> 94.864105 | AH45: =31.1035*L45*Q45*1.1023*K45/100 -> 47.906049 | AI45: =+((+$AI$2-R45+U45)*L45*Q45*V45)/100 -> 52.862553 | AJ45: =31.1035*1.1023*K45*P45*O45/100 -> 44.397362 | AL45: =+IF(AB45*K45>0,AB45*K45,0) -> 2936.8532
A46: IP-1047 | B46: 45670 | C46: 45667 | D46: MELCHOR AGUSTIN VERA PACHECO | E46: {=XLOOKUP(D46,RUC!$B$3:$B$79,RUC!$D$3:$D$79)} -> 10082235774 | G46: 50 | H46: MINERAL | I46: 5.1 | J46: 1.8 | K46: =+I46-(I46*(J46/100)) -> 5.0082 | L46: 0.61 | M46: 0.601 | N46: 0.601 | O46: =+ROUND((M46+N46)/2,3) -> 0.601 | P46: 90 | Q46: 90.16 | R46: 2687.45 | S46: 125 | U46: 80 | V46: 1.1023 | Z46: 10 | AA46: =+Y46+Z46 -> 10 | AB46: =+((O46*P46*(R46-U46)/100)-S46-AA46+T46)*V46 -> 1405.84 | AC46: =+(S46-T46)*V46-'data 1'!$F$4 -> 57.7875 | AD46: =+(Q46-P46)*(R46-U46)*L46*V46/100 -> 2.8052115 | AE46: =+(Y46*V46-70)+V46*(Z46-IF(D46="UNTUCA",IF(+((W46-3)*2.5+(X46-3)*3.1)>0,+((W46-3)*1.5+(X46-3)*3.1),0),IF(+((W46-3)*1.5+(X46-3)*3.1)>0,+((W46-3)*1.5+(X46-3)*3.1),0))) -> -58.977 | AF46: =(L46-O46)*(R46-U46)*Q46*V46/100 -> 23.322345 | AG46: =+IF(D46="RONALD WILLIAN GARIBAY ESCUDERO",AC46+AD46+AE46+AF46+70,AC46+AD46+AE46+AF46)+70 -> 94.938056 | AH46: =31.1035*L46*Q46*1.1023*K46/100 -> 94.435323 | AI46: =+((+$AI$2-R46+U46)*L46*Q46*V46)/100 -> 128.856 | AJ46: =31.1035*1.1023*K46*P46*O46/100 -> 92.876901 | AL46: =+IF(AB46*K46>0,AB46*K46,0) -> 7040.728
A47: IP-1048 | B47: 45670 | C47: 45667 | D47: MELCHOR AGUSTIN VERA PACHECO | E47: {=XLOOKUP(D47,RUC!$B$3:$B$79,RUC!$D$3:$D$79)} -> 10082235774 | G47: 50 | H47: MINERAL | I47: 4.67 | J47: 1.9 | K47: =+I47-(I47*(J47/100)) -> 4.58127 | L47: 0.274 | M47: 0.269 | N47: 0.269 | O47: =+ROUND((M47+N47)/2,3) -> 0.269 | P47: 90 | Q47: 89.88 | R47: 2687.45 | S47: 105 | U47: 80 | V47: 1.1023 | Z47: 10 | AA47: =+Y47+Z47 -> 10 | AB47: =+((O47*P47*(R47-U47)/100)-S47-AA47+T47)*V47 -> 569.07742 | AC47: =+(S47-T47)*V47-'data 1'!$F$4 -> 35.7415 | AD47: =+(Q47-P47)*(R47-U47)*L47*V47/100 -> -0.94503437 | AE47: =+(Y47*V47-70)+V47*(Z47-IF(D47="UNTUCA",IF(+((W47-3)*2.5+(X47-3)*3.1)>0,+((W47-3)*1.5+(X47-3)*3.1),0),IF(+((W47-3)*1.5+(X47-3)*3.1)>0,+((W47-3)*1.5+(X47-3)*3.1),0))) -> -58.977 | AF47: =(L47-O47)*(R47-U47)*Q47*V47/100 -> 12.916619 | AG47: =+IF(D47="RONALD WILLIAN GARIBAY ESCUDERO",AC47+AD47+AE47+AF47+70,AC47+AD47+AE47+AF47)+70 -> 58.736085 | AH47: =31.1035*L47*Q47*1.1023*K47/100 -> 38.68197 | AI47: =+((+$AI$2-R47+U47)*L47*Q47*V47)/100 -> 57.699831 | AJ47: =31.1035*1.1023*K47*P47*O47/100 -> 38.026797 | AL47: =+IF(AB47*K47>0,AB47*K47,0) -> 2607.0973
A48: IP-1049 | B48: 45670 | C48: 45667 | D48: MELCHOR AGUSTIN VERA PACHECO | E48: {=XLOOKUP(D48,RUC!$B$3:$B$79,RUC!$D$3:$D$79)} -> 10082235774 | G48: 50 | H48: MINERAL | I48: 8.29 | J48: 1.7 | K48: =+I48-(I48*(J48/100)) -> 8.14907 | L48: 0.147 | M48: 0.144 | N48: 0.144 | O48: =+ROUND((M48+N48)/2,3) -> 0.144 | P48: 85 | Q48: 89.46 | R48: 2687.45 | S48: 95 | U48: 80 | V48: 1.1023 | Z48: 10 | AA48: =+Y48+Z48 -> 10 | AB48: =+((O48*P48*(R48-U48)/100)-S48-AA48+T48)*V48 -> 236.05962 | AC48: =+(S48-T48)*V48-'data 1'!$F$4 -> 24.7185 | AD48: =+(Q48-P48)*(R48-U48)*L48*V48/100 -> 18.843778 | AE48: =+(Y48*V48-70)+V48*(Z48-IF(D48="UNTUCA",IF(+((W48-3)*2.5+(X48-3)*3.1)>0,+((W48-3)*1.5+(X48-3)*3.1),0),IF(+((W48-3)*1.5+(X48-3)*3.1)>0,+((W48-3)*1.5+(X48-3)*3.1),0))) -> -58.977 | AF48: =(L48-O48)*(R48-U48)*Q48*V48/100 -> 7.7137569 | AG48: =+IF(D48="RONALD WILLIAN GARIBAY ESCUDERO",AC48+AD48+AE48+AF48+70,AC48+AD48+AE48+AF48)+70 -> 62.299035 | AH48: =31.1035*L48*Q48*1.1023*K48/100 -> 36.742047 | AI48: =+((+$AI$2-R48+U48)*L48*Q48*V48)/100 -> 30.811096 | AJ48: =31.1035*1.1023*K48*P48*O48/100 -> 34.197829 | AL48: =+IF(AB48*K48>0,AB48*K48,0) -> 1923.6663
A49: IP-1050 | B49: 45670 | C49: 45667 | D49: MELCHOR AGUSTIN VERA PACHECO | E49: {=XLOOKUP(D49,RUC!$B$3:$B$79,RUC!$D$3:$D$79)} -> 10082235774 | G49: 50 | H49: MINERAL | I49: 5.68 | J49: 1.6 | K49: =+I49-(I49*(J49/100)) -> 5.58912 | L49: 0.343 | M49: 0.337 | N49: 0.377 | O49: =+ROUND((M49+N49)/2,3) -> 0.357 | P49: 90 | Q49: 90.16 | R49: 2687.45 | S49: 110 | U49: 80 | V49: 1.1023 | Z49: 10 | AA49: =+Y49+Z49 -> 10 | AB49: =+((O49*P49*(R49-U49)/100)-S49-AA49+T49)*V49 -> 791.20193 | AC49: =+(S49-T49)*V49-'data 1'!$F$4 -> 41.253 | AD49: =+(Q49-P49)*(R49-U49)*L49*V49/100 -> 1.5773566 | AE49: =+(Y49*V49-70)+V49*(Z49-IF(D49="UNTUCA",IF(+((W49-3)*2.5+(X49-3)*3.1)>0,+((W49-3)*1.5+(X49-3)*3.1),0),IF(+((W49-3)*1.5+(X49-3)*3.1)>0,+((W49-3)*1.5+(X49-3)*3.1),0))) -> -58.977 | AF49: =(L49-O49)*(R49-U49)*Q49*V49/100 -> -36.279203 | AG49: =+IF(D49="RONALD WILLIAN GARIBAY ESCUDERO",AC49+AD49+AE49+AF49+70,AC49+AD49+AE49+AF49)+70 -> 17.574154 | AH49: =31.1035*L49*Q49*1.1023*K49/100 -> 59.259847 | AI49: =+((+$AI$2-R49+U49)*L49*Q49*V49)/100 -> 72.455097 | AJ49: =31.1035*1.1023*K49*P49*O49/100 -> 61.56916 | AL49: =+IF(AB49*K49>0,AB49*K49,0) -> 4422.1225
A50: IP-1051 | B50: 45670 | C50: 45667 | D50: MELCHOR AGUSTIN VERA PACHECO | E50: {=XLOOKUP(D50,RUC!$B$3:$B$79,RUC!$D$3:$D$79)} -> 10082235774 | G50: 50 | H50: MINERAL | I50: 4.23 | J50: 1.8 | K50: =+I50-(I50*(J50/100)) -> 4.15386 | L50: 0.22 | M50: 0.217 | N50: 0.217 | O50: =+ROUND((M50+N50)/2,3) -> 0.217 | P50: 85 | Q50: 90.3 | R50: 2687.45 | S50: 105 | U50: 80 | V50: 1.1023 | Z50: 10 | AA50: =+Y50+Z50 -> 10 | AB50: =+((O50*P50*(R50-U50)/100)-S50-AA50+T50)*V50 -> 403.38024 | AC50: =+(S50-T50)*V50-'data 1'!$F$4 -> 35.7415 | AD50: =+(Q50-P50)*(R50-U50)*L50*V50/100 -> 33.51308 | AE50: =+(Y50*V50-70)+V50*(Z50-IF(D50="UNTUCA",IF(+((W50-3)*2.5+(X50-3)*3.1)>0,+((W50-3)*1.5+(X50-3)*3.1),0),IF(+((W50-3)*1.5+(X50-3)*3.1)>0,+((W50-3)*1.5+(X50-3)*3.1),0))) -> -58.977 | AF50: =(L50-O50)*(R50-U50)*Q50*V50/100 -> 7.7861865 | AG50: =+IF(D50="RONALD WILLIAN GARIBAY ESCUDERO",AC50+AD50+AE50+AF50+70,AC50+AD50+AE50+AF50)+70 -> 88.063767 | AH50: =31.1035*L50*Q50*1.1023*K50/100 -> 28.292502 | AI50: =+((+$AI$2-R50+U50)*L50*Q50*V50)/100 -> 46.544819 | AJ50: =31.1035*1.1023*K50*P50*O50/100 -> 26.268761 | AL50: =+IF(AB50*K50>0,AB50*K50,0) -> 1675.585
A51: IP-1052 | B51: 45670 | C51: 45667 | D51: MELCHOR AGUSTIN VERA PACHECO | E51: {=XLOOKUP(D51,RUC!$B$3:$B$79,RUC!$D$3:$D$79)} -> 10082235774 | G51: 50 | H51: MINERAL | I51: 5.79 | J51: 1.9 | K51: =+I51-(I51*(J51/100)) -> 5.67999 | L51: 0.345 | M51: 0.34 | N51: 0.34 | O51: =+ROUND((M51+N51)/2,3) -> 0.34 | P51: 90 | Q51: 89.89 | R51: 2687.45 | S51: 110 | U51: 80 | V51: 1.1023 | Z51: 10 | AA51: =+Y51+Z51 -> 10 | AB51: =+((O51*P51*(R51-U51)/100)-S51-AA51+T51)*V51 -> 747.22679 | AC51: =+(S51-T51)*V51-'data 1'!$F$4 -> 41.253 | AD51: =+(Q51-P51)*(R51-U51)*L51*V51/100 -> -1.0907559 | AE51: =+(Y51*V51-70)+V51*(Z51-IF(D51="UNTUCA",IF(+((W51-3)*2.5+(X51-3)*3.1)>0,+((W51-3)*1.5+(X51-3)*3.1),0),IF(+((W51-3)*1.5+(X51-3)*3.1)>0,+((W51-3)*1.5+(X51-3)*3.1),0))) -> -58.977 | AF51: =(L51-O51)*(R51-U51)*Q51*V51/100 -> 12.918057 | AG51: =+IF(D51="RONALD WILLIAN GARIBAY ESCUDERO",AC51+AD51+AE51+AF51+70,AC51+AD51+AE51+AF51)+70 -> 64.103301 | AH51: =31.1035*L51*Q51*1.1023*K51/100 -> 60.393071 | AI51: =+((+$AI$2-R51+U51)*L51*Q51*V51)/100 -> 72.659331 | AJ51: =31.1035*1.1023*K51*P51*O51/100 -> 59.590642 | AL51: =+IF(AB51*K51>0,AB51*K51,0) -> 4244.2407
A52: IP-1053 | B52: 45670 | C52: 45667 | D52: LIMBER EDISON MONTALVO QUISPE | E52: {=XLOOKUP(D52,RUC!$B$3:$B$79,RUC!$D$3:$D$79)} -> 10479968131 | G52: 50 | H52: LLAMPO | I52: 3.7 | J52: 14.45 | K52: =+I52-(I52*(J52/100)) -> 3.16535 | L52: 0.511 | M52: 0.5 | N52: 0.5 | O52: =+ROUND((M52+N52)/2,3) -> 0.5 | P52: 90 | Q52: 90.24 | R52: 2687.45 | S52: =IF((90+ROUNDDOWN(O52,1)*100)<95,95,(90+ROUNDDOWN(O52,1)*100)) -> 140 | U52: 120 | V52: 1.1023 | Z52: 25 | AA52: =+Y52+Z52 -> 25 | AB52: =+((O52*P52*(R52-U52)/100)-S52-AA52+T52)*V52 -> 1091.6656 | AC52: =+(S52-T52)*V52-'data 1'!$F$4 -> 74.322 | AD52: =+(Q52-P52)*(R52-U52)*L52*V52/100 -> 3.4708348 | AE52: =+(Y52*V52-70)+V52*(Z52-IF(D52="UNTUCA",IF(+((W52-3)*2.5+(X52-3)*3.1)>0,+((W52-3)*1.5+(X52-3)*3.1),0),IF(+((W52-3)*1.5+(X52-3)*3.1)>0,+((W52-3)*1.5+(X52-3)*3.1),0))) -> -42.4425 | AF52: =(L52-O52)*(R52-U52)*Q52*V52/100 -> 28.092706 | AG52: =+IF(D52="RONALD WILLIAN GARIBAY ESCUDERO",AC52+AD52+AE52+AF52+70,AC52+AD52+AE52+AF52)+70-53 -> 80.443041 | AH52: =31.1035*L52*Q52*1.1023*K52/100 -> 50.043859 | AI52: =+((+$AI$2-R52+U52)*L52*Q52*V52)/100 -> 128.37107 | AJ52: =31.1035*1.1023*K52*P52*O52/100 -> 48.836364 | AL52: =+IF(AB52*K52>0,AB52*K52,0) -> 3455.5036
A53: IP-1054 | B53: 45669 | C53: 45667 | D53: LIMBER EDISON MONTALVO QUISPE | E53: {=XLOOKUP(D53,RUC!$B$3:$B$79,RUC!$D$3:$D$79)} -> 10479968131 | G53: 50 | H53: LLAMPO | I53: 3.76 | J53: 15.77 | K53: =+I53-(I53*(J53/100)) -> 3.167048 | L53: 0.944 | M53: 0.906 | N53: 0.906 | O53: =+ROUND((M53+N53)/2,3) -> 0.906 | P53: 90 | Q53: 90.11 | R53: 2687.45 | S53: =IF((90+ROUNDDOWN(O53,1)*100)<95,95,(90+ROUNDDOWN(O53,1)*100)) -> 180 | U53: 120 | V53: 1.1023 | Z53: 25 | AA53: =+Y53+Z53 -> 25 | AB53: =+((O53*P53*(R53-U53)/100)-S53-AA53+T53)*V53 -> 2081.6921 | AC53: =+(S53-T53)*V53-'data 1'!$F$4 -> 118.414 | AD53: =+(Q53-P53)*(R53-U53)*L53*V53/100 -> 2.938776 | AE53: =+(Y53*V53-70)+V53*(Z53-IF(D53="UNTUCA",IF(+((W53-3)*2.5+(X53-3)*3.1)>0,+((W53-3)*1.5+(X53-3)*3.1),0),IF(+((W53-3)*1.5+(X53-3)*3.1)>0,+((W53-3)*1.5+(X53-3)*3.1),0))) -> -42.4425 | AF53: =(L53-O53)*(R53-U53)*Q53*V53/100 -> 96.907723 | AG53: =+IF(D53="RONALD WILLIAN GARIBAY ESCUDERO",AC53+AD53+AE53+AF53+70,AC53+AD53+AE53+AF53)+70-53 -> 192.818 | AH53: =31.1035*L53*Q53*1.1023*K53/100 -> 92.365269 | AI53: =+((+$AI$2-R53+U53)*L53*Q53*V53)/100 -> 236.80571 | AJ53: =31.1035*1.1023*K53*P53*O53/100 -> 88.538961 | AL53: =+IF(AB53*K53>0,AB53*K53,0) -> 6592.819
A54: IP-1055 | B54: 45669 | C54: 45667 | D54: LIMBER EDISON MONTALVO QUISPE | E54: {=XLOOKUP(D54,RUC!$B$3:$B$79,RUC!$D$3:$D$79)} -> 10479968131 | G54: 49 | H54: LLAMPO | I54: 3.67 | J54: 19.07 | K54: =+I54-(I54*(J54/100)) -> 2.970131 | L54: 0.134 | M54: 0.128 | N54: 0.128 | O54: =+ROUND((M54+N54)/2,3) -> 0.128 | P54: 85 | Q54: 89.81 | R54: 2687.45 | S54: =IF((90+ROUNDDOWN(O54,1)*100)<95,95,(90+ROUNDDOWN(O54,1)*100)) -> 100 | U54: 100 | V54: 1.1023 | Z54: 25 | AA54: =+Y54+Z54 -> 25 | AB54: =+((O54*P54*(R54-U54)/100)-S54-AA54+T54)*V54 -> 172.526 | AC54: =+(S54-T54)*V54-'data 1'!$F$4 -> 30.23 | AD54: =+(Q54-P54)*(R54-U54)*L54*V54/100 -> 18.383223 | AE54: =+(Y54*V54-70)+V54*(Z54-IF(D54="UNTUCA",IF(+((W54-3)*2.5+(X54-3)*3.1)>0,+((W54-3)*1.5+(X54-3)*3.1),0),IF(+((W54-3)*1.5+(X54-3)*3.1)>0,+((W54-3)*1.5+(X54-3)*3.1),0))) -> -42.4425 | AF54: =(L54-O54)*(R54-U54)*Q54*V54/100 -> 15.369075 | AG54: =+IF(D54="RONALD WILLIAN GARIBAY ESCUDERO",AC54+AD54+AE54+AF54+70,AC54+AD54+AE54+AF54)+70-53 -> 38.539797 | AH54: =31.1035*L54*Q54*1.1023*K54/100 -> 12.255024 | AI54: =+((+$AI$2-R54+U54)*L54*Q54*V54)/100 -> 30.849324 | AJ54: =31.1035*1.1023*K54*P54*O54/100 -> 11.079332 | AL54: =+IF(AB54*K54>0,AB54*K54,0) -> 512.42482
A55: IP-1056 | B55: 45674 | C55: 45668 | D55: MINERA AURIFERA 2 DE DICIEMBRE CALPA RENACE S.A. | E55: {=XLOOKUP(D55,RUC!$B$3:$B$79,RUC!$D$3:$D$79)} -> #N/A | G55: 50 | H55: MINERAL | I55: 6.91 | J55: 1 | K55: =+I55-(I55*(J55/100)) -> 6.8409 | L55: 0.618 | M55: 0.593 | N55: 0.593 | O55: =+ROUND((M55+N55)/2,3) -> 0.593 | P55: 90 | Q55: 90.19 | R55: 2687.45 | S55: =IF((90+ROUNDDOWN(O55,1)*100)<95,95,(90+ROUNDDOWN(O55,1)*100))-5 -> 135 | U55: 90 | V55: 1.1023 | Z55: 25 | AA55: =+Y55+Z55 -> 25 | AB55: =+((O55*P55*(R55-U55)/100)-S55-AA55+T55)*V55 -> 1351.7054 | AC55: =+(S55-T55)*V55-'data 1'!$F$4 -> 68.8105 | AD55: =+(Q55-P55)*(R55-U55)*L55*V55/100 -> 3.3619332 | AE55: =+(Y55*V55-70)+V55*(Z55-IF(D55="UNTUCA",IF(+((W55-3)*2.5+(X55-3)*3.1)>0,+((W55-3)*1.5+(X55-3)*3.1),0),IF(+((W55-3)*1.5+(X55-3)*3.1)>0,+((W55-3)*1.5+(X55-3)*3.1),0))) -> -42.4425 | AF55: =(L55-O55)*(R55-U55)*Q55*V55/100 -> 64.557306 | AG55: =+IF(D55="RONALD WILLIAN GARIBAY ESCUDERO",AC55+AD55+AE55+AF55+70,AC55+AD55+AE55+AF55)+70-53 -> 111.28724 | AH55: =31.1035*L55*Q55*1.1023*K55/100 -> 130.72817 | AI55: =+((+$AI$2-R55+U55)*L55*Q55*V55)/100 -> 136.73329 | AJ55: =31.1035*1.1023*K55*P55*O55/100 -> 125.17555 | AL55: =+IF(AB55*K55>0,AB55*K55,0) -> 9246.8812
A56: IP-1057 | B56: 45674 | C56: 45668 | D56: MINERA AURIFERA 2 DE DICIEMBRE CALPA RENACE S.A. | E56: {=XLOOKUP(D56,RUC!$B$3:$B$79,RUC!$D$3:$D$79)} -> #N/A | G56: 50 | H56: MINERAL | I56: 6.42 | J56: 1.1 | K56: =+I56-(I56*(J56/100)) -> 6.34938 | L56: 0.68 | M56: 0.652 | N56: 0.652 | O56: =+ROUND((M56+N56)/2,3) -> 0.652 | P56: 90 | Q56: 89.96 | R56: 2687.45 | S56: =IF((90+ROUNDDOWN(O56,1)*100)<95,95,(90+ROUNDDOWN(O56,1)*100))-5 -> 145 | U56: 90 | V56: 1.1023 | Z56: 25 | AA56: =+Y56+Z56 -> 25 | AB56: =+((O56*P56*(R56-U56)/100)-S56-AA56+T56)*V56 -> 1492.7166 | AC56: =+(S56-T56)*V56-'data 1'!$F$4 -> 79.8335 | AD56: =+(Q56-P56)*(R56-U56)*L56*V56/100 -> -0.778782 | AE56: =+(Y56*V56-70)+V56*(Z56-IF(D56="UNTUCA",IF(+((W56-3)*2.5+(X56-3)*3.1)>0,+((W56-3)*1.5+(X56-3)*3.1),0),IF(+((W56-3)*1.5+(X56-3)*3.1)>0,+((W56-3)*1.5+(X56-3)*3.1),0))) -> -42.4425 | AF56: =(L56-O56)*(R56-U56)*Q56*V56/100 -> 72.119795 | AG56: =+IF(D56="RONALD WILLIAN GARIBAY ESCUDERO",AC56+AD56+AE56+AF56+70,AC56+AD56+AE56+AF56)+70-53 -> 125.73201 | AH56: =31.1035*L56*Q56*1.1023*K56/100 -> 133.16765 | AI56: =+((+$AI$2-R56+U56)*L56*Q56*V56)/100 -> 150.0672 | AJ56: =31.1035*1.1023*K56*P56*O56/100 -> 127.74105 | AL56: =+IF(AB56*K56>0,AB56*K56,0) -> 9477.8252
A57: IP-1058 | B57: 45674 | C57: 45668 | D57: MINERA AURIFERA 2 DE DICIEMBRE CALPA RENACE S.A. | E57: {=XLOOKUP(D57,RUC!$B$3:$B$79,RUC!$D$3:$D$79)} -> #N/A | G57: 50 | H57: MINERAL | I57: 6.64 | J57: 1.2 | K57: =+I57-(I57*(J57/100)) -> 6.56032 | L57: 0.614 | M57: 0.589 | N57: 0.589 | O57: =+ROUND((M57+N57)/2,3) -> 0.589 | P57: 90 | Q57: 90.16 | R57: 2687.45 | S57: =IF((90+ROUNDDOWN(O57,1)*100)<95,95,(90+ROUNDDOWN(O57,1)*100))-5 -> 135 | U57: 90 | V57: 1.1023 | Z57: 25 | AA57: =+Y57+Z57 -> 25 | AB57: =+((O57*P57*(R57-U57)/100)-S57-AA57+T57)*V57 -> 1341.398 | AC57: =+(S57-T57)*V57-'data 1'!$F$4 -> 68.8105 | AD57: =+(Q57-P57)*(R57-U57)*L57*V57/100 -> 2.8127774 | AE57: =+(Y57*V57-70)+V57*(Z57-IF(D57="UNTUCA",IF(+((W57-3)*2.5+(X57-3)*3.1)>0,+((W57-3)*1.5+(X57-3)*3.1),0),IF(+((W57-3)*1.5+(X57-3)*3.1)>0,+((W57-3)*1.5+(X57-3)*3.1),0))) -> -42.4425 | AF57: =(L57-O57)*(R57-U57)*Q57*V57/100 -> 64.535832 | AG57: =+IF(D57="RONALD WILLIAN GARIBAY ESCUDERO",AC57+AD57+AE57+AF57+70,AC57+AD57+AE57+AF57)+70-53 -> 110.71661 | AH57: =31.1035*L57*Q57*1.1023*K57/100 -> 124.51348 | AI57: =+((+$AI$2-R57+U57)*L57*Q57*V57)/100 -> 135.8031 | AJ57: =31.1035*1.1023*K57*P57*O57/100 -> 119.23174 | AL57: =+IF(AB57*K57>0,AB57*K57,0) -> 8799.9999
A58: IP-1059 | B58: 45674 | C58: 45668 | D58: MINERA AURIFERA 2 DE DICIEMBRE CALPA RENACE S.A. | E58: {=XLOOKUP(D58,RUC!$B$3:$B$79,RUC!$D$3:$D$79)} -> #N/A | G58: 50 | H58: MINERAL | I58: 6.67 | J58: 1.1 | K58: =+I58-(I58*(J58/100)) -> 6.59663 | L58: 0.812 | M58: 0.779 | N58: 0.849 | O58: =+ROUND((M58+N58)/2,3) -> 0.814 | P58: 90 | Q58: 89.93 | R58: 2687.45 | S58: =IF((90+ROUNDDOWN(O58,1)*100)<95,95,(90+ROUNDDOWN(O58,1)*100))-5 -> 165 | U58: 90 | V58: 1.1023 | Z58: 25 | AA58: =+Y58+Z58 -> 25 | AB58: =+((O58*P58*(R58-U58)/100)-S58-AA58+T58)*V58 -> 1888.1207 | AC58: =+(S58-T58)*V58-'data 1'!$F$4 -> 101.8795 | AD58: =+(Q58-P58)*(R58-U58)*L58*V58/100 -> -1.6274253 | AE58: =+(Y58*V58-70)+V58*(Z58-IF(D58="UNTUCA",IF(+((W58-3)*2.5+(X58-3)*3.1)>0,+((W58-3)*1.5+(X58-3)*3.1),0),IF(+((W58-3)*1.5+(X58-3)*3.1)>0,+((W58-3)*1.5+(X58-3)*3.1),0))) -> -42.4425 | AF58: =(L58-O58)*(R58-U58)*Q58*V58/100 -> -5.149696 | AG58: =+IF(D58="RONALD WILLIAN GARIBAY ESCUDERO",AC58+AD58+AE58+AF58+70,AC58+AD58+AE58+AF58)+70-53 -> 69.659879 | AH58: =31.1035*L58*Q58*1.1023*K58/100 -> 165.15503 | AI58: =+((+$AI$2-R58+U58)*L58*Q58*V58)/100 -> 179.13813 | AJ58: =31.1035*1.1023*K58*P58*O58/100 -> 165.69069 | AL58: =+IF(AB58*K58>0,AB58*K58,0) -> 12455.234
A59: IP-1060 | B59: 45674 | C59: 45668 | D59: MINERA AURIFERA 2 DE DICIEMBRE CALPA RENACE S.A. | E59: {=XLOOKUP(D59,RUC!$B$3:$B$79,RUC!$D$3:$D$79)} -> #N/A | G59: 50 | H59: MINERAL | I59: 6.48 | J59: 1 | K59: =+I59-(I59*(J59/100)) -> 6.4152 | L59: 0.569 | M59: 0.546 | N59: 0.546 | O59: =+ROUND((M59+N59)/2,3) -> 0.546 | P59: 90 | Q59: 90.18 | R59: 2687.45 | S59: =IF((90+ROUNDDOWN(O59,1)*100)<95,95,(90+ROUNDDOWN(O59,1)*100))-5 -> 135 | U59: 90 | V59: 1.1023 | Z59: 25 | AA59: =+Y59+Z59 -> 25 | AB59: =+((O59*P59*(R59-U59)/100)-S59-AA59+T59)*V59 -> 1230.5933 | AC59: =+(S59-T59)*V59-'data 1'!$F$4 -> 68.8105 | AD59: =+(Q59-P59)*(R59-U59)*L59*V59/100 -> 2.9324578 | AE59: =+(Y59*V59-70)+V59*(Z59-IF(D59="UNTUCA",IF(+((W59-3)*2.5+(X59-3)*3.1)>0,+((W59-3)*1.5+(X59-3)*3.1),0),IF(+((W59-3)*1.5+(X59-3)*3.1)>0,+((W59-3)*1.5+(X59-3)*3.1),0))) -> -42.4425 | AF59: =(L59-O59)*(R59-U59)*Q59*V59/100 -> 59.386136 | AG59: =+IF(D59="RONALD WILLIAN GARIBAY ESCUDERO",AC59+AD59+AE59+AF59+70,AC59+AD59+AE59+AF59)+70-53 -> 105.68659 | AH59: =31.1035*L59*Q59*1.1023*K59/100 -> 112.86045 | AI59: =+((+$AI$2-R59+U59)*L59*Q59*V59)/100 -> 125.87802 | AJ59: =31.1035*1.1023*K59*P59*O59/100 -> 108.08226 | AL59: =+IF(AB59*K59>0,AB59*K59,0) -> 7894.5022
A60: IP-1061 | B60: 45674 | C60: 45668 | D60: MINERA AURIFERA 2 DE DICIEMBRE CALPA RENACE S.A. | E60: {=XLOOKUP(D60,RUC!$B$3:$B$79,RUC!$D$3:$D$79)} -> #N/A | G60: 50 | H60: MINERAL | I60: 6.41 | J60: 1.2 | K60: =+I60-(I60*(J60/100)) -> 6.33308 | L60: 0.631 | M60: 0.605 | N60: 0.605 | O60: =+ROUND((M60+N60)/2,3) -> 0.605 | P60: 90 | Q60: 90.34 | R60: 2687.45 | S60: =IF((90+ROUNDDOWN(O60,1)*100)<95,95,(90+ROUNDDOWN(O60,1)*100))-5 -> 145 | U60: 90 | V60: 1.1023 | Z60: 25 | AA60: =+Y60+Z60 -> 25 | AB60: =+((O60*P60*(R60-U60)/100)-S60-AA60+T60)*V60 -> 1371.6046 | AC60: =+(S60-T60)*V60-'data 1'!$F$4 -> 79.8335 | AD60: =+(Q60-P60)*(R60-U60)*L60*V60/100 -> 6.1426431 | AE60: =+(Y60*V60-70)+V60*(Z60-IF(D60="UNTUCA",IF(+((W60-3)*2.5+(X60-3)*3.1)>0,+((W60-3)*1.5+(X60-3)*3.1),0),IF(+((W60-3)*1.5+(X60-3)*3.1)>0,+((W60-3)*1.5+(X60-3)*3.1),0))) -> -42.4425 | AF60: =(L60-O60)*(R60-U60)*Q60*V60/100 -> 67.251262 | AG60: =+IF(D60="RONALD WILLIAN GARIBAY ESCUDERO",AC60+AD60+AE60+AF60+70,AC60+AD60+AE60+AF60)+70-53 -> 127.7849 | AH60: =31.1035*L60*Q60*1.1023*K60/100 -> 123.77516 | AI60: =+((+$AI$2-R60+U60)*L60*Q60*V60)/100 -> 139.84175 | AJ60: =31.1035*1.1023*K60*P60*O60/100 -> 118.22843 | AL60: =+IF(AB60*K60>0,AB60*K60,0) -> 8686.4816
A61: IP-1062 | B61: 45674 | C61: 45668 | D61: MINERA AURIFERA 2 DE DICIEMBRE CALPA RENACE S.A. | E61: {=XLOOKUP(D61,RUC!$B$3:$B$79,RUC!$D$3:$D$79)} -> #N/A | G61: 50 | H61: MINERAL | I61: 6.99 | J61: 1.1 | K61: =+I61-(I61*(J61/100)) -> 6.91311 | L61: 0.618 | M61: 0.593 | N61: 0.593 | O61: =+ROUND((M61+N61)/2,3) -> 0.593 | P61: 90 | Q61: 90.08 | R61: 2687.45 | S61: =IF((90+ROUNDDOWN(O61,1)*100)<95,95,(90+ROUNDDOWN(O61,1)*100))-5 -> 135 | U61: 90 | V61: 1.1023 | Z61: 25 | AA61: =+Y61+Z61 -> 25 | AB61: =+((O61*P61*(R61-U61)/100)-S61-AA61+T61)*V61 -> 1351.7054 | AC61: =+(S61-T61)*V61-'data 1'!$F$4 -> 68.8105 | AD61: =+(Q61-P61)*(R61-U61)*L61*V61/100 -> 1.4155508 | AE61: =+(Y61*V61-70)+V61*(Z61-IF(D61="UNTUCA",IF(+((W61-3)*2.5+(X61-3)*3.1)>0,+((W61-3)*1.5+(X61-3)*3.1),0),IF(+((W61-3)*1.5+(X61-3)*3.1)>0,+((W61-3)*1.5+(X61-3)*3.1),0))) -> -42.4425 | AF61: =(L61-O61)*(R61-U61)*Q61*V61/100 -> 64.478569 | AG61: =+IF(D61="RONALD WILLIAN GARIBAY ESCUDERO",AC61+AD61+AE61+AF61+70,AC61+AD61+AE61+AF61)+70-53 -> 109.26212 | AH61: =31.1035*L61*Q61*1.1023*K61/100 -> 131.94696 | AI61: =+((+$AI$2-R61+U61)*L61*Q61*V61)/100 -> 136.56653 | AJ61: =31.1035*1.1023*K61*P61*O61/100 -> 126.49686 | AL61: =+IF(AB61*K61>0,AB61*K61,0) -> 9344.4879
A62: IP-1063 | B62: 45674 | C62: 45668 | D62: MINERA AURIFERA 2 DE DICIEMBRE CALPA RENACE S.A. | E62: {=XLOOKUP(D62,RUC!$B$3:$B$79,RUC!$D$3:$D$79)} -> #N/A | G62: 50 | H62: MINERAL | I62: 5.15 | J62: 1 | K62: =+I62-(I62*(J62/100)) -> 5.0985 | L62: 0.393 | M62: 0.377 | N62: 0.377 | O62: =+ROUND((M62+N62)/2,3) -> 0.377 | P62: 90 | Q62: 90.32 | R62: 2687.45 | S62: =IF((90+ROUNDDOWN(O62,1)*100)<95,95,(90+ROUNDDOWN(O62,1)*100))-5 -> 115 | U62: 90 | V62: 1.1023 | Z62: 25 | AA62: =+Y62+Z62 -> 25 | AB62: =+((O62*P62*(R62-U62)/100)-S62-AA62+T62)*V62 -> 817.15129 | AC62: =+(S62-T62)*V62-'data 1'!$F$4 -> 46.7645 | AD62: =+(Q62-P62)*(R62-U62)*L62*V62/100 -> 3.6007215 | AE62: =+(Y62*V62-70)+V62*(Z62-IF(D62="UNTUCA",IF(+((W62-3)*2.5+(X62-3)*3.1)>0,+((W62-3)*1.5+(X62-3)*3.1),0),IF(+((W62-3)*1.5+(X62-3)*3.1)>0,+((W62-3)*1.5+(X62-3)*3.1),0))) -> -42.4425 | AF62: =(L62-O62)*(R62-U62)*Q62*V62/100 -> 41.37623 | AG62: =+IF(D62="RONALD WILLIAN GARIBAY ESCUDERO",AC62+AD62+AE62+AF62+70,AC62+AD62+AE62+AF62)+70-53 -> 66.298951 | AH62: =31.1035*L62*Q62*1.1023*K62/100 -> 62.048026 | AI62: =+((+$AI$2-R62+U62)*L62*Q62*V62)/100 -> 87.077086 | AJ62: =31.1035*1.1023*K62*P62*O62/100 -> 59.311014 | AL62: =+IF(AB62*K62>0,AB62*K62,0) -> 4166.2458
A63: IP-1064 | B63: 45673 | C63: 45670 | D63: RONALD WILLIAN GARIBAY ESCUDERO | E63: {=XLOOKUP(D63,RUC!$B$3:$B$79,RUC!$D$3:$D$79)} -> #N/A | G63: 275 | H63: MINERAL | I63: 31.75 | J63: 1.5 | K63: =+I63-(I63*(J63/100)) -> 31.27375 | L63: 0.529 | M63: 0.507 | N63: 0.507 | O63: =+ROUND((M63+N63)/2,3) -> 0.507 | P63: 90 | Q63: 89.92 | R63: 2669.5 | S63: =IF((90+ROUNDDOWN(O63,1)*100)<95,95,(90+ROUNDDOWN(O63,1)*100)) -> 140 | U63: 100 | V63: 1.1023 | Z63: =IF(IF(D63="UNTUCA",IF(+((W63-3)*1.5+(X63-3)*3.1)>0,+((W63-3)*1.5+(X63-3)*3.1),0),IF(+((W63-3)*1.5+(X63-3)*3.1)>0,+((W63-3)*1.5+(X63-3)*3.1),0))<30,30,IF(D63="UNTUCA",IF(+((W63-3)*1.5+(X63-3)*3.1)>0,+((W63-3)*1.5+(X63-3)*3.1),0),IF(+((W63-3)*1.5+(X63-3)*3.1)>0,+((W63-3)*1.5+(X63-3)*3.1),0))) -> 30 | AA63: =+Y63+Z63 -> 30 | AB63: =+((O63*P63*(R63-U63)/100)-S63-AA63+T63)*V63 -> 1105.0148 | AC63: =+(S63-T63)*V63-'data 1'!$F$4 -> 74.322 | AD63: =+(Q63-P63)*(R63-U63)*L63*V63/100 -> -1.1986547 | AE63: =+(Y63*V63-70)+V63*(Z63-IF(D63="UNTUCA",IF(+((W63-3)*2.5+(X63-3)*3.1)>0,+((W63-3)*1.5+(X63-3)*3.1),0),IF(+((W63-3)*1.5+(X63-3)*3.1)>0,+((W63-3)*1.5+(X63-3)*3.1),0))) -> -36.931 | AF63: =(L63-O63)*(R63-U63)*Q63*V63/100 -> 56.030876 | AG63: =+IF(D63="RONALD WILLIAN GARIBAY ESCUDERO",AC63+AD63+AE63+AF63+70,AC63+AD63+AE63+AF63) -> 162.22322 | AH63: =31.1035*L63*Q63*1.1023*K63/100 -> 510.0362 | AI63: =+((+$AI$2-R63+U63)*L63*Q63*V63)/100 -> 131.3468 | AJ63: =31.1035*1.1023*K63*P63*O63/100 -> 489.25976 | AL63: =+IF(AB63*K63>0,AB63*K63,0) -> 34557.957
A64: IP-1065 | B64: 45672 | C64: 45670 | D64: GRUPO EL CAZADOR GOLD E.I.R.L | E64: {=XLOOKUP(D64,RUC!$B$3:$B$79,RUC!$D$3:$D$79)} -> 20606094010 | G64: 90 | H64: MINERAL | I64: 7.66 | J64: 1 | K64: =+I64-(I64*(J64/100)) -> 7.5834 | L64: 0.691 | M64: 0.663 | N64: 0.663 | O64: =+ROUND((M64+N64)/2,3) -> 0.663 | P64: 90 | Q64: 89.9 | R64: 2669.5 | S64: =IF((90+ROUNDDOWN(O64,1)*100)<95,95,(90+ROUNDDOWN(O64,1)*100)) -> 150 | U64: 120 | V64: 1.1023 | Y64: 20 | Z64: =IF(IF(D64="UNTUCA",IF(+((W64-3)*1.5+(X64-3)*3.1)>0,+((W64-3)*1.5+(X64-3)*3.1),0),IF(+((W64-3)*1.5+(X64-3)*3.1)>0,+((W64-3)*1.5+(X64-3)*3.1),0))<30,30,IF(D64="UNTUCA",IF(+((W64-3)*1.5+(X64-3)*3.1)>0,+((W64-3)*1.5+(X64-3)*3.1),0),IF(+((W64-3)*1.5+(X64-3)*3.1)>0,+((W64-3)*1.5+(X64-3)*3.1),0))) -> 30 | AA64: =+Y64+Z64 -> 50 | AB64: =+((O64*P64*(R64-U64)/100)-S64-AA64+T64)*V64 -> 1456.4543 | AC64: =+(S64-T64)*V64-'data 1'!$F$4 -> 85.345 | AD64: =+(Q64-P64)*(R64-U64)*L64*V64/100 -> -1.9419269 | AE64: =+(Y64*V64-70)+V64*(Z64-IF(D64="UNTUCA",IF(+((W64-3)*2.5+(X64-3)*3.1)>0,+((W64-3)*1.5+(X64-3)*3.1),0),IF(+((W64-3)*1.5+(X64-3)*3.1)>0,+((W64-3)*1.5+(X64-3)*3.1),0))) -> -14.885 | AF64: =(L64-O64)*(R64-U64)*Q64*V64/100 -> 70.74122 | AG64: =+IF(D64="RONALD WILLIAN GARIBAY ESCUDERO",AC64+AD64+AE64+AF64+70,AC64+AD64+AE64+AF64)+70-53 -> 156.25929 | AH64: =31.1035*L64*Q64*1.1023*K64/100 -> 161.51422 | AI64: =+((+$AI$2-R64+U64)*L64*Q64*V64)/100 -> 185.22722 | AJ64: =31.1035*1.1023*K64*P64*O64/100 -> 155.14189 | AL64: =+IF(AB64*K64>0,AB64*K64,0) -> 11044.875
A65: IP-1066 | B65: 45673 | C65: 45670 | D65: EMPRESA MINERA MARKATA CAS S.A.C. | E65: {=XLOOKUP(D65,RUC!$B$3:$B$79,RUC!$D$3:$D$79)} -> 20606526599 | G65: 78 | H65: MINERAL | I65: 6.1 | J65: 1.2 | K65: =+I65-(I65*(J65/100)) -> 6.0268 | L65: 0.167 | M65: 0.157 | N65: 0.157 | O65: =+ROUND((M65+N65)/2,3) -> 0.157 | P65: 90 | Q65: 90.09 | R65: 2669.5 | S65: =IF((90+ROUNDDOWN(O65,1)*100)<95,95,(90+ROUNDDOWN(O65,1)*100)) -> 100 | U65: 120 | V65: 1.1023 | Y65: 20 | Z65: =IF(IF(D65="UNTUCA",IF(+((W65-3)*1.5+(X65-3)*3.1)>0,+((W65-3)*1.5+(X65-3)*3.1),0),IF(+((W65-3)*1.5+(X65-3)*3.1)>0,+((W65-3)*1.5+(X65-3)*3.1),0))<30,30,IF(D65="UNTUCA",IF(+((W65-3)*1.5+(X65-3)*3.1)>0,+((W65-3)*1.5+(X65-3)*3.1),0),IF(+((W65-3)*1.5+(X65-3)*3.1)>0,+((W65-3)*1.5+(X65-3)*3.1),0))) -> 30 | AA65: =+Y65+Z65 -> 50 | AB65: =+((O65*P65*(R65-U65)/100)-S65-AA65+T65)*V65 -> 231.75235 | AC65: =+(S65-T65)*V65-'data 1'!$F$4 -> 30.23 | AD65: =+(Q65-P65)*(R65-U65)*L65*V65/100 -> 0.42239017 | AE65: =+(Y65*V65-70)+V65*(Z65-IF(D65="UNTUCA",IF(+((W65-3)*2.5+(X65-3)*3.1)>0,+((W65-3)*1.5+(X65-3)*3.1),0),IF(+((W65-3)*1.5+(X65-3)*3.1)>0,+((W65-3)*1.5+(X65-3)*3.1),0))) -> -14.885 | AF65: =(L65-O65)*(R65-U65)*Q65*V65/100 -> 25.318117 | AG65: =+IF(D65="RONALD WILLIAN GARIBAY ESCUDERO",AC65+AD65+AE65+AF65+70,AC65+AD65+AE65+AF65)+70-53 -> 58.085508 | AH65: =31.1035*L65*Q65*1.1023*K65/100 -> 31.087723 | AI65: =+((+$AI$2-R65+U65)*L65*Q65*V65)/100 -> 44.860089 | AJ65: =31.1035*1.1023*K65*P65*O65/100 -> 29.196985 | AL65: =+IF(AB65*K65>0,AB65*K65,0) -> 1396.725
A66: IP-1067 | B66: 45673 | C66: 45670 | D66: EMPRESA MINERA MARKATA CAS S.A.C. | E66: {=XLOOKUP(D66,RUC!$B$3:$B$79,RUC!$D$3:$D$79)} -> 20606526599 | G66: 87 | H66: MINERAL | I66: 6.07 | J66: 1.1 | K66: =+I66-(I66*(J66/100)) -> 6.00323 | L66: 0.239 | M66: 0.229 | N66: 0.297 | O66: =+ROUND((M66+N66)/2,3) -> 0.263 | P66: 90 | Q66: 90.11 | R66: 2669.5 | S66: =IF((90+ROUNDDOWN(O66,1)*100)<95,95,(90+ROUNDDOWN(O66,1)*100)) -> 110 | U66: 120 | V66: 1.1023 | Y66: 20 | Z66: =IF(IF(D66="UNTUCA",IF(+((W66-3)*1.5+(X66-3)*3.1)>0,+((W66-3)*1.5+(X66-3)*3.1),0),IF(+((W66-3)*1.5+(X66-3)*3.1)>0,+((W66-3)*1.5+(X66-3)*3.1),0))<30,30,IF(D66="UNTUCA",IF(+((W66-3)*1.5+(X66-3)*3.1)>0,+((W66-3)*1.5+(X66-3)*3.1),0),IF(+((W66-3)*1.5+(X66-3)*3.1)>0,+((W66-3)*1.5+(X66-3)*3.1),0))) -> 30 | AA66: =+Y66+Z66 -> 50 | AB66: =+((O66*P66*(R66-U66)/100)-S66-AA66+T66)*V66 -> 488.83329 | AC66: =+(S66-T66)*V66-'data 1'!$F$4 -> 41.253 | AD66: =+(Q66-P66)*(R66-U66)*L66*V66/100 -> 0.73883151 | AE66: =+(Y66*V66-70)+V66*(Z66-IF(D66="UNTUCA",IF(+((W66-3)*2.5+(X66-3)*3.1)>0,+((W66-3)*1.5+(X66-3)*3.1),0),IF(+((W66-3)*1.5+(X66-3)*3.1)>0,+((W66-3)*1.5+(X66-3)*3.1),0))) -> -14.885 | AF66: =(L66-O66)*(R66-U66)*Q66*V66/100 -> -60.776971 | AG66: =+IF(D66="RONALD WILLIAN GARIBAY ESCUDERO",AC66+AD66+AE66+AF66+70,AC66+AD66+AE66+AF66)+70-53 -> -16.67014 | AH66: =31.1035*L66*Q66*1.1023*K66/100 -> 44.326653 | AI66: =+((+$AI$2-R66+U66)*L66*Q66*V66)/100 -> 64.215219 | AJ66: =31.1035*1.1023*K66*P66*O66/100 -> 48.718321 | AL66: =+IF(AB66*K66>0,AB66*K66,0) -> 2934.5787
A67: IP-1068 | B67: 45673 | C67: 45670 | D67: LLASA YUCRA YOLANDA | E67: {=XLOOKUP(D67,RUC!$B$3:$B$79,RUC!$D$3:$D$79)} -> #N/A | G67: 100 | H67: MINERAL | I67: 8.61 | J67: 1.2 | K67: =+I67-(I67*(J67/100)) -> 8.50668 | L67: 0.56 | M67: 0.537 | N67: 0.57 | O67: =+ROUND((M67+N67)/2,3) -> 0.554 | P67: 90 | Q67: 89.96 | R67: 2669.5 | S67: =IF((90+ROUNDDOWN(O67,1)*100)<95,95,(90+ROUNDDOWN(O67,1)*100)) -> 140 | U67: 120 | V67: 1.1023 | Y67: 20 | Z67: =IF(IF(D67="UNTUCA",IF(+((W67-3)*1.5+(X67-3)*3.1)>0,+((W67-3)*1.5+(X67-3)*3.1),0),IF(+((W67-3)*1.5+(X67-3)*3.1)>0,+((W67-3)*1.5+(X67-3)*3.1),0))<30,30,IF(D67="UNTUCA",IF(+((W67-3)*1.5+(X67-3)*3.1)>0,+((W67-3)*1.5+(X67-3)*3.1),0),IF(+((W67-3)*1.5+(X67-3)*3.1)>0,+((W67-3)*1.5+(X67-3)*3.1),0))) -> 30 | AA67: =+Y67+Z67 -> 50 | AB67: =+((O67*P67*(R67-U67)/100)-S67-AA67+T67)*V67 -> 1191.7855 | AC67: =+(S67-T67)*V67-'data 1'!$F$4 -> 74.322 | AD67: =+(Q67-P67)*(R67-U67)*L67*V67/100 -> -0.6295103 | AE67: =+(Y67*V67-70)+V67*(Z67-IF(D67="UNTUCA",IF(+((W67-3)*2.5+(X67-3)*3.1)>0,+((W67-3)*1.5+(X67-3)*3.1),0),IF(+((W67-3)*1.5+(X67-3)*3.1)>0,+((W67-3)*1.5+(X67-3)*3.1),0))) -> -14.885 | AF67: =(L67-O67)*(R67-U67)*Q67*V67/100 -> 15.16895 | AG67: =+IF(D67="RONALD WILLIAN GARIBAY ESCUDERO",AC67+AD67+AE67+AF67+70,AC67+AD67+AE67+AF67)+70-53 -> 90.97644 | AH67: =31.1035*L67*Q67*1.1023*K67/100 -> 146.9287 | AI67: =+((+$AI$2-R67+U67)*L67*Q67*V67)/100 -> 150.21197 | AJ67: =31.1035*1.1023*K67*P67*O67/100 -> 145.4191 | AL67: =+IF(AB67*K67>0,AB67*K67,0) -> 10138.138
A68: IP-1069 | B68: 45674 | C68: 45670 | D68: J_M SOLUCIONES MINERAS E.I.R.L | E68: {=XLOOKUP(D68,RUC!$B$3:$B$79,RUC!$D$3:$D$79)} -> 20611329556 | G68: 130 | H68: MINERAL | I68: 12.26 | J68: 1.1 | K68: =+I68-(I68*(J68/100)) -> 12.12514 | L68: 0.399 | M68: 0.383 | N68: 0.383 | O68: =+ROUND((M68+N68)/2,3) -> 0.383 | P68: 90 | Q68: 90.09 | R68: 2669.5 | S68: 115 | U68: 120 | V68: 1.1023 | Y68: 20 | Z68: =IF(IF(D68="UNTUCA",IF(+((W68-3)*1.5+(X68-3)*3.1)>0,+((W68-3)*1.5+(X68-3)*3.1),0),IF(+((W68-3)*1.5+(X68-3)*3.1)>0,+((W68-3)*1.5+(X68-3)*3.1),0))<30,30,IF(D68="UNTUCA",IF(+((W68-3)*1.5+(X68-3)*3.1)>0,+((W68-3)*1.5+(X68-3)*3.1),0),IF(+((W68-3)*1.5+(X68-3)*3.1)>0,+((W68-3)*1.5+(X68-3)*3.1),0))) -> 30 | AA68: =+Y68+Z68 -> 50 | AB68: =+((O68*P68*(R68-U68)/100)-S68-AA68+T68)*V68 -> 786.83568 | AC68: =+(S68-T68)*V68-'data 1'!$F$4 -> 46.7645 | AD68: =+(Q68-P68)*(R68-U68)*L68*V68/100 -> 1.0091837 | AE68: =+(Y68*V68-70)+V68*(Z68-IF(D68="UNTUCA",IF(+((W68-3)*2.5+(X68-3)*3.1)>0,+((W68-3)*1.5+(X68-3)*3.1),0),IF(+((W68-3)*1.5+(X68-3)*3.1)>0,+((W68-3)*1.5+(X68-3)*3.1),0))) -> -14.885 | AF68: =(L68-O68)*(R68-U68)*Q68*V68/100 -> 40.508988 | AG68: =+IF(D68="RONALD WILLIAN GARIBAY ESCUDERO",AC68+AD68+AE68+AF68+70,AC68+AD68+AE68+AF68)+70-53 -> 90.397672 | AH68: =31.1035*L68*Q68*1.1023*K68/100 -> 149.43259 | AI68: =+((+$AI$2-R68+U68)*L68*Q68*V68)/100 -> 107.18069 | AJ68: =31.1035*1.1023*K68*P68*O68/100 -> 143.29701 | AL68: =+IF(AB68*K68>0,AB68*K68,0) -> 9540.4928
A69: IP-1070 | B69: 45674 | C69: 45670 | D69: J_M SOLUCIONES MINERAS E.I.R.L | E69: {=XLOOKUP(D69,RUC!$B$3:$B$79,RUC!$D$3:$D$79)} -> 20611329556 | G69: 110 | H69: MINERAL | I69: 9.86 | J69: 1.15 | K69: =+I69-(I69*(J69/100)) -> 9.74661 | L69: 0.559 | M69: 0.536 | N69: 0.536 | O69: =+ROUND((M69+N69)/2,3) -> 0.536 | P69: 90 | Q69: 90.15 | R69: 2669.5 | S69: 135 | U69: 120 | V69: 1.1023 | Y69: 20 | Z69: =IF(IF(D69="UNTUCA",IF(+((W69-3)*1.5+(X69-3)*3.1)>0,+((W69-3)*1.5+(X69-3)*3.1),0),IF(+((W69-3)*1.5+(X69-3)*3.1)>0,+((W69-3)*1.5+(X69-3)*3.1),0))<30,30,IF(D69="UNTUCA",IF(+((W69-3)*1.5+(X69-3)*3.1)>0,+((W69-3)*1.5+(X69-3)*3.1),0),IF(+((W69-3)*1.5+(X69-3)*3.1)>0,+((W69-3)*1.5+(X69-3)*3.1),0))) -> 30 | AA69: =+Y69+Z69 -> 50 | AB69: =+((O69*P69*(R69-U69)/100)-S69-AA69+T69)*V69 -> 1151.7699 | AC69: =+(S69-T69)*V69-'data 1'!$F$4 -> 68.8105 | AD69: =+(Q69-P69)*(R69-U69)*L69*V69/100 -> 2.3564482 | AE69: =+(Y69*V69-70)+V69*(Z69-IF(D69="UNTUCA",IF(+((W69-3)*2.5+(X69-3)*3.1)>0,+((W69-3)*1.5+(X69-3)*3.1),0),IF(+((W69-3)*1.5+(X69-3)*3.1)>0,+((W69-3)*1.5+(X69-3)*3.1),0))) -> -14.885 | AF69: =(L69-O69)*(R69-U69)*Q69*V69/100 -> 58.270453 | AG69: =+IF(D69="RONALD WILLIAN GARIBAY ESCUDERO",AC69+AD69+AE69+AF69+70,AC69+AD69+AE69+AF69)+70-53 -> 131.5524 | AH69: =31.1035*L69*Q69*1.1023*K69/100 -> 168.39927 | AI69: =+((+$AI$2-R69+U69)*L69*Q69*V69)/100 -> 150.26043 | AJ69: =31.1035*1.1023*K69*P69*O69/100 -> 161.20183 | AL69: =+IF(AB69*K69>0,AB69*K69,0) -> 11225.852
A70: IP-1071 | B70: 45674 | C70: 45671 | D70: LIMBER EDISON MONTALVO QUISPE | E70: {=XLOOKUP(D70,RUC!$B$3:$B$79,RUC!$D$3:$D$79)} -> 10479968131 | G70: 39 | H70: LLAMPO | I70: 1.53 | J70: 18.5 | K70: =+I70-(I70*(J70/100)) -> 1.24695 | L70: 0.413 | M70: 0.396 | N70: 0.396 | O70: =+ROUND((M70+N70)/2,3) -> 0.396 | P70: 90 | Q70: 89.89 | R70: 2667 | S70: =IF((90+ROUNDDOWN(O70,1)*100)<95,95,(90+ROUNDDOWN(O70,1)*100)) -> 120 | U70: 120 | V70: 1.1023 | Y70: 20 | Z70: =IF(IF(D70="UNTUCA",IF(+((W70-3)*1.5+(X70-3)*3.1)>0,+((W70-3)*1.5+(X70-3)*3.1),0),IF(+((W70-3)*1.5+(X70-3)*3.1)>0,+((W70-3)*1.5+(X70-3)*3.1),0))<30,30,IF(D70="UNTUCA",IF(+((W70-3)*1.5+(X70-3)*3.1)>0,+((W70-3)*1.5+(X70-3)*3.1),0),IF(+((W70-3)*1.5+(X70-3)*3.1)>0,+((W70-3)*1.5+(X70-3)*3.1),0))) -> 30 | AA70: =+Y70+Z70 -> 50 | AB70: =+((O70*P70*(R70-U70)/100)-S70-AA70+T70)*V70 -> 813.22271 | AC70: =+(S70-T70)*V70-'data 1'!$F$4 -> 52.276 | AD70: =+(Q70-P70)*(R70-U70)*L70*V70/100 -> -1.2754736 | AE70: =+(Y70*V70-70)+V70*(Z70-IF(D70="UNTUCA",IF(+((W70-3)*2.5+(X70-3)*3.1)>0,+((W70-3)*1.5+(X70-3)*3.1),0),IF(+((W70-3)*1.5+(X70-3)*3.1)>0,+((W70-3)*1.5+(X70-3)*3.1),0))) -> -14.885 | AF70: =(L70-O70)*(R70-U70)*Q70*V70/100 -> 42.903138 | AG70: =+IF(D70="RONALD WILLIAN GARIBAY ESCUDERO",AC70+AD70+AE70+AF70+70,AC70+AD70+AE70+AF70)+70-53 -> 96.018664 | AH70: =31.1035*L70*Q70*1.1023*K70/100 -> 15.871557 | AI70: =+((+$AI$2-R70+U70)*L70*Q70*V70)/100 -> 111.71819 | AJ70: =31.1035*1.1023*K70*P70*O70/100 -> 15.236871 | AL70: =+IF(AB70*K70>0,AB70*K70,0) -> 1014.0481
A71: IP-1072 | B71: 45674 | C71: 45671 | D71: LIMBER EDISON MONTALVO QUISPE | E71: {=XLOOKUP(D71,RUC!$B$3:$B$79,RUC!$D$3:$D$79)} -> 10479968131 | G71: 110 | H71: LLAMPO | I71: 4.17 | J71: 18.35 | K71: =+I71-(I71*(J71/100)) -> 3.404805 | L71: 0.53 | M71: 0.509 | N71: 0.509 | O71: =+ROUND((M71+N71)/2,3) -> 0.509 | P71: 90 | Q71: 89.92 | R71: 2667 | S71: =IF((90+ROUNDDOWN(O71,1)*100)<95,95,(90+ROUNDDOWN(O71,1)*100)) -> 140 | U71: 120 | V71: 1.1023 | Y71: 20 | Z71: =IF(IF(D71="UNTUCA",IF(+((W71-3)*1.5+(X71-3)*3.1)>0,+((W71-3)*1.5+(X71-3)*3.1),0),IF(+((W71-3)*1.5+(X71-3)*3.1)>0,+((W71-3)*1.5+(X71-3)*3.1),0))<30,30,IF(D71="UNTUCA",IF(+((W71-3)*1.5+(X71-3)*3.1)>0,+((W71-3)*1.5+(X71-3)*3.1),0),IF(+((W71-3)*1.5+(X71-3)*3.1)>0,+((W71-3)*1.5+(X71-3)*3.1),0))) -> 30 | AA71: =+Y71+Z71 -> 50 | AB71: =+((O71*P71*(R71-U71)/100)-S71-AA71+T71)*V71 -> 1076.7054 | AC71: =+(S71-T71)*V71-'data 1'!$F$4 -> 74.322 | AD71: =+(Q71-P71)*(R71-U71)*L71*V71/100 -> -1.1904046 | AE71: =+(Y71*V71-70)+V71*(Z71-IF(D71="UNTUCA",IF(+((W71-3)*2.5+(X71-3)*3.1)>0,+((W71-3)*1.5+(X71-3)*3.1),0),IF(+((W71-3)*1.5+(X71-3)*3.1)>0,+((W71-3)*1.5+(X71-3)*3.1),0))) -> -14.885 | AF71: =(L71-O71)*(R71-U71)*Q71*V71/100 -> 53.015681 | AG71: =+IF(D71="RONALD WILLIAN GARIBAY ESCUDERO",AC71+AD71+AE71+AF71+70,AC71+AD71+AE71+AF71)+70-53 -> 128.26228 | AH71: =31.1035*L71*Q71*1.1023*K71/100 -> 55.633128 | AI71: =+((+$AI$2-R71+U71)*L71*Q71*V71)/100 -> 143.41501 | AJ71: =31.1035*1.1023*K71*P71*O71/100 -> 53.476331 | AL71: =+IF(AB71*K71>0,AB71*K71,0) -> 3665.9718
A72: IP-1073 | B72: 45674 | C72: 45671 | D72: LIMBER EDISON MONTALVO QUISPE | E72: {=XLOOKUP(D72,RUC!$B$3:$B$79,RUC!$D$3:$D$79)} -> 10479968131 | G72: 40 | H72: LLAMPO | I72: 3.42 | J72: 18 | K72: =+I72-(I72*(J72/100)) -> 2.8044 | L72: 0.626 | M72: 0.6 | N72: 0.6 | O72: =+ROUND((M72+N72)/2,3) -> 0.6 | P72: 90 | Q72: 89.75 | R72: 2667 | S72: =IF((90+ROUNDDOWN(O72,1)*100)<95,95,(90+ROUNDDOWN(O72,1)*100)) -> 150 | U72: 120 | V72: 1.1023 | Y72: 20 | Z72: =IF(IF(D72="UNTUCA",IF(+((W72-3)*1.5+(X72-3)*3.1)>0,+((W72-3)*1.5+(X72-3)*3.1),0),IF(+((W72-3)*1.5+(X72-3)*3.1)>0,+((W72-3)*1.5+(X72-3)*3.1),0))<30,30,IF(D72="UNTUCA",IF(+((W72-3)*1.5+(X72-3)*3.1)>0,+((W72-3)*1.5+(X72-3)*3.1),0),IF(+((W72-3)*1.5+(X72-3)*3.1)>0,+((W72-3)*1.5+(X72-3)*3.1),0))) -> 30 | AA72: =+Y72+Z72 -> 50 | AB72: =+((O72*P72*(R72-U72)/100)-S72-AA72+T72)*V72 -> 1295.6214 | AC72: =+(S72-T72)*V72-'data 1'!$F$4 -> 85.345 | AD72: =+(Q72-P72)*(R72-U72)*L72*V72/100 -> -4.3938284 | AE72: =+(Y72*V72-70)+V72*(Z72-IF(D72="UNTUCA",IF(+((W72-3)*2.5+(X72-3)*3.1)>0,+((W72-3)*1.5+(X72-3)*3.1),0),IF(+((W72-3)*1.5+(X72-3)*3.1)>0,+((W72-3)*1.5+(X72-3)*3.1),0))) -> -14.885 | AF72: =(L72-O72)*(R72-U72)*Q72*V72/100 -> 65.514368 | AG72: =+IF(D72="RONALD WILLIAN GARIBAY ESCUDERO",AC72+AD72+AE72+AF72+70,AC72+AD72+AE72+AF72)+70-53 -> 148.58054 | AH72: =31.1035*L72*Q72*1.1023*K72/100 -> 54.020403 | AI72: =+((+$AI$2-R72+U72)*L72*Q72*V72)/100 -> 169.07183 | AJ72: =31.1035*1.1023*K72*P72*O72/100 -> 51.920969 | AL72: =+IF(AB72*K72>0,AB72*K72,0) -> 3633.4406
A73: IP-1074 | B73: 45674 | C73: 45671 | D73: LIMBER EDISON MONTALVO QUISPE | E73: {=XLOOKUP(D73,RUC!$B$3:$B$79,RUC!$D$3:$D$79)} -> 10479968131 | G73: 31 | H73: LLAMPO | I73: 2.68 | J73: 12.05 | K73: =+I73-(I73*(J73/100)) -> 2.35706 | L73: 0.334 | M73: 0.32 | N73: 0.32 | O73: =+ROUND((M73+N73)/2,3) -> 0.32 | P73: 90 | Q73: 89.69 | R73: 2667 | S73: =IF((90+ROUNDDOWN(O73,1)*100)<95,95,(90+ROUNDDOWN(O73,1)*100)) -> 120 | U73: 120 | V73: 1.1023 | Y73: 20 | Z73: =IF(IF(D73="UNTUCA",IF(+((W73-3)*1.5+(X73-3)*3.1)>0,+((W73-3)*1.5+(X73-3)*3.1),0),IF(+((W73-3)*1.5+(X73-3)*3.1)>0,+((W73-3)*1.5+(X73-3)*3.1),0))<30,30,IF(D73="UNTUCA",IF(+((W73-3)*1.5+(X73-3)*3.1)>0,+((W73-3)*1.5+(X73-3)*3.1),0),IF(+((W73-3)*1.5+(X73-3)*3.1)>0,+((W73-3)*1.5+(X73-3)*3.1),0))) -> 30 | AA73: =+Y73+Z73 -> 50 | AB73: =+((O73*P73*(R73-U73)/100)-S73-AA73+T73)*V73 -> 621.18573 | AC73: =+(S73-T73)*V73-'data 1'!$F$4 -> 52.276 | AD73: =+(Q73-P73)*(R73-U73)*L73*V73/100 -> -2.9069457 | AE73: =+(Y73*V73-70)+V73*(Z73-IF(D73="UNTUCA",IF(+((W73-3)*2.5+(X73-3)*3.1)>0,+((W73-3)*1.5+(X73-3)*3.1),0),IF(+((W73-3)*1.5+(X73-3)*3.1)>0,+((W73-3)*1.5+(X73-3)*3.1),0))) -> -14.885 | AF73: =(L73-O73)*(R73-U73)*Q73*V73/100 -> 35.253384 | AG73: =+IF(D73="RONALD WILLIAN GARIBAY ESCUDERO",AC73+AD73+AE73+AF73+70,AC73+AD73+AE73+AF73)+70-53 -> 86.737438 | AH73: =31.1035*L73*Q73*1.1023*K73/100 -> 24.208629 | AI73: =+((+$AI$2-R73+U73)*L73*Q73*V73)/100 -> 90.147346 | AJ73: =31.1035*1.1023*K73*P73*O73/100 -> 23.274062 | AL73: =+IF(AB73*K73>0,AB73*K73,0) -> 1464.172
A74: IP-1075 | B74: 45674 | C74: 45671 | D74: LIMBER EDISON MONTALVO QUISPE | E74: {=XLOOKUP(D74,RUC!$B$3:$B$79,RUC!$D$3:$D$79)} -> 10479968131 | G74: 29 | H74: LLAMPO | I74: 2.36 | J74: 14.44 | K74: =+I74-(I74*(J74/100)) -> 2.019216 | L74: 0.422 | M74: 0.405 | N74: 0.405 | O74: =+ROUND((M74+N74)/2,3) -> 0.405 | P74: 90 | Q74: 89.86 | R74: 2667 | S74: =IF((90+ROUNDDOWN(O74,1)*100)<95,95,(90+ROUNDDOWN(O74,1)*100)) -> 130 | U74: 120 | V74: 1.1023 | Y74: 20 | Z74: =IF(IF(D74="UNTUCA",IF(+((W74-3)*1.5+(X74-3)*3.1)>0,+((W74-3)*1.5+(X74-3)*3.1),0),IF(+((W74-3)*1.5+(X74-3)*3.1)>0,+((W74-3)*1.5+(X74-3)*3.1),0))<30,30,IF(D74="UNTUCA",IF(+((W74-3)*1.5+(X74-3)*3.1)>0,+((W74-3)*1.5+(X74-3)*3.1),0),IF(+((W74-3)*1.5+(X74-3)*3.1)>0,+((W74-3)*1.5+(X74-3)*3.1),0))) -> 30 | AA74: =+Y74+Z74 -> 50 | AB74: =+((O74*P74*(R74-U74)/100)-S74-AA74+T74)*V74 -> 824.94093 | AC74: =+(S74-T74)*V74-'data 1'!$F$4 -> 63.299 | AD74: =+(Q74-P74)*(R74-U74)*L74*V74/100 -> -1.6587053 | AE74: =+(Y74*V74-70)+V74*(Z74-IF(D74="UNTUCA",IF(+((W74-3)*2.5+(X74-3)*3.1)>0,+((W74-3)*1.5+(X74-3)*3.1),0),IF(+((W74-3)*1.5+(X74-3)*3.1)>0,+((W74-3)*1.5+(X74-3)*3.1),0))) -> -14.885 | AF74: =(L74-O74)*(R74-U74)*Q74*V74/100 -> 42.888819 | AG74: =+IF(D74="RONALD WILLIAN GARIBAY ESCUDERO",AC74+AD74+AE74+AF74+70,AC74+AD74+AE74+AF74)+70-53 -> 106.64411 | AH74: =31.1035*L74*Q74*1.1023*K74/100 -> 26.252503 | AI74: =+((+$AI$2-R74+U74)*L74*Q74*V74)/100 -> 114.11463 | AJ74: =31.1035*1.1023*K74*P74*O74/100 -> 25.234191 | AL74: =+IF(AB74*K74>0,AB74*K74,0) -> 1665.7339
A75: IP-1084 | B75: 45950 | C75: 45674 | D75: MELCHOR AGUSTIN VERA PACHECO | E75: {=XLOOKUP(D75,RUC!$B$3:$B$79,RUC!$D$3:$D$79)} -> 10082235774 | G75: 53 | H75: MINERAL | I75: 5.27 | J75: 1.9 | K75: =+I75-(I75*(J75/100)) -> 5.16987 | L75: 0.214 | M75: 0.211 | N75: 0.211 | O75: =+ROUND((M75+N75)/2,3) -> 0.211 | P75: 85 | Q75: 90.12 | R75: 2715.2 | S75: 105 | U75: 80 | V75: 1.1023 | Z75: 10 | AA75: =+Y75+Z75 -> 10 | AB75: =+((O75*P75*(R75-U75)/100)-S75-AA75+T75)*V75 -> 394.20797 | AC75: =+(S75-T75)*V75-'data 1'!$F$4 -> 35.7415 | AD75: =+(Q75-P75)*(R75-U75)*L75*V75/100 -> 31.827104 | AE75: =+(Y75*V75-70)+V75*(Z75-IF(D75="UNTUCA",IF(+((W75-3)*2.5+(X75-3)*3.1)>0,+((W75-3)*1.5+(X75-3)*3.1),0),IF(+((W75-3)*1.5+(X75-3)*3.1)>0,+((W75-3)*1.5+(X75-3)*3.1),0))) -> -58.977 | AF75: =(L75-O75)*(R75-U75)*Q75*V75/100 -> 7.8533658 | AG75: =+IF(D75="RONALD WILLIAN GARIBAY ESCUDERO",AC75+AD75+AE75+AF75+70,AC75+AD75+AE75+AF75)+70 -> 86.44497 | AH75: =31.1035*L75*Q75*1.1023*K75/100 -> 34.18406 | AI75: =+((+$AI$2-R75+U75)*L75*Q75*V75)/100 -> 39.285902 | AJ75: =31.1035*1.1023*K75*P75*O75/100 -> 31.789967 | AL75: =+IF(AB75*K75>0,AB75*K75,0) -> 2038.0039
A76: IP-1085 | B76: 45950 | C76: 45674 | D76: MELCHOR AGUSTIN VERA PACHECO | E76: {=XLOOKUP(D76,RUC!$B$3:$B$79,RUC!$D$3:$D$79)} -> 10082235774 | G76: 43 | H76: MINERAL | I76: 4.65 | J76: 1.8 | K76: =+I76-(I76*(J76/100)) -> 4.5663 | L76: 0.596 | M76: 0.587 | N76: 0.587 | O76: =+ROUND((M76+N76)/2,3) -> 0.587 | P76: 90 | Q76: 90.09 | R76: 2715.2 | S76: 120 | U76: 80 | V76: 1.1023 | Z76: 10 | AA76: =+Y76+Z76 -> 10 | AB76: =+((O76*P76*(R76-U76)/100)-S76-AA76+T76)*V76 -> 1391.2968 | AC76: =+(S76-T76)*V76-'data 1'!$F$4 -> 52.276 | AD76: =+(Q76-P76)*(R76-U76)*L76*V76/100 -> 1.5581245 | AE76: =+(Y76*V76-70)+V76*(Z76-IF(D76="UNTUCA",IF(+((W76-3)*2.5+(X76-3)*3.1)>0,+((W76-3)*1.5+(X76-3)*3.1),0),IF(+((W76-3)*1.5+(X76-3)*3.1)>0,+((W76-3)*1.5+(X76-3)*3.1),0))) -> -58.977 | AF76: =(L76-O76)*(R76-U76)*Q76*V76/100 -> 23.552255 | AG76: =+IF(D76="RONALD WILLIAN GARIBAY ESCUDERO",AC76+AD76+AE76+AF76+70,AC76+AD76+AE76+AF76)+70 -> 88.409379 | AH76: =31.1035*L76*Q76*1.1023*K76/100 -> 84.061349 | AI76: =+((+$AI$2-R76+U76)*L76*Q76*V76)/100 -> 109.37665 | AJ76: =31.1035*1.1023*K76*P76*O76/100 -> 82.709257 | AL76: =+IF(AB76*K76>0,AB76*K76,0) -> 6353.0785
A77: IP-1086 | B77: 45950 | C77: 45674 | D77: MELCHOR AGUSTIN VERA PACHECO | E77: {=XLOOKUP(D77,RUC!$B$3:$B$79,RUC!$D$3:$D$79)} -> 10082235774 | G77: 65 | H77: MINERAL | I77: 6.64 | J77: 1.7 | K77: =+I77-(I77*(J77/100)) -> 6.52712 | L77: 0.198 | M77: 0.195 | N77: 0.195 | O77: =+ROUND((M77+N77)/2,3) -> 0.195 | P77: 85 | Q77: 90.21 | R77: 2715.2 | S77: 95 | U77: 80 | V77: 1.1023 | Z77: 10 | AA77: =+Y77+Z77 -> 10 | AB77: =+((O77*P77*(R77-U77)/100)-S77-AA77+T77)*V77 -> 365.72594 | AC77: =+(S77-T77)*V77-'data 1'!$F$4 -> 24.7185 | AD77: =+(Q77-P77)*(R77-U77)*L77*V77/100 -> 29.965139 | AE77: =+(Y77*V77-70)+V77*(Z77-IF(D77="UNTUCA",IF(+((W77-3)*2.5+(X77-3)*3.1)>0,+((W77-3)*1.5+(X77-3)*3.1),0),IF(+((W77-3)*1.5+(X77-3)*3.1)>0,+((W77-3)*1.5+(X77-3)*3.1),0))) -> -58.977 | AF77: =(L77-O77)*(R77-U77)*Q77*V77/100 -> 7.8612087 | AG77: =+IF(D77="RONALD WILLIAN GARIBAY ESCUDERO",AC77+AD77+AE77+AF77+70,AC77+AD77+AE77+AF77)+70 -> 73.567848 | AH77: =31.1035*L77*Q77*1.1023*K77/100 -> 39.971509 | AI77: =+((+$AI$2-R77+U77)*L77*Q77*V77)/100 -> 36.384939 | AJ77: =31.1035*1.1023*K77*P77*O77/100 -> 37.092338 | AL77: =+IF(AB77*K77>0,AB77*K77,0) -> 2387.1371
A78: IP-1087 | B78: 45950 | C78: 45674 | D78: MELCHOR AGUSTIN VERA PACHECO | E78: {=XLOOKUP(D78,RUC!$B$3:$B$79,RUC!$D$3:$D$79)} -> 10082235774 | G78: 65 | H78: MINERAL | I78: 6.59 | J78: 1.8 | K78: =+I78-(I78*(J78/100)) -> 6.47138 | L78: 0.15 | M78: 0.148 | N78: 0.148 | O78: =+ROUND((M78+N78)/2,3) -> 0.148 | P78: 85 | Q78: 90.11 | R78: 2715.2 | S78: 95 | U78: 80 | V78: 1.1023 | Z78: 10 | AA78: =+Y78+Z78 -> 10 | AB78: =+((O78*P78*(R78-U78)/100)-S78-AA78+T78)*V78 -> 249.67994 | AC78: =+(S78-T78)*V78-'data 1'!$F$4 -> 24.7185 | AD78: =+(Q78-P78)*(R78-U78)*L78*V78/100 -> 22.265146 | AE78: =+(Y78*V78-70)+V78*(Z78-IF(D78="UNTUCA",IF(+((W78-3)*2.5+(X78-3)*3.1)>0,+((W78-3)*1.5+(X78-3)*3.1),0),IF(+((W78-3)*1.5+(X78-3)*3.1)>0,+((W78-3)*1.5+(X78-3)*3.1),0))) -> -58.977 | AF78: =(L78-O78)*(R78-U78)*Q78*V78/100 -> 5.2349962 | AG78: =+IF(D78="RONALD WILLIAN GARIBAY ESCUDERO",AC78+AD78+AE78+AF78+70,AC78+AD78+AE78+AF78)+70 -> 63.241642 | AH78: =31.1035*L78*Q78*1.1023*K78/100 -> 29.989569 | AI78: =+((+$AI$2-R78+U78)*L78*Q78*V78)/100 -> 27.533792 | AJ78: =31.1035*1.1023*K78*P78*O78/100 -> 27.911721 | AL78: =+IF(AB78*K78>0,AB78*K78,0) -> 1615.7738
A79: IP-1088 | B79: 45950 | C79: 45674 | D79: MELCHOR AGUSTIN VERA PACHECO | E79: {=XLOOKUP(D79,RUC!$B$3:$B$79,RUC!$D$3:$D$79)} -> 10082235774 | G79: 47 | H79: MINERAL | I79: 5.11 | J79: 1.7 | K79: =+I79-(I79*(J79/100)) -> 5.02313 | L79: 0.561 | M79: 0.552 | N79: 0.552 | O79: =+ROUND((M79+N79)/2,3) -> 0.552 | P79: 90 | Q79: 90.06 | R79: 2715.2 | S79: 120 | U79: 80 | V79: 1.1023 | Z79: 10 | AA79: =+Y79+Z79 -> 10 | AB79: =+((O79*P79*(R79-U79)/100)-S79-AA79+T79)*V79 -> 1299.7962 | AC79: =+(S79-T79)*V79-'data 1'!$F$4 -> 52.276 | AD79: =+(Q79-P79)*(R79-U79)*L79*V79/100 -> 0.97774927 | AE79: =+(Y79*V79-70)+V79*(Z79-IF(D79="UNTUCA",IF(+((W79-3)*2.5+(X79-3)*3.1)>0,+((W79-3)*1.5+(X79-3)*3.1),0),IF(+((W79-3)*1.5+(X79-3)*3.1)>0,+((W79-3)*1.5+(X79-3)*3.1),0))) -> -58.977 | AF79: =(L79-O79)*(R79-U79)*Q79*V79/100 -> 23.544412 | AG79: =+IF(D79="RONALD WILLIAN GARIBAY ESCUDERO",AC79+AD79+AE79+AF79+70,AC79+AD79+AE79+AF79)+70 -> 87.821161 | AH79: =31.1035*L79*Q79*1.1023*K79/100 -> 87.011828 | AI79: =+((+$AI$2-R79+U79)*L79*Q79*V79)/100 -> 102.91924 | AJ79: =31.1035*1.1023*K79*P79*O79/100 -> 85.558877 | AL79: =+IF(AB79*K79>0,AB79*K79,0) -> 6529.0452
A80: IP-1089 | B80: 45950 | C80: 45674 | D80: MELCHOR AGUSTIN VERA PACHECO | E80: {=XLOOKUP(D80,RUC!$B$3:$B$79,RUC!$D$3:$D$79)} -> 10082235774 | G80: 40 | H80: MINERAL | I80: 4.04 | J80: 1.9 | K80: =+I80-(I80*(J80/100)) -> 3.96324 | L80: 0.211 | M80: 0.208 | N80: 0.208 | O80: =+ROUND((M80+N80)/2,3) -> 0.208 | P80: 85 | Q80: 90.16 | R80: 2715.2 | S80: 105 | U80: 80 | V80: 1.1023 | Z80: 10 | AA80: =+Y80+Z80 -> 10 | AB80: =+((O80*P80*(R80-U80)/100)-S80-AA80+T80)*V80 -> 386.80077 | AC80: =+(S80-T80)*V80-'data 1'!$F$4 -> 35.7415 | AD80: =+(Q80-P80)*(R80-U80)*L80*V80/100 -> 31.626093 | AE80: =+(Y80*V80-70)+V80*(Z80-IF(D80="UNTUCA",IF(+((W80-3)*2.5+(X80-3)*3.1)>0,+((W80-3)*1.5+(X80-3)*3.1),0),IF(+((W80-3)*1.5+(X80-3)*3.1)>0,+((W80-3)*1.5+(X80-3)*3.1),0))) -> -58.977 | AF80: =(L80-O80)*(R80-U80)*Q80*V80/100 -> 7.8568515 | AG80: =+IF(D80="RONALD WILLIAN GARIBAY ESCUDERO",AC80+AD80+AE80+AF80+70,AC80+AD80+AE80+AF80)+70 -> 86.247445 | AH80: =31.1035*L80*Q80*1.1023*K80/100 -> 25.849717 | AI80: =+((+$AI$2-R80+U80)*L80*Q80*V80)/100 -> 38.752358 | AJ80: =31.1035*1.1023*K80*P80*O80/100 -> 24.0238 | AL80: =+IF(AB80*K80>0,AB80*K80,0) -> 1532.9843
A81: IP-1090 | B81: 45950 | C81: 45674 | D81: MELCHOR AGUSTIN VERA PACHECO | E81: {=XLOOKUP(D81,RUC!$B$3:$B$79,RUC!$D$3:$D$79)} -> 10082235774 | G81: 40 | H81: MINERAL | I81: 4.07 | J81: 1.8 | K81: =+I81-(I81*(J81/100)) -> 3.99674 | L81: 0.198 | M81: 0.195 | N81: 0.195 | O81: =+ROUND((M81+N81)/2,3) -> 0.195 | P81: 85 | Q81: 90.25 | R81: 2715.2 | S81: 95 | U81: 80 | V81: 1.1023 | Z81: 10 | AA81: =+Y81+Z81 -> 10 | AB81: =+((O81*P81*(R81-U81)/100)-S81-AA81+T81)*V81 -> 365.72594 | AC81: =+(S81-T81)*V81-'data 1'!$F$4 -> 24.7185 | AD81: =+(Q81-P81)*(R81-U81)*L81*V81/100 -> 30.195198 | AE81: =+(Y81*V81-70)+V81*(Z81-IF(D81="UNTUCA",IF(+((W81-3)*2.5+(X81-3)*3.1)>0,+((W81-3)*1.5+(X81-3)*3.1),0),IF(+((W81-3)*1.5+(X81-3)*3.1)>0,+((W81-3)*1.5+(X81-3)*3.1),0))) -> -58.977 | AF81: =(L81-O81)*(R81-U81)*Q81*V81/100 -> 7.8646944 | AG81: =+IF(D81="RONALD WILLIAN GARIBAY ESCUDERO",AC81+AD81+AE81+AF81+70,AC81+AD81+AE81+AF81)+70 -> 73.801393 | AH81: =31.1035*L81*Q81*1.1023*K81/100 -> 24.486537 | AI81: =+((+$AI$2-R81+U81)*L81*Q81*V81)/100 -> 36.401072 | AJ81: =31.1035*1.1023*K81*P81*O81/100 -> 22.712686 | AL81: =+IF(AB81*K81>0,AB81*K81,0) -> 1461.7115
A82: IP-1091 | B82: 45950 | C82: 45674 | D82: MELCHOR AGUSTIN VERA PACHECO | E82: {=XLOOKUP(D82,RUC!$B$3:$B$79,RUC!$D$3:$D$79)} -> 10082235774 | G82: 46 | H82: MINERAL | I82: 4.39 | J82: 2.3 | K82: =+I82-(I82*(J82/100)) -> 4.28903 | L82: 0.095 | M82: 0.093 | N82: 0.093 | O82: =+ROUND((M82+N82)/2,3) -> 0.093 | P82: 85 | Q82: 89.89 | R82: 2715.2 | S82: =IF((90+ROUNDDOWN(O82,1)*100)<95,95,(90+ROUNDDOWN(O82,1)*100)) -> 95 | U82: 80 | V82: 1.1023 | Z82: 10 | AA82: =+Y82+Z82 -> 10 | AB82: 0 | AC82: =+(S82-T82)*V82-'data 1'!$F$4 -> 24.7185 | AD82: =+(Q82-P82)*(R82-U82)*L82*V82/100 -> 13.49416 | AE82: =+(Y82*V82-70)+V82*(Z82-IF(D82="UNTUCA",IF(+((W82-3)*2.5+(X82-3)*3.1)>0,+((W82-3)*1.5+(X82-3)*3.1),0),IF(+((W82-3)*1.5+(X82-3)*3.1)>0,+((W82-3)*1.5+(X82-3)*3.1),0))) -> -58.977 | AF82: =(L82-O82)*(R82-U82)*Q82*V82/100 -> 5.2222152 | AG82: =+IF(D82="RONALD WILLIAN GARIBAY ESCUDERO",AC82+AD82+AE82+AF82+70,AC82+AD82+AE82+AF82)+70+113.88 -> 168.33788 | AH82: =31.1035*L82*Q82*1.1023*K82/100 -> 12.557499 | AI82: =+((+$AI$2-R82+U82)*L82*Q82*V82)/100 -> 17.395494 | AJ82: =31.1035*1.1023*K82*P82*O82/100 -> 11.624386 | AL82: =+IF(AB82*K82>0,AB82*K82,0) -> 0
A83: IP-1092
A84: IP-1093
A85: IP-1099 | B85: 45681 | C85: 45678 | D85: LLASA YUCRA YOLANDA | E85: {=XLOOKUP(D85,RUC!$B$3:$B$79,RUC!$D$3:$D$79)} -> #N/A | G85: 100 | H85: MINERAL | I85: 7.7 | J85: 1.4 | K85: =+I85-(I85*(J85/100)) -> 7.5922 | L85: 0.239 | M85: 0.229 | N85: 0.255 | O85: =+ROUND((M85+N85)/2,3) -> 0.242 | P85: 90 | Q85: 90.13 | R85: 2737.8 | S85: =IF((90+ROUNDDOWN(O85,1)*100)<95,95,(90+ROUNDDOWN(O85,1)*100)) -> 110 | U85: 120 | V85: 1.1023 | Y85: 20 | Z85: =IF(IF(D85="UNTUCA",IF(+((W85-3)*1.5+(X85-3)*3.1)>0,+((W85-3)*1.5+(X85-3)*3.1),0),IF(+((W85-3)*1.5+(X85-3)*3.1)>0,+((W85-3)*1.5+(X85-3)*3.1),0))<30,30,IF(D85="UNTUCA",IF(+((W85-3)*1.5+(X85-3)*3.1)>0,+((W85-3)*1.5+(X85-3)*3.1),0),IF(+((W85-3)*1.5+(X85-3)*3.1)>0,+((W85-3)*1.5+(X85-3)*3.1),0))) -> 30 | AA85: =+Y85+Z85 -> 50 | AB85: =+((O85*P85*(R85-U85)/100)-S85-AA85+T85)*V85 -> 452.11588 | AC85: =+(S85-T85)*V85-'data 1'!$F$4 -> 41.253 | AD85: =+(Q85-P85)*(R85-U85)*L85*V85/100 -> 0.89655621 | AE85: =+(Y85*V85-70)+V85*(Z85-IF(D85="UNTUCA",IF(+((W85-3)*2.5+(X85-3)*3.1)>0,+((W85-3)*1.5+(X85-3)*3.1),0),IF(+((W85-3)*1.5+(X85-3)*3.1)>0,+((W85-3)*1.5+(X85-3)*3.1),0))) -> -14.885 | AF85: =(L85-O85)*(R85-U85)*Q85*V85/100 -> -7.8023764 | AG85: =+IF(D85="RONALD WILLIAN GARIBAY ESCUDERO",AC85+AD85+AE85+AF85+70,AC85+AD85+AE85+AF85)+70-53 -> 36.46218 | AH85: =31.1035*L85*Q85*1.1023*K85/100 -> 56.071733 | AI85: =+((+$AI$2-R85+U85)*L85*Q85*V85)/100 -> 48.011827 | AJ85: =31.1035*1.1023*K85*P85*O85/100 -> 56.693672 | AL85: =+IF(AB85*K85>0,AB85*K85,0) -> 3432.5542
A86: IP-1100 | B86: 45686 | C86: 45678 | D86: EMPRESA MINERA MARKATA CAS S.A.C. | E86: {=XLOOKUP(D86,RUC!$B$3:$B$79,RUC!$D$3:$D$79)} -> 20606526599 | G86: 77 | H86: MINERAL | I86: 5.92 | J86: 1.2 | K86: =+I86-(I86*(J86/100)) -> 5.84896 | L86: 0.302 | M86: 0.29 | N86: 0.327 | O86: =+ROUND((M86+N86)/2,3) -> 0.309 | P86: 90 | Q86: 90.27 | R86: 2737.8 | S86: =IF((90+ROUNDDOWN(O86,1)*100)<95,95,(90+ROUNDDOWN(O86,1)*100)) -> 120 | U86: 120 | V86: 1.1023 | Y86: 20 | Z86: =IF(IF(D86="UNTUCA",IF(+((W86-3)*1.5+(X86-3)*3.1)>0,+((W86-3)*1.5+(X86-3)*3.1),0),IF(+((W86-3)*1.5+(X86-3)*3.1)>0,+((W86-3)*1.5+(X86-3)*3.1),0))<30,30,IF(D86="UNTUCA",IF(+((W86-3)*1.5+(X86-3)*3.1)>0,+((W86-3)*1.5+(X86-3)*3.1),0),IF(+((W86-3)*1.5+(X86-3)*3.1)>0,+((W86-3)*1.5+(X86-3)*3.1),0))) -> 30 | AA86: =+Y86+Z86 -> 50 | AB86: =+((O86*P86*(R86-U86)/100)-S86-AA86+T86)*V86 -> 615.09462 | AC86: =+(S86-T86)*V86-'data 1'!$F$4 -> 52.276 | AD86: =+(Q86-P86)*(R86-U86)*L86*V86/100 -> 2.352919 | AE86: =+(Y86*V86-70)+V86*(Z86-IF(D86="UNTUCA",IF(+((W86-3)*2.5+(X86-3)*3.1)>0,+((W86-3)*1.5+(X86-3)*3.1),0),IF(+((W86-3)*1.5+(X86-3)*3.1)>0,+((W86-3)*1.5+(X86-3)*3.1),0))) -> -14.885 | AF86: =(L86-O86)*(R86-U86)*Q86*V86/100 -> -18.233824 | AG86: =+IF(D86="RONALD WILLIAN GARIBAY ESCUDERO",AC86+AD86+AE86+AF86+70,AC86+AD86+AE86+AF86)+70-53 -> 38.510095 | AH86: =31.1035*L86*Q86*1.1023*K86/100 -> 54.668619 | AI86: =+((+$AI$2-R86+U86)*L86*Q86*V86)/100 -> 60.7619 | AJ86: =31.1035*1.1023*K86*P86*O86/100 -> 55.768467 | AL86: =+IF(AB86*K86>0,AB86*K86,0) -> 3597.6638
A87: IP-1115 | B87: 45685 | C87: 45682 | D87: MELCHOR AGUSTIN VERA PACHECO | E87: {=XLOOKUP(D87,RUC!$B$3:$B$79,RUC!$D$3:$D$79)} -> 10082235774 | G87: 52 | H87: MINERAL | I87: 4.83 | J87: 1.5 | K87: =+I87-(I87*(J87/100)) -> 4.75755 | L87: 0.163 | M87: 0.161 | N87: 0.161 | O87: =+ROUND((M87+N87)/2,3) -> 0.161 | P87: 85 | Q87: 89.89 | R87: 2776.8 | S87: 95 | U87: 80 | V87: 1.1023 | Z87: 10 | AA87: =+Y87+Z87 -> 10 | AB87: =+((O87*P87*(R87-U87)/100)-S87-AA87+T87)*V87 -> 291.07012 | AC87: =+(S87-T87)*V87-'data 1'!$F$4 -> 24.7185 | AD87: =+(Q87-P87)*(R87-U87)*L87*V87/100 -> 23.694362 | AE87: =+(Y87*V87-70)+V87*(Z87-IF(D87="UNTUCA",IF(+((W87-3)*2.5+(X87-3)*3.1)>0,+((W87-3)*1.5+(X87-3)*3.1),0),IF(+((W87-3)*1.5+(X87-3)*3.1)>0,+((W87-3)*1.5+(X87-3)*3.1),0))) -> -58.977 | AF87: =(L87-O87)*(R87-U87)*Q87*V87/100 -> 5.3442888 | AG87: =+IF(D87="RONALD WILLIAN GARIBAY ESCUDERO",AC87+AD87+AE87+AF87+70,AC87+AD87+AE87+AF87)+70 -> 64.78015 | AH87: =31.1035*L87*Q87*1.1023*K87/100 -> 23.899643 | AI87: =+((+$AI$2-R87+U87)*L87*Q87*V87)/100 -> 19.898003 | AJ87: =31.1035*1.1023*K87*P87*O87/100 -> 22.322212 | AL87: =+IF(AB87*K87>0,AB87*K87,0) -> 1384.7806
A88: IP-1116 | B88: 45685 | C88: 45682 | D88: MELCHOR AGUSTIN VERA PACHECO | E88: {=XLOOKUP(D88,RUC!$B$3:$B$79,RUC!$D$3:$D$79)} -> 10082235774 | G88: 49 | H88: MINERAL | I88: 4.91 | J88: 1.7 | K88: =+I88-(I88*(J88/100)) -> 4.82653 | L88: 0.123 | M88: 0.121 | N88: 0.121 | O88: =+ROUND((M88+N88)/2,3) -> 0.121 | P88: 85 | Q88: 89.78 | R88: 2776.8 | S88: 95 | U88: 80 | V88: 1.1023 | Z88: 10 | AA88: =+Y88+Z88 -> 10 | AB88: =+((O88*P88*(R88-U88)/100)-S88-AA88+T88)*V88 -> 189.99891 | AC88: =+(S88-T88)*V88-'data 1'!$F$4 -> 24.7185 | AD88: =+(Q88-P88)*(R88-U88)*L88*V88/100 -> 17.47759 | AE88: =+(Y88*V88-70)+V88*(Z88-IF(D88="UNTUCA",IF(+((W88-3)*2.5+(X88-3)*3.1)>0,+((W88-3)*1.5+(X88-3)*3.1),0),IF(+((W88-3)*1.5+(X88-3)*3.1)>0,+((W88-3)*1.5+(X88-3)*3.1),0))) -> -58.977 | AF88: =(L88-O88)*(R88-U88)*Q88*V88/100 -> 5.3377489 | AG88: =+IF(D88="RONALD WILLIAN GARIBAY ESCUDERO",AC88+AD88+AE88+AF88+70,AC88+AD88+AE88+AF88)+70 -> 58.556839 | AH88: =31.1035*L88*Q88*1.1023*K88/100 -> 18.273797 | AI88: =+((+$AI$2-R88+U88)*L88*Q88*V88)/100 -> 14.996684 | AJ88: =31.1035*1.1023*K88*P88*O88/100 -> 17.019562 | AL88: =+IF(AB88*K88>0,AB88*K88,0) -> 917.03544
A89: IP-1117 | B89: 45685 | C89: 45682 | D89: MELCHOR AGUSTIN VERA PACHECO | E89: {=XLOOKUP(D89,RUC!$B$3:$B$79,RUC!$D$3:$D$79)} -> 10082235774 | G89: 44 | H89: MINERAL | I89: 4.62 | J89: 1.8 | K89: =+I89-(I89*(J89/100)) -> 4.53684 | L89: 0.487 | M89: 0.48 | N89: 0.48 | O89: =+ROUND((M89+N89)/2,3) -> 0.48 | P89: 90 | Q89: 90.21 | R89: 2776.8 | S89: 115 | U89: 80 | V89: 1.1023 | Z89: 10 | AA89: =+Y89+Z89 -> 10 | AB89: =+((O89*P89*(R89-U89)/100)-S89-AA89+T89)*V89 -> 1146.4114 | AC89: =+(S89-T89)*V89-'data 1'!$F$4 -> 46.7645 | AD89: =+(Q89-P89)*(R89-U89)*L89*V89/100 -> 3.0401625 | AE89: =+(Y89*V89-70)+V89*(Z89-IF(D89="UNTUCA",IF(+((W89-3)*2.5+(X89-3)*3.1)>0,+((W89-3)*1.5+(X89-3)*3.1),0),IF(+((W89-3)*1.5+(X89-3)*3.1)>0,+((W89-3)*1.5+(X89-3)*3.1),0))) -> -58.977 | AF89: =(L89-O89)*(R89-U89)*Q89*V89/100 -> 18.771599 | AG89: =+IF(D89="RONALD WILLIAN GARIBAY ESCUDERO",AC89+AD89+AE89+AF89+70,AC89+AD89+AE89+AF89)+70 -> 79.599262 | AH89: =31.1035*L89*Q89*1.1023*K89/100 -> 68.335469 | AI89: =+((+$AI$2-R89+U89)*L89*Q89*V89)/100 -> 59.661499 | AJ89: =31.1035*1.1023*K89*P89*O89/100 -> 67.196442 | AL89: =+IF(AB89*K89>0,AB89*K89,0) -> 5201.0851
A90: IP-1118 | B90: 45685 | C90: 45682 | D90: MELCHOR AGUSTIN VERA PACHECO | E90: {=XLOOKUP(D90,RUC!$B$3:$B$79,RUC!$D$3:$D$79)} -> 10082235774 | G90: 48 | H90: MINERAL | I90: 4.61 | J90: 1.1 | K90: =+I90-(I90*(J90/100)) -> 4.55929 | L90: 0.216 | M90: 0.212 | N90: 0.212 | O90: =+ROUND((M90+N90)/2,3) -> 0.212 | P90: 90 | Q90: 90.17 | R90: 2776.8 | S90: 105 | U90: 80 | V90: 1.1023 | Z90: 10 | AA90: =+Y90+Z90 -> 10 | AB90: =+((O90*P90*(R90-U90)/100)-S90-AA90+T90)*V90 -> 440.42335 | AC90: =+(S90-T90)*V90-'data 1'!$F$4 -> 35.7415 | AD90: =+(Q90-P90)*(R90-U90)*L90*V90/100 -> 1.0915691 | AE90: =+(Y90*V90-70)+V90*(Z90-IF(D90="UNTUCA",IF(+((W90-3)*2.5+(X90-3)*3.1)>0,+((W90-3)*1.5+(X90-3)*3.1),0),IF(+((W90-3)*1.5+(X90-3)*3.1)>0,+((W90-3)*1.5+(X90-3)*3.1),0))) -> -58.977 | AF90: =(L90-O90)*(R90-U90)*Q90*V90/100 -> 10.721872 | AG90: =+IF(D90="RONALD WILLIAN GARIBAY ESCUDERO",AC90+AD90+AE90+AF90+70,AC90+AD90+AE90+AF90)+70 -> 58.577941 | AH90: =31.1035*L90*Q90*1.1023*K90/100 -> 30.44543 | AI90: =+((+$AI$2-R90+U90)*L90*Q90*V90)/100 -> 26.45004 | AJ90: =31.1035*1.1023*K90*P90*O90/100 -> 29.825289 | AL90: =+IF(AB90*K90>0,AB90*K90,0) -> 2008.0178
A91: IP-1119 | B91: 45685 | C91: 45682 | D91: MELCHOR AGUSTIN VERA PACHECO | E91: {=XLOOKUP(D91,RUC!$B$3:$B$79,RUC!$D$3:$D$79)} -> 10082235774 | G91: 44 | H91: MINERAL | I91: 4.37 | J91: 1.7 | K91: =+I91-(I91*(J91/100)) -> 4.29571 | L91: 0.31 | M91: 0.305 | N91: 0.305 | O91: =+ROUND((M91+N91)/2,3) -> 0.305 | P91: 90 | Q91: 90.26 | R91: 2776.8 | S91: 110 | U91: 80 | V91: 1.1023 | Z91: 10 | AA91: =+Y91+Z91 -> 10 | AB91: =+((O91*P91*(R91-U91)/100)-S91-AA91+T91)*V91 -> 683.72538 | AC91: =+(S91-T91)*V91-'data 1'!$F$4 -> 41.253 | AD91: =+(Q91-P91)*(R91-U91)*L91*V91/100 -> 2.3959822 | AE91: =+(Y91*V91-70)+V91*(Z91-IF(D91="UNTUCA",IF(+((W91-3)*2.5+(X91-3)*3.1)>0,+((W91-3)*1.5+(X91-3)*3.1),0),IF(+((W91-3)*1.5+(X91-3)*3.1)>0,+((W91-3)*1.5+(X91-3)*3.1),0))) -> -58.977 | AF91: =(L91-O91)*(R91-U91)*Q91*V91/100 -> 13.415717 | AG91: =+IF(D91="RONALD WILLIAN GARIBAY ESCUDERO",AC91+AD91+AE91+AF91+70,AC91+AD91+AE91+AF91)+70 -> 68.087699 | AH91: =31.1035*L91*Q91*1.1023*K91/100 -> 41.209851 | AI91: =+((+$AI$2-R91+U91)*L91*Q91*V91)/100 -> 37.998595 | AJ91: =31.1035*1.1023*K91*P91*O91/100 -> 40.428383 | AL91: =+IF(AB91*K91>0,AB91*K91,0) -> 2937.086
A92: IP-1120 | B92: 45685 | C92: 45682 | D92: COMPAÑÍA MINERA CIKAM PERU SAC | E92: {=XLOOKUP(D92,RUC!$B$3:$B$79,RUC!$D$3:$D$79)} -> 20517242919 | G92: 41 | H92: MINERAL | I92: 3.92 | J92: 1.1 | K92: =+I92-(I92*(J92/100)) -> 3.87688 | L92: 0.17 | M92: 0.167 | N92: 0.167 | O92: =+ROUND((M92+N92)/2,3) -> 0.167 | P92: 85 | Q92: 89.92 | R92: 2776.8 | S92: 95 | U92: 80 | V92: 1.1023 | Z92: 10 | AA92: =+Y92+Z92 -> 10 | AB92: =+((O92*P92*(R92-U92)/100)-S92-AA92+T92)*V92 -> 306.2308 | AC92: =+(S92-T92)*V92-'data 1'!$F$4 -> 24.7185 | AD92: =+(Q92-P92)*(R92-U92)*L92*V92/100 -> 24.863518 | AE92: =+(Y92*V92-70)+V92*(Z92-IF(D92="UNTUCA",IF(+((W92-3)*2.5+(X92-3)*3.1)>0,+((W92-3)*1.5+(X92-3)*3.1),0),IF(+((W92-3)*1.5+(X92-3)*3.1)>0,+((W92-3)*1.5+(X92-3)*3.1),0))) -> -58.977 | AF92: =(L92-O92)*(R92-U92)*Q92*V92/100 -> 8.0191087 | AG92: =+IF(D92="RONALD WILLIAN GARIBAY ESCUDERO",AC92+AD92+AE92+AF92+70,AC92+AD92+AE92+AF92)+70 -> 68.624126 | AH92: =31.1035*L92*Q92*1.1023*K92/100 -> 20.318734 | AI92: =+((+$AI$2-R92+U92)*L92*Q92*V92)/100 -> 20.759445 | AJ92: =31.1035*1.1023*K92*P92*O92/100 -> 18.868042 | AL92: =+IF(AB92*K92>0,AB92*K92,0) -> 1187.2201
A93: IP-1121 | B93: 45685 | C93: 45682 | D93: COMPAÑÍA MINERA CIKAM PERU SAC | E93: {=XLOOKUP(D93,RUC!$B$3:$B$79,RUC!$D$3:$D$79)} -> 20517242919 | G93: 42 | H93: MINERAL | I93: 4.22 | J93: 1.9 | K93: =+I93-(I93*(J93/100)) -> 4.13982 | L93: 0.366 | M93: 0.36 | N93: 0.36 | O93: =+ROUND((M93+N93)/2,3) -> 0.36 | P93: 90 | Q93: 90.13 | R93: 2776.8 | S93: 110 | U93: 80 | V93: 1.1023 | Z93: 10 | AA93: =+Y93+Z93 -> 10 | AB93: =+((O93*P93*(R93-U93)/100)-S93-AA93+T93)*V93 -> 830.87318 | AC93: =+(S93-T93)*V93-'data 1'!$F$4 -> 41.253 | AD93: =+(Q93-P93)*(R93-U93)*L93*V93/100 -> 1.4144024 | AE93: =+(Y93*V93-70)+V93*(Z93-IF(D93="UNTUCA",IF(+((W93-3)*2.5+(X93-3)*3.1)>0,+((W93-3)*1.5+(X93-3)*3.1),0),IF(+((W93-3)*1.5+(X93-3)*3.1)>0,+((W93-3)*1.5+(X93-3)*3.1),0))) -> -58.977 | AF93: =(L93-O93)*(R93-U93)*Q93*V93/100 -> 16.075673 | AG93: =+IF(D93="RONALD WILLIAN GARIBAY ESCUDERO",AC93+AD93+AE93+AF93+70,AC93+AD93+AE93+AF93)+70 -> 69.766076 | AH93: =31.1035*L93*Q93*1.1023*K93/100 -> 46.821032 | AI93: =+((+$AI$2-R93+U93)*L93*Q93*V93)/100 -> 44.798242 | AJ93: =31.1035*1.1023*K93*P93*O93/100 -> 45.987049 | AL93: =+IF(AB93*K93>0,AB93*K93,0) -> 3439.6654
A94: IP-1122 | B94: 45685 | C94: 45682 | D94: COMPAÑÍA MINERA CIKAM PERU SAC | E94: {=XLOOKUP(D94,RUC!$B$3:$B$79,RUC!$D$3:$D$79)} -> 20517242919 | G94: 73 | H94: MINERAL | I94: 6.96 | J94: 1.3 | K94: =+I94-(I94*(J94/100)) -> 6.86952 | L94: 0.175 | M94: 0.172 | N94: 0.172 | O94: =+ROUND((M94+N94)/2,3) -> 0.172 | P94: 85 | Q94: 89.88 | R94: 2776.8 | S94: 95 | U94: 80 | V94: 1.1023 | Z94: 10 | AA94: =+Y94+Z94 -> 10 | AB94: =+((O94*P94*(R94-U94)/100)-S94-AA94+T94)*V94 -> 318.8647 | AC94: =+(S94-T94)*V94-'data 1'!$F$4 -> 24.7185 | AD94: =+(Q94-P94)*(R94-U94)*L94*V94/100 -> 25.38671 | AE94: =+(Y94*V94-70)+V94*(Z94-IF(D94="UNTUCA",IF(+((W94-3)*2.5+(X94-3)*3.1)>0,+((W94-3)*1.5+(X94-3)*3.1),0),IF(+((W94-3)*1.5+(X94-3)*3.1)>0,+((W94-3)*1.5+(X94-3)*3.1),0))) -> -58.977 | AF94: =(L94-O94)*(R94-U94)*Q94*V94/100 -> 8.0155415 | AG94: =+IF(D94="RONALD WILLIAN GARIBAY ESCUDERO",AC94+AD94+AE94+AF94+70,AC94+AD94+AE94+AF94)+70 -> 69.143751 | AH94: =31.1035*L94*Q94*1.1023*K94/100 -> 37.045595 | AI94: =+((+$AI$2-R94+U94)*L94*Q94*V94)/100 -> 21.36051 | AJ94: =31.1035*1.1023*K94*P94*O94/100 -> 34.433632 | AL94: =+IF(AB94*K94>0,AB94*K94,0) -> 2190.4474

Sheet 18
AG1: Profit Terminos | AH1: Au Real (con Rec) | AI1: Profit RC | AJ1: Au Comprado | AL1: Valor
I2: =SUBTOTAL(9,I4:I9246) -> 629.56 | K2: =SUBTOTAL(9,K4:K9246) -> 604.60735 | L2: =SUMPRODUCT(L5:L90,K5:K90)/K2 -> 0.36407714 | Q2: =+SUMPRODUCT(Q5:Q62,AH5:AH62)/SUM(AH5:AH62) -> 90.047409 | R2: =+SUMPRODUCT(R5:R62,AH5:AH62)/SUM(AH5:AH62) -> 2746.4108 | AG2: =SUMPRODUCT($AG5:$AG886,$K5:$K886)/SUM($K5:$K886) -> 66.038922 | AI2: 2900
A3: Lote | B3: F emision | C3: F recepcion | D3: Nombre | E3: RUC | F3: Minero | G3: Sacos | I3: TMH | J3: %H2O | K3: TMS | L3: Oz/tc Planta | M3: Oz/tc comercial | N3: Oz/tc Minero | O3: Oz/tc Pomedio | P3: % Rec Liq | Q3: % Rec Planta | R3: Inter US$ | S3: TC US$ x tc | T3: Bono | U3: Riesgo | V3: Factor | W3: Soda | X3: Cianuro | Y3: Gasto acopio x tm | Z3: Insumos planta x tm | AA3: Insumos liq x tm | AB3: Precio x TMS | AC3: profit maquila | AD3: Profit Rec | AE3: Profit Consumo | AF3: Profit Leyes | AG3: Profit Total $/TM | AH3: =SUBTOTAL(9,AH5:AH9247) -> 6791.7303 | AI3: =SUMPRODUCT(K5:K62,AI5:AI62)/K2 -> 61.117475 | AJ3: =SUBTOTAL(9,AJ5:AJ9247) -> 6638.7725 | AL3: =SUBTOTAL(9,AL5:AL9247) -> 476936.16 | AM3: 6138
AM4: 7010
A5: IP-1031 | C5: 45660 | D5: LLASA YUCRA YOLANDA | E5: {=XLOOKUP(D5,RUC!$B$3:$B$79,RUC!$D$3:$D$79)} -> #N/A | G5: 60 | H5: MINERAL | I5: 4.78 | J5: 1.4 | K5: =+I5-(I5*(J5/100)) -> 4.71308 | L5: 0.07 | M5: 0.067 | N5: 0.067 | O5: =+ROUND((M5+N5)/2,3) -> 0.067 | P5: 80 | Q5: 87.92 | R5: 2646.8 | S5: =IF((90+ROUNDDOWN(O5,1)*100)<95,95,(90+ROUNDDOWN(O5,1)*100)) -> 95 | U5: 120 | V5: 1.1023 | Y5: 30 | Z5: =IF(IF(D5="UNTUCA",IF(+((W5-3)*1.5+(X5-3)*3.1)>0,+((W5-3)*1.5+(X5-3)*3.1),0),IF(+((W5-3)*1.5+(X5-3)*3.1)>0,+((W5-3)*1.5+(X5-3)*3.1),0))<30,30,IF(D5="UNTUCA",IF(+((W5-3)*1.5+(X5-3)*3.1)>0,+((W5-3)*1.5+(X5-3)*3.1),0),IF(+((W5-3)*1.5+(X5-3)*3.1)>0,+((W5-3)*1.5+(X5-3)*3.1),0))) -> 30 | AA5: =+Y5+Z5 -> 60 | AB5: =+((O5*P5*(R5-U5)/100)-S5-AA5+T5)*V5 -> -21.564868 | AC5: =+(S5-T5)*V5-'data 1'!$F$4 -> 24.7185 | AD5: =+(Q5-P5)*(R5-U5)*L5*V5/100 -> 15.441657 | AE5: =+(Y5*V5-70)+V5*(Z5-IF(D5="UNTUCA",IF(+((W5-3)*2.5+(X5-3)*3.1)>0,+((W5-3)*1.5+(X5-3)*3.1),0),IF(+((W5-3)*1.5+(X5-3)*3.1)>0,+((W5-3)*1.5+(X5-3)*3.1),0))) -> -3.862 | AF5: =(L5-O5)*(R5-U5)*Q5*V5/100 -> 7.3464852 | AG5: =+IF(D5="RONALD WILLIAN GARIBAY ESCUDERO",AC5+AD5+AE5+AF5+70,AC5+AD5+AE5+AF5)+70-53 -> 60.644642 | AH5: =31.1035*L5*Q5*1.1023*K5/100 -> 9.9448812 | AI5: =+((+$AI$2-R5+U5)*L5*Q5*V5)/100 -> 25.31787 | AJ5: =31.1035*1.1023*K5*P5*O5/100 -> 8.661212 | AL5: =+IF(AB5*K5>0,AB5*K5,0) -> 0 | AM5: 499
A6: IP-1076 | B6: 45677 | C6: 45671 | D6: MINERA AURIFERA 2 DE DICIEMBRE CALPA RENACE S.A. | E6: {=XLOOKUP(D6,RUC!$B$3:$B$79,RUC!$D$3:$D$79)} -> #N/A | G6: 38 | H6: MINERAL | I6: 4.05 | J6: 1.1 | K6: =+I6-(I6*(J6/100)) -> 4.00545 | L6: 1.65 | M6: 1.584 | N6: 1.634 | O6: =+ROUND((M6+N6)/2,3) -> 1.609 | P6: 90 | Q6: 89.82 | R6: 2667 | S6: 190 | U6: 90 | V6: 1.1023 | Z6: 25 | AA6: =+Y6+Z6 -> 25 | AB6: =+((O6*P6*(R6-U6)/100)-S6-AA6+T6)*V6 -> 3876.5176 | AC6: =+(S6-T6)*V6-'data 1'!$F$4 -> 129.437 | AD6: =+(Q6-P6)*(R6-U6)*L6*V6/100 -> -8.4366625 | AE6: =+(Y6*V6-70)+V6*(Z6-IF(D6="UNTUCA",IF(+((W6-3)*2.5+(X6-3)*3.1)>0,+((W6-3)*1.5+(X6-3)*3.1),0),IF(+((W6-3)*1.5+(X6-3)*3.1)>0,+((W6-3)*1.5+(X6-3)*3.1),0))) -> -42.4425 | AF6: =(L6-O6)*(R6-U6)*Q6*V6/100 -> 104.6095 | AG6: =+IF(D6="RONALD WILLIAN GARIBAY ESCUDERO",AC6+AD6+AE6+AF6+70,AC6+AD6+AE6+AF6)+70-30-5-3 -> 215.16734 | AH6: =31.1035*L6*Q6*1.1023*K6/100 -> 203.52482 | AI6: =+((+$AI$2-R6+U6)*L6*Q6*V6)/100 -> 527.66626 | AJ6: =31.1035*1.1023*K6*P6*O6/100 -> 198.86527 | AL6: =+IF(AB6*K6>0,AB6*K6,0) -> 15527.197 | AM6: =+AM4+AM5-AM3 -> 1371
A7: IP-1077 | B7: 45677 | C7: 45671 | D7: MINERA AURIFERA 2 DE DICIEMBRE CALPA RENACE S.A. | E7: {=XLOOKUP(D7,RUC!$B$3:$B$79,RUC!$D$3:$D$79)} -> #N/A | G7: 55 | H7: MINERAL | I7: 6.7 | J7: 1.2 | K7: =+I7-(I7*(J7/100)) -> 6.6196 | L7: 2.494 | M7: 2.394 | N7: 2.561 | O7: =+ROUND((M7+N7)/2,3) -> 2.478 | P7: 90 | Q7: 89.87 | R7: 2667 | S7: 190 | U7: 90 | V7: 1.1023 | Z7: 25 | AA7: =+Y7+Z7 -> 25 | AB7: =+((O7*P7*(R7-U7)/100)-S7-AA7+T7)*V7 -> 6098.1721 | AC7: =+(S7-T7)*V7-'data 1'!$F$4 -> 129.437 | AD7: =+(Q7-P7)*(R7-U7)*L7*V7/100 -> -9.2098812 | AE7: =+(Y7*V7-70)+V7*(Z7-IF(D7="UNTUCA",IF(+((W7-3)*2.5+(X7-3)*3.1)>0,+((W7-3)*1.5+(X7-3)*3.1),0),IF(+((W7-3)*1.5+(X7-3)*3.1)>0,+((W7-3)*1.5+(X7-3)*3.1),0))) -> -42.4425 | AF7: =(L7-O7)*(R7-U7)*Q7*V7/100 -> 40.845945 | AG7: =+IF(D7="RONALD WILLIAN GARIBAY ESCUDERO",AC7+AD7+AE7+AF7+70,AC7+AD7+AE7+AF7)+70-30-5-3 -> 150.63056 | AH7: =31.1035*L7*Q7*1.1023*K7/100 -> 508.6886 | AI7: =+((+$AI$2-R7+U7)*L7*Q7*V7)/100 -> 798.01953 | AJ7: =31.1035*1.1023*K7*P7*O7/100 -> 506.15628 | AL7: =+IF(AB7*K7>0,AB7*K7,0) -> 40367.46 | AM7: 600 | AN7: rec
A8: IP-1078 | B8: 45677 | C8: 45671 | D8: MINERA AURIFERA 2 DE DICIEMBRE CALPA RENACE S.A. | E8: {=XLOOKUP(D8,RUC!$B$3:$B$79,RUC!$D$3:$D$79)} -> #N/A | G8: 45 | H8: MINERAL | I8: 6.2 | J8: 1.1 | K8: =+I8-(I8*(J8/100)) -> 6.1318 | L8: 0.789 | M8: 0.757 | N8: 0.757 | O8: =+ROUND((M8+N8)/2,3) -> 0.757 | P8: 90 | Q8: 90.16 | R8: 2667 | S8: =IF((90+ROUNDDOWN(O8,1)*100)<95,95,(90+ROUNDDOWN(O8,1)*100))-5 -> 155 | U8: 90 | V8: 1.1023 | Z8: 25 | AA8: =+Y8+Z8 -> 25 | AB8: =+((O8*P8*(R8-U8)/100)-S8-AA8+T8)*V8 -> 1736.9052 | AC8: =+(S8-T8)*V8-'data 1'!$F$4 -> 90.8565 | AD8: =+(Q8-P8)*(R8-U8)*L8*V8/100 -> 3.5860077 | AE8: =+(Y8*V8-70)+V8*(Z8-IF(D8="UNTUCA",IF(+((W8-3)*2.5+(X8-3)*3.1)>0,+((W8-3)*1.5+(X8-3)*3.1),0),IF(+((W8-3)*1.5+(X8-3)*3.1)>0,+((W8-3)*1.5+(X8-3)*3.1),0))) -> -42.4425 | AF8: =(L8-O8)*(R8-U8)*Q8*V8/100 -> 81.955501 | AG8: =+IF(D8="RONALD WILLIAN GARIBAY ESCUDERO",AC8+AD8+AE8+AF8+70,AC8+AD8+AE8+AF8)+70-30-5-3 -> 165.95551 | AH8: =31.1035*L8*Q8*1.1023*K8/100 -> 149.55053 | AI8: =+((+$AI$2-R8+U8)*L8*Q8*V8)/100 -> 253.27553 | AJ8: =31.1035*1.1023*K8*P8*O8/100 -> 143.23048 | AL8: =+IF(AB8*K8>0,AB8*K8,0) -> 10650.356 | AM8: =+AM6-AM7 -> 771
A9: IP-1079 | B9: 45677 | C9: 45671 | D9: MINERA AURIFERA 2 DE DICIEMBRE CALPA RENACE S.A. | E9: {=XLOOKUP(D9,RUC!$B$3:$B$79,RUC!$D$3:$D$79)} -> #N/A | G9: 50 | H9: MINERAL | I9: 6.67 | J9: 1.2 | K9: =+I9-(I9*(J9/100)) -> 6.58996 | L9: 0.179 | M9: 0.169 | N9: 0.217 | O9: =+ROUND((M9+N9)/2,3) -> 0.193 | P9: 85 | Q9: 90.23 | R9: 2667 | S9: =IF((90+ROUNDDOWN(O9,1)*100)<95,95,(90+ROUNDDOWN(O9,1)*100))-5 -> 95 | U9: 90 | V9: 1.1023 | Z9: 25 | AA9: =+Y9+Z9 -> 25 | AB9: =+((O9*P9*(R9-U9)/100)-S9-AA9+T9)*V9 -> 333.72888 | AC9: =+(S9-T9)*V9-'data 1'!$F$4 -> 24.7185 | AD9: =+(Q9-P9)*(R9-U9)*L9*V9/100 -> 26.593099 | AE9: =+(Y9*V9-70)+V9*(Z9-IF(D9="UNTUCA",IF(+((W9-3)*2.5+(X9-3)*3.1)>0,+((W9-3)*1.5+(X9-3)*3.1),0),IF(+((W9-3)*1.5+(X9-3)*3.1)>0,+((W9-3)*1.5+(X9-3)*3.1),0))) -> -42.4425 | AF9: =(L9-O9)*(R9-U9)*Q9*V9/100 -> -35.88337 | AG9: =+IF(D9="RONALD WILLIAN GARIBAY ESCUDERO",AC9+AD9+AE9+AF9+70,AC9+AD9+AE9+AF9)+70-30-5-3 -> 4.9857291 | AH9: =31.1035*L9*Q9*1.1023*K9/100 -> 36.491846 | AI9: =+((+$AI$2-R9+U9)*L9*Q9*V9)/100 -> 57.505094 | AJ9: =31.1035*1.1023*K9*P9*O9/100 -> 37.065348 | AL9: =+IF(AB9*K9>0,AB9*K9,0) -> 2199.2599
A10: IP-1080 | B10: 45677 | C10: 45671 | D10: MINERA AURIFERA 2 DE DICIEMBRE CALPA RENACE S.A. | E10: {=XLOOKUP(D10,RUC!$B$3:$B$79,RUC!$D$3:$D$79)} -> #N/A | G10: 27 | H10: MINERAL | I10: 3.07 | J10: 1.3 | K10: =+I10-(I10*(J10/100)) -> 3.03009 | L10: 0.467 | M10: 0.448 | N10: 0.448 | O10: =+ROUND((M10+N10)/2,3) -> 0.448 | P10: 90 | Q10: 90.18 | R10: 2667 | S10: =IF((90+ROUNDDOWN(O10,1)*100)<95,95,(90+ROUNDDOWN(O10,1)*100))-5 -> 125 | U10: 90 | V10: 1.1023 | Z10: 25 | AA10: =+Y10+Z10 -> 25 | AB10: =+((O10*P10*(R10-U10)/100)-S10-AA10+T10)*V10 -> 979.99585 | AC10: =+(S10-T10)*V10-'data 1'!$F$4 -> 57.7875 | AD10: =+(Q10-P10)*(R10-U10)*L10*V10/100 -> 2.3878311 | AE10: =+(Y10*V10-70)+V10*(Z10-IF(D10="UNTUCA",IF(+((W10-3)*2.5+(X10-3)*3.1)>0,+((W10-3)*1.5+(X10-3)*3.1),0),IF(+((W10-3)*1.5+(X10-3)*3.1)>0,+((W10-3)*1.5+(X10-3)*3.1),0))) -> -42.4425 | AF10: =(L10-O10)*(R10-U10)*Q10*V10/100 -> 48.671873 | AG10: =+IF(D10="RONALD WILLIAN GARIBAY ESCUDERO",AC10+AD10+AE10+AF10+70,AC10+AD10+AE10+AF10)+70-30-5-3 -> 98.404704 | AH10: =31.1035*L10*Q10*1.1023*K10/100 -> 43.751375 | AI10: =+((+$AI$2-R10+U10)*L10*Q10*V10)/100 -> 149.94412 | AJ10: =31.1035*1.1023*K10*P10*O10/100 -> 41.887566 | AL10: =+IF(AB10*K10>0,AB10*K10,0) -> 2969.4756
A11: IP-1081 | B11: 45677 | C11: 45671 | D11: MINERA AURIFERA 2 DE DICIEMBRE CALPA RENACE S.A. | E11: {=XLOOKUP(D11,RUC!$B$3:$B$79,RUC!$D$3:$D$79)} -> #N/A | G11: 25 | H11: MINERAL | I11: 3.5 | J11: 1.2 | K11: =+I11-(I11*(J11/100)) -> 3.458 | L11: 0.761 | M11: 0.73 | N11: 0.799 | O11: =+ROUND((M11+N11)/2,3) -> 0.765 | P11: 90 | Q11: 90.2 | R11: 2667 | S11: =IF((90+ROUNDDOWN(O11,1)*100)<95,95,(90+ROUNDDOWN(O11,1)*100))-5 -> 155 | U11: 90 | V11: 1.1023 | Z11: 25 | AA11: =+Y11+Z11 -> 25 | AB11: =+((O11*P11*(R11-U11)/100)-S11-AA11+T11)*V11 -> 1757.3578 | AC11: =+(S11-T11)*V11-'data 1'!$F$4 -> 90.8565 | AD11: =+(Q11-P11)*(R11-U11)*L11*V11/100 -> 4.3234344 | AE11: =+(Y11*V11-70)+V11*(Z11-IF(D11="UNTUCA",IF(+((W11-3)*2.5+(X11-3)*3.1)>0,+((W11-3)*1.5+(X11-3)*3.1),0),IF(+((W11-3)*1.5+(X11-3)*3.1)>0,+((W11-3)*1.5+(X11-3)*3.1),0))) -> -42.4425 | AF11: =(L11-O11)*(R11-U11)*Q11*V11/100 -> -10.248983 | AG11: =+IF(D11="RONALD WILLIAN GARIBAY ESCUDERO",AC11+AD11+AE11+AF11+70,AC11+AD11+AE11+AF11)+70-30-5-3 -> 74.488452 | AH11: =31.1035*L11*Q11*1.1023*K11/100 -> 81.381418 | AI11: =+((+$AI$2-R11+U11)*L11*Q11*V11)/100 -> 244.39568 | AJ11: =31.1035*1.1023*K11*P11*O11/100 -> 81.627783 | AL11: =+IF(AB11*K11>0,AB11*K11,0) -> 6076.9431
A12: IP-1095 | B12: 45685 | C12: 45675 | D12: SOTOMAYOR CORAZAO WISTHERMUNDO | E12: {=XLOOKUP(D12,RUC!$B$3:$B$79,RUC!$D$3:$D$79)} -> 10416085884 | G12: AGRANEL | H12: MINERAL | I12: 30.53 | J12: 5.65 | K12: =+I12-(I12*(J12/100)) -> 28.805055 | L12: 0.154 | M12: 0.141 | N12: 0.15 | O12: =+ROUND((M12+N12)/2,3) -> 0.146 | P12: 85 | Q12: 90.22 | R12: 2715.2 | S12: 110 | U12: 90 | V12: 1.1023 | Z12: =IF(IF(D12="UNTUCA",IF(+((W12-3)*1.5+(X12-3)*3.1)>0,+((W12-3)*1.5+(X12-3)*3.1),0),IF(+((W12-3)*1.5+(X12-3)*3.1)>0,+((W12-3)*1.5+(X12-3)*3.1),0))<30,30,IF(D12="UNTUCA",IF(+((W12-3)*1.5+(X12-3)*3.1)>0,+((W12-3)*1.5+(X12-3)*3.1),0),IF(+((W12-3)*1.5+(X12-3)*3.1)>0,+((W12-3)*1.5+(X12-3)*3.1),0))) -> 30 | AA12: =+Y12+Z12 -> 30 | AB12: =+((O12*P12*(R12-U12)/100)-S12-AA12+T12)*V12 -> 204.79336 | AC12: =+(S12-T12)*V12-'data 1'!$F$4 -> 41.253 | AD12: =+(Q12-P12)*(R12-U12)*L12*V12/100 -> 23.262341 | AE12: =+(Y12*V12-70)+V12*(Z12-IF(D12="UNTUCA",IF(+((W12-3)*2.5+(X12-3)*3.1)>0,+((W12-3)*1.5+(X12-3)*3.1),0),IF(+((W12-3)*1.5+(X12-3)*3.1)>0,+((W12-3)*1.5+(X12-3)*3.1),0))) -> -36.931 | AF12: =(L12-O12)*(R12-U12)*Q12*V12/100 -> 20.885987 | AG12: =+IF(D12="RONALD WILLIAN GARIBAY ESCUDERO",AC12+AD12+AE12+AF12+70,AC12+AD12+AE12+AF12)+70-53 -> 65.470329 | AH12: =31.1035*L12*Q12*1.1023*K12/100 -> 137.21492 | AI12: =+((+$AI$2-R12+U12)*L12*Q12*V12)/100 -> 42.086235 | AJ12: =31.1035*1.1023*K12*P12*O12/100 -> 122.56023 | AL12: =+IF(AB12*K12>0,AB12*K12,0) -> 5899.0841
A13: IP-1096 | B13: 45685 | C13: 45674 | D13: QUISPE MARTINEZ IZEQUIEL | E13: {=XLOOKUP(D13,RUC!$B$3:$B$79,RUC!$D$3:$D$79)} -> 10457401928 | G13: AGRANEL | H13: MINERAL | I13: 21.2 | J13: 7.5 | K13: =+I13-(I13*(J13/100)) -> 19.61 | L13: 0.146 | M13: 0.136 | N13: 0.197 | O13: =+ROUND((M13+N13)/2,3) -> 0.167 | P13: 88 | Q13: 90.07 | R13: 2715.2 | S13: 120 | U13: 100 | V13: 1.1023 | Z13: =IF(IF(D13="UNTUCA",IF(+((W13-3)*1.5+(X13-3)*3.1)>0,+((W13-3)*1.5+(X13-3)*3.1),0),IF(+((W13-3)*1.5+(X13-3)*3.1)>0,+((W13-3)*1.5+(X13-3)*3.1),0))<30,30,IF(D13="UNTUCA",IF(+((W13-3)*1.5+(X13-3)*3.1)>0,+((W13-3)*1.5+(X13-3)*3.1),0),IF(+((W13-3)*1.5+(X13-3)*3.1)>0,+((W13-3)*1.5+(X13-3)*3.1),0))) -> 30 | AA13: =+Y13+Z13 -> 30 | AB13: =+((O13*P13*(R13-U13)/100)-S13-AA13+T13)*V13 -> 258.30173 | AC13: =+(S13-T13)*V13-'data 1'!$F$4 -> 52.276 | AD13: =+(Q13-P13)*(R13-U13)*L13*V13/100 -> 8.7122016 | AE13: =+(Y13*V13-70)+V13*(Z13-IF(D13="UNTUCA",IF(+((W13-3)*2.5+(X13-3)*3.1)>0,+((W13-3)*1.5+(X13-3)*3.1),0),IF(+((W13-3)*1.5+(X13-3)*3.1)>0,+((W13-3)*1.5+(X13-3)*3.1),0))) -> -36.931 | AF13: =(L13-O13)*(R13-U13)*Q13*V13/100 -> -54.526067 | AG13: =+IF(D13="RONALD WILLIAN GARIBAY ESCUDERO",AC13+AD13+AE13+AF13+70,AC13+AD13+AE13+AF13)+70-53 -> -13.468865 | AH13: =31.1035*L13*Q13*1.1023*K13/100 -> 88.413724 | AI13: =+((+$AI$2-R13+U13)*L13*Q13*V13)/100 -> 41.283148 | AJ13: =31.1035*1.1023*K13*P13*O13/100 -> 98.806566 | AL13: =+IF(AB13*K13>0,AB13*K13,0) -> 5065.2969
A14: IP-1097 | B14: 45685 | C14: 45674 | D14: QUISPE MARTINEZ IZEQUIEL | E14: {=XLOOKUP(D14,RUC!$B$3:$B$79,RUC!$D$3:$D$79)} -> 10457401928 | G14: AGRANEL | H14: MINERAL | I14: 15.93 | J14: 7.35 | K14: =+I14-(I14*(J14/100)) -> 14.759145 | L14: 0.161 | M14: 0.151 | N14: 0.194 | O14: =+ROUND((M14+N14)/2,3) -> 0.173 | P14: 90 | Q14: 90.15 | R14: 2715.2 | S14: 120 | U14: 100 | V14: 1.1023 | Z14: =IF(IF(D14="UNTUCA",IF(+((W14-3)*1.5+(X14-3)*3.1)>0,+((W14-3)*1.5+(X14-3)*3.1),0),IF(+((W14-3)*1.5+(X14-3)*3.1)>0,+((W14-3)*1.5+(X14-3)*3.1),0))<30,30,IF(D14="UNTUCA",IF(+((W14-3)*1.5+(X14-3)*3.1)>0,+((W14-3)*1.5+(X14-3)*3.1),0),IF(+((W14-3)*1.5+(X14-3)*3.1)>0,+((W14-3)*1.5+(X14-3)*3.1),0))) -> 30 | AA14: =+Y14+Z14 -> 30 | AB14: =+((O14*P14*(R14-U14)/100)-S14-AA14+T14)*V14 -> 283.49683 | AC14: =+(S14-T14)*V14-'data 1'!$F$4 -> 52.276 | AD14: =+(Q14-P14)*(R14-U14)*L14*V14/100 -> 0.69618049 | AE14: =+(Y14*V14-70)+V14*(Z14-IF(D14="UNTUCA",IF(+((W14-3)*2.5+(X14-3)*3.1)>0,+((W14-3)*1.5+(X14-3)*3.1),0),IF(+((W14-3)*1.5+(X14-3)*3.1)>0,+((W14-3)*1.5+(X14-3)*3.1),0))) -> -36.931 | AF14: =(L14-O14)*(R14-U14)*Q14*V14/100 -> -31.185427 | AG14: =+IF(D14="RONALD WILLIAN GARIBAY ESCUDERO",AC14+AD14+AE14+AF14+70,AC14+AD14+AE14+AF14)+70-53 -> 1.8557537 | AH14: =31.1035*L14*Q14*1.1023*K14/100 -> 73.444939 | AI14: =+((+$AI$2-R14+U14)*L14*Q14*V14)/100 -> 45.565003 | AJ14: =31.1035*1.1023*K14*P14*O14/100 -> 78.787783 | AL14: =+IF(AB14*K14>0,AB14*K14,0) -> 4184.1709
A15: IP-1098 | B15: 45680 | C15: 45676 | D15: EMPRESA MINERA MARKATA CAS S.A.C. | E15: {=XLOOKUP(D15,RUC!$B$3:$B$79,RUC!$D$3:$D$79)} -> 20606526599 | G15: 146 | H15: MINERAL | I15: 11.98 | J15: 1.3 | K15: =+I15-(I15*(J15/100)) -> 11.82426 | L15: 0.427 | M15: 0.409 | N15: 0.44 | O15: =+ROUND((M15+N15)/2,3) -> 0.425 | P15: 90 | Q15: 90.23 | R15: 2707.15 | S15: =IF((90+ROUNDDOWN(O15,1)*100)<95,95,(90+ROUNDDOWN(O15,1)*100)) -> 130 | U15: 120 | V15: 1.1023 | Y15: 20 | Z15: =IF(IF(D15="UNTUCA",IF(+((W15-3)*1.5+(X15-3)*3.1)>0,+((W15-3)*1.5+(X15-3)*3.1),0),IF(+((W15-3)*1.5+(X15-3)*3.1)>0,+((W15-3)*1.5+(X15-3)*3.1),0))<30,30,IF(D15="UNTUCA",IF(+((W15-3)*1.5+(X15-3)*3.1)>0,+((W15-3)*1.5+(X15-3)*3.1),0),IF(+((W15-3)*1.5+(X15-3)*3.1)>0,+((W15-3)*1.5+(X15-3)*3.1),0))) -> 30 | AA15: =+Y15+Z15 -> 50 | AB15: =+((O15*P15*(R15-U15)/100)-S15-AA15+T15)*V15 -> 892.40541 | AC15: =+(S15-T15)*V15-'data 1'!$F$4 -> 63.299 | AD15: =+(Q15-P15)*(R15-U15)*L15*V15/100 -> 2.8007679 | AE15: =+(Y15*V15-70)+V15*(Z15-IF(D15="UNTUCA",IF(+((W15-3)*2.5+(X15-3)*3.1)>0,+((W15-3)*1.5+(X15-3)*3.1),0),IF(+((W15-3)*1.5+(X15-3)*3.1)>0,+((W15-3)*1.5+(X15-3)*3.1),0))) -> -14.885 | AF15: =(L15-O15)*(R15-U15)*Q15*V15/100 -> 5.1463862 | AG15: =+IF(D15="RONALD WILLIAN GARIBAY ESCUDERO",AC15+AD15+AE15+AF15+70,AC15+AD15+AE15+AF15)+70-53 -> 73.361154 | AH15: =31.1035*L15*Q15*1.1023*K15/100 -> 156.19311 | AI15: =+((+$AI$2-R15+U15)*L15*Q15*V15)/100 -> 132.86629 | AJ15: =31.1035*1.1023*K15*P15*O15/100 -> 155.06525 | AL15: =+IF(AB15*K15>0,AB15*K15,0) -> 10552.034
A16: IP-1101 | B16: 45681 | C16: 45678 | D16: EMPRESA MINERA MARKATA CAS S.A.C. | E16: {=XLOOKUP(D16,RUC!$B$3:$B$79,RUC!$D$3:$D$79)} -> 20606526599 | G16: 200 | H16: MINERAL | I16: 12.64 | J16: 1.3 | K16: =+I16-(I16*(J16/100)) -> 12.47568 | L16: 0.25 | M16: 0.24 | N16: 0.24 | O16: =+ROUND((M16+N16)/2,3) -> 0.24 | P16: 90 | Q16: 90.19 | R16: 2737.8 | S16: =IF((90+ROUNDDOWN(O16,1)*100)<95,95,(90+ROUNDDOWN(O16,1)*100)) -> 110 | U16: 120 | V16: 1.1023 | Y16: 20 | Z16: =IF(IF(D16="UNTUCA",IF(+((W16-3)*1.5+(X16-3)*3.1)>0,+((W16-3)*1.5+(X16-3)*3.1),0),IF(+((W16-3)*1.5+(X16-3)*3.1)>0,+((W16-3)*1.5+(X16-3)*3.1),0))<30,30,IF(D16="UNTUCA",IF(+((W16-3)*1.5+(X16-3)*3.1)>0,+((W16-3)*1.5+(X16-3)*3.1),0),IF(+((W16-3)*1.5+(X16-3)*3.1)>0,+((W16-3)*1.5+(X16-3)*3.1),0))) -> 30 | AA16: =+Y16+Z16 -> 50 | AB16: =+((O16*P16*(R16-U16)/100)-S16-AA16+T16)*V16 -> 446.9218 | AC16: =+(S16-T16)*V16-'data 1'!$F$4 -> 41.253 | AD16: =+(Q16-P16)*(R16-U16)*L16*V16/100 -> 1.3706604 | AE16: =+(Y16*V16-70)+V16*(Z16-IF(D16="UNTUCA",IF(+((W16-3)*2.5+(X16-3)*3.1)>0,+((W16-3)*1.5+(X16-3)*3.1),0),IF(+((W16-3)*1.5+(X16-3)*3.1)>0,+((W16-3)*1.5+(X16-3)*3.1),0))) -> -14.885 | AF16: =(L16-O16)*(R16-U16)*Q16*V16/100 -> 26.025235 | AG16: =+IF(D16="RONALD WILLIAN GARIBAY ESCUDERO",AC16+AD16+AE16+AF16+70,AC16+AD16+AE16+AF16)+70-53 -> 70.763895 | AH16: =31.1035*L16*Q16*1.1023*K16/100 -> 96.443218 | AI16: =+((+$AI$2-R16+U16)*L16*Q16*V16)/100 -> 70.138296 | AJ16: =31.1035*1.1023*K16*P16*O16/100 -> 92.390442 | AL16: =+IF(AB16*K16>0,AB16*K16,0) -> 5575.6534
A17: IP-1108 | B17: 45702 | C17: 45678 | D17: MINERA AURIFERA 2 DE DICIEMBRE CALPA RENACE S.A. | E17: {=XLOOKUP(D17,RUC!$B$3:$B$79,RUC!$D$3:$D$79)} -> #N/A | G17: 50 | H17: MINERAL | I17: 6.96 | J17: 1.1 | K17: =+I17-(I17*(J17/100)) -> 6.88344 | L17: 0.535 | M17: 0.514 | N17: 0.514 | O17: =+ROUND((M17+N17)/2,3) -> 0.514 | P17: 90 | Q17: 89.88 | R17: 2737.8 | S17: =IF((85+ROUNDDOWN(O17,1)*100)<95,95,(85+ROUNDDOWN(O17,1)*100)) -> 135 | U17: 90 | V17: 1.1023 | Z17: 25 | AA17: =+Y17+Z17 -> 25 | AB17: =+((O17*P17*(R17-U17)/100)-S17-AA17+T17)*V17 -> 1173.8087 | AC17: =+(S17-T17)*V17-'data 1'!$F$4 -> 68.8105 | AD17: =+(Q17-P17)*(R17-U17)*L17*V17/100 -> -1.8737861 | AE17: =+(Y17*V17-70)+V17*(Z17-IF(D17="UNTUCA",IF(+((W17-3)*2.5+(X17-3)*3.1)>0,+((W17-3)*1.5+(X17-3)*3.1),0),IF(+((W17-3)*1.5+(X17-3)*3.1)>0,+((W17-3)*1.5+(X17-3)*3.1),0))) -> -42.4425 | AF17: =(L17-O17)*(R17-U17)*Q17*V17/100 -> 55.089311 | AG17: =+IF(D17="RONALD WILLIAN GARIBAY ESCUDERO",AC17+AD17+AE17+AF17+70,AC17+AD17+AE17+AF17)+70-30-5-3 -> 111.58353 | AH17: =31.1035*L17*Q17*1.1023*K17/100 -> 113.48317 | AI17: =+((+$AI$2-R17+U17)*L17*Q17*V17)/100 -> 133.67855 | AJ17: =31.1035*1.1023*K17*P17*O17/100 -> 109.17425 | AL17: =+IF(AB17*K17>0,AB17*K17,0) -> 8079.8419
A18: IP-1109 | B18: 45702 | C18: 45678 | D18: MINERA AURIFERA 2 DE DICIEMBRE CALPA RENACE S.A. | E18: {=XLOOKUP(D18,RUC!$B$3:$B$79,RUC!$D$3:$D$79)} -> #N/A | G18: 50 | H18: MINERAL | I18: 5.29 | J18: 1.8 | K18: =+I18-(I18*(J18/100)) -> 5.19478 | L18: 0.193 | M18: 0.183 | N18: 0.183 | O18: =+ROUND((M18+N18)/2,3) -> 0.183 | P18: 85 | Q18: 90.31 | R18: 2737.8 | S18: =IF((85+ROUNDDOWN(O18,1)*100)<95,95,(85+ROUNDDOWN(O18,1)*100)) -> 95 | U18: 90 | V18: 1.1023 | Z18: 25 | AA18: =+Y18+Z18 -> 25 | AB18: =+((O18*P18*(R18-U18)/100)-S18-AA18+T18)*V18 -> 321.72311 | AC18: =+(S18-T18)*V18-'data 1'!$F$4 -> 24.7185 | AD18: =+(Q18-P18)*(R18-U18)*L18*V18/100 -> 29.911405 | AE18: =+(Y18*V18-70)+V18*(Z18-IF(D18="UNTUCA",IF(+((W18-3)*2.5+(X18-3)*3.1)>0,+((W18-3)*1.5+(X18-3)*3.1),0),IF(+((W18-3)*1.5+(X18-3)*3.1)>0,+((W18-3)*1.5+(X18-3)*3.1),0))) -> -42.4425 | AF18: =(L18-O18)*(R18-U18)*Q18*V18/100 -> 26.358508 | AG18: =+IF(D18="RONALD WILLIAN GARIBAY ESCUDERO",AC18+AD18+AE18+AF18+70,AC18+AD18+AE18+AF18)+70-30-5-3 -> 70.545913 | AH18: =31.1035*L18*Q18*1.1023*K18/100 -> 31.043407 | AI18: =+((+$AI$2-R18+U18)*L18*Q18*V18)/100 -> 48.454938 | AJ18: =31.1035*1.1023*K18*P18*O18/100 -> 27.70424 | AL18: =+IF(AB18*K18>0,AB18*K18,0) -> 1671.2808
A19: IP-1110 | B19: 45684 | C19: 45679 | D19: LLASA YUCRA YOLANDA | E19: {=XLOOKUP(D19,RUC!$B$3:$B$79,RUC!$D$3:$D$79)} -> #N/A | G19: 83 | H19: MINERAL | I19: 8.86 | J19: 1.2 | K19: =+I19-(I19*(J19/100)) -> 8.75368 | L19: 0.478 | M19: 0.458 | N19: 0.458 | O19: =+ROUND((M19+N19)/2,3) -> 0.458 | P19: 90 | Q19: 90.16 | R19: 2751.8 | S19: =IF((90+ROUNDDOWN(O19,1)*100)<95,95,(90+ROUNDDOWN(O19,1)*100)) -> 130 | U19: 120 | V19: 1.1023 | Y19: 20 | Z19: =IF(IF(D19="UNTUCA",IF(+((W19-3)*1.5+(X19-3)*3.1)>0,+((W19-3)*1.5+(X19-3)*3.1),0),IF(+((W19-3)*1.5+(X19-3)*3.1)>0,+((W19-3)*1.5+(X19-3)*3.1),0))<30,30,IF(D19="UNTUCA",IF(+((W19-3)*1.5+(X19-3)*3.1)>0,+((W19-3)*1.5+(X19-3)*3.1),0),IF(+((W19-3)*1.5+(X19-3)*3.1)>0,+((W19-3)*1.5+(X19-3)*3.1),0))) -> 30 | AA19: =+Y19+Z19 -> 50 | AB19: =+((O19*P19*(R19-U19)/100)-S19-AA19+T19)*V19 -> 997.39186 | AC19: =+(S19-T19)*V19-'data 1'!$F$4 -> 63.299 | AD19: =+(Q19-P19)*(R19-U19)*L19*V19/100 -> 2.2187101 | AE19: =+(Y19*V19-70)+V19*(Z19-IF(D19="UNTUCA",IF(+((W19-3)*2.5+(X19-3)*3.1)>0,+((W19-3)*1.5+(X19-3)*3.1),0),IF(+((W19-3)*1.5+(X19-3)*3.1)>0,+((W19-3)*1.5+(X19-3)*3.1),0))) -> -14.885 | AF19: =(L19-O19)*(R19-U19)*Q19*V19/100 -> 52.31143 | AG19: =+IF(D19="RONALD WILLIAN GARIBAY ESCUDERO",AC19+AD19+AE19+AF19+70,AC19+AD19+AE19+AF19)+70-53 -> 119.94414 | AH19: =31.1035*L19*Q19*1.1023*K19/100 -> 129.34258 | AI19: =+((+$AI$2-R19+U19)*L19*Q19*V19)/100 -> 127.40908 | AJ19: =31.1035*1.1023*K19*P19*O19/100 -> 123.71083 | AL19: =+IF(AB19*K19>0,AB19*K19,0) -> 8730.8492
A20: IP-1111 | B20: 45685 | C20: 45679 | D20: LLASA YUCRA YOLANDA | E20: {=XLOOKUP(D20,RUC!$B$3:$B$79,RUC!$D$3:$D$79)} -> #N/A | G20: 46 | H20: MINERAL | I20: 5.31 | J20: 1.3 | K20: =+I20-(I20*(J20/100)) -> 5.24097 | L20: 0.456 | M20: 0.437 | N20: 0.437 | O20: =+ROUND((M20+N20)/2,3) -> 0.437 | P20: 90 | Q20: 90.27 | R20: 2751.8 | S20: =IF((90+ROUNDDOWN(O20,1)*100)<95,95,(90+ROUNDDOWN(O20,1)*100)) -> 130 | U20: 120 | V20: 1.1023 | Y20: 20 | Z20: =IF(IF(D20="UNTUCA",IF(+((W20-3)*1.5+(X20-3)*3.1)>0,+((W20-3)*1.5+(X20-3)*3.1),0),IF(+((W20-3)*1.5+(X20-3)*3.1)>0,+((W20-3)*1.5+(X20-3)*3.1),0))<30,30,IF(D20="UNTUCA",IF(+((W20-3)*1.5+(X20-3)*3.1)>0,+((W20-3)*1.5+(X20-3)*3.1),0),IF(+((W20-3)*1.5+(X20-3)*3.1)>0,+((W20-3)*1.5+(X20-3)*3.1),0))) -> 30 | AA20: =+Y20+Z20 -> 50 | AB20: =+((O20*P20*(R20-U20)/100)-S20-AA20+T20)*V20 -> 942.56233 | AC20: =+(S20-T20)*V20-'data 1'!$F$4 -> 63.299 | AD20: =+(Q20-P20)*(R20-U20)*L20*V20/100 -> 3.571752 | AE20: =+(Y20*V20-70)+V20*(Z20-IF(D20="UNTUCA",IF(+((W20-3)*2.5+(X20-3)*3.1)>0,+((W20-3)*1.5+(X20-3)*3.1),0),IF(+((W20-3)*1.5+(X20-3)*3.1)>0,+((W20-3)*1.5+(X20-3)*3.1),0))) -> -14.885 | AF20: =(L20-O20)*(R20-U20)*Q20*V20/100 -> 49.75649 | AG20: =+IF(D20="RONALD WILLIAN GARIBAY ESCUDERO",AC20+AD20+AE20+AF20+70,AC20+AD20+AE20+AF20)+70-53 -> 118.74224 | AH20: =31.1035*L20*Q20*1.1023*K20/100 -> 73.965471 | AI20: =+((+$AI$2-R20+U20)*L20*Q20*V20)/100 -> 121.69336 | AJ20: =31.1035*1.1023*K20*P20*O20/100 -> 70.671562 | AL20: =+IF(AB20*K20>0,AB20*K20,0) -> 4939.9409
A21: IP-1112 | B21: 45689 | C21: 45679 | D21: LLASA YUCRA YOLANDA | E21: {=XLOOKUP(D21,RUC!$B$3:$B$79,RUC!$D$3:$D$79)} -> #N/A | G21: 64 | H21: MINERAL | I21: 8.71 | J21: 1.3 | K21: =+I21-(I21*(J21/100)) -> 8.59677 | L21: 0.244 | M21: 0.233 | N21: 0.233 | O21: =+ROUND((M21+N21)/2,3) -> 0.233 | P21: 90 | Q21: 90.07 | R21: 2751.8 | S21: =IF((90+ROUNDDOWN(O21,1)*100)<95,95,(90+ROUNDDOWN(O21,1)*100)) -> 110 | U21: 120 | V21: 1.1023 | Y21: 20 | Z21: =IF(IF(D21="UNTUCA",IF(+((W21-3)*1.5+(X21-3)*3.1)>0,+((W21-3)*1.5+(X21-3)*3.1),0),IF(+((W21-3)*1.5+(X21-3)*3.1)>0,+((W21-3)*1.5+(X21-3)*3.1),0))<30,30,IF(D21="UNTUCA",IF(+((W21-3)*1.5+(X21-3)*3.1)>0,+((W21-3)*1.5+(X21-3)*3.1),0),IF(+((W21-3)*1.5+(X21-3)*3.1)>0,+((W21-3)*1.5+(X21-3)*3.1),0))) -> 30 | AA21: =+Y21+Z21 -> 50 | AB21: =+((O21*P21*(R21-U21)/100)-S21-AA21+T21)*V21 -> 431.97865 | AC21: =+(S21-T21)*V21-'data 1'!$F$4 -> 41.253 | AD21: =+(Q21-P21)*(R21-U21)*L21*V21/100 -> 0.49549646 | AE21: =+(Y21*V21-70)+V21*(Z21-IF(D21="UNTUCA",IF(+((W21-3)*2.5+(X21-3)*3.1)>0,+((W21-3)*1.5+(X21-3)*3.1),0),IF(+((W21-3)*1.5+(X21-3)*3.1)>0,+((W21-3)*1.5+(X21-3)*3.1),0))) -> -14.885 | AF21: =(L21-O21)*(R21-U21)*Q21*V21/100 -> 28.742566 | AG21: =+IF(D21="RONALD WILLIAN GARIBAY ESCUDERO",AC21+AD21+AE21+AF21+70,AC21+AD21+AE21+AF21)+70-53 -> 72.606062 | AH21: =31.1035*L21*Q21*1.1023*K21/100 -> 64.776036 | AI21: =+((+$AI$2-R21+U21)*L21*Q21*V21)/100 -> 64.972349 | AJ21: =31.1035*1.1023*K21*P21*O21/100 -> 61.807732 | AL21: =+IF(AB21*K21>0,AB21*K21,0) -> 3713.6211
A22: IP-1113 | B22: 45686 | C22: 45681 | D22: LLASA YUCRA YOLANDA | E22: {=XLOOKUP(D22,RUC!$B$3:$B$79,RUC!$D$3:$D$79)} -> #N/A | G22: 46 | H22: MINERAL | I22: 3.63 | J22: 1.6 | K22: =+I22-(I22*(J22/100)) -> 3.57192 | L22: 0.215 | M22: 0.206 | N22: 0.206 | O22: =+ROUND((M22+N22)/2,3) -> 0.206 | P22: 90 | Q22: 90.28 | R22: 2776.8 | S22: =IF((90+ROUNDDOWN(O22,1)*100)<95,95,(90+ROUNDDOWN(O22,1)*100)) -> 110 | U22: 120 | V22: 1.1023 | Y22: 20 | Z22: =IF(IF(D22="UNTUCA",IF(+((W22-3)*1.5+(X22-3)*3.1)>0,+((W22-3)*1.5+(X22-3)*3.1),0),IF(+((W22-3)*1.5+(X22-3)*3.1)>0,+((W22-3)*1.5+(X22-3)*3.1),0))<30,30,IF(D22="UNTUCA",IF(+((W22-3)*1.5+(X22-3)*3.1)>0,+((W22-3)*1.5+(X22-3)*3.1),0),IF(+((W22-3)*1.5+(X22-3)*3.1)>0,+((W22-3)*1.5+(X22-3)*3.1),0))) -> 30 | AA22: =+Y22+Z22 -> 50 | AB22: =+((O22*P22*(R22-U22)/100)-S22-AA22+T22)*V22 -> 366.5927 | AC22: =+(S22-T22)*V22-'data 1'!$F$4 -> 41.253 | AD22: =+(Q22-P22)*(R22-U22)*L22*V22/100 -> 1.7630116 | AE22: =+(Y22*V22-70)+V22*(Z22-IF(D22="UNTUCA",IF(+((W22-3)*2.5+(X22-3)*3.1)>0,+((W22-3)*1.5+(X22-3)*3.1),0),IF(+((W22-3)*1.5+(X22-3)*3.1)>0,+((W22-3)*1.5+(X22-3)*3.1),0))) -> -14.885 | AF22: =(L22-O22)*(R22-U22)*Q22*V22/100 -> 23.795385 | AG22: =+IF(D22="RONALD WILLIAN GARIBAY ESCUDERO",AC22+AD22+AE22+AF22+70,AC22+AD22+AE22+AF22)+70-53 -> 68.926396 | AH22: =31.1035*L22*Q22*1.1023*K22/100 -> 23.770636 | AI22: =+((+$AI$2-R22+U22)*L22*Q22*V22)/100 -> 52.03474 | AJ22: =31.1035*1.1023*K22*P22*O22/100 -> 22.704949 | AL22: =+IF(AB22*K22>0,AB22*K22,0) -> 1309.4398
A23: IP-1114 | B23: 45686 | C23: 45681 | D23: LLASA YUCRA YOLANDA | E23: {=XLOOKUP(D23,RUC!$B$3:$B$79,RUC!$D$3:$D$79)} -> #N/A | G23: 64 | H23: MINERAL | I23: 5.69 | J23: 1.4 | K23: =+I23-(I23*(J23/100)) -> 5.61034 | L23: 0.349 | M23: 0.335 | N23: 0.335 | O23: =+ROUND((M23+N23)/2,3) -> 0.335 | P23: 90 | Q23: 90.13 | R23: 2776.8 | S23: =IF((90+ROUNDDOWN(O23,1)*100)<95,95,(90+ROUNDDOWN(O23,1)*100)) -> 120 | U23: 120 | V23: 1.1023 | Y23: 20 | Z23: =IF(IF(D23="UNTUCA",IF(+((W23-3)*1.5+(X23-3)*3.1)>0,+((W23-3)*1.5+(X23-3)*3.1),0),IF(+((W23-3)*1.5+(X23-3)*3.1)>0,+((W23-3)*1.5+(X23-3)*3.1),0))<30,30,IF(D23="UNTUCA",IF(+((W23-3)*1.5+(X23-3)*3.1)>0,+((W23-3)*1.5+(X23-3)*3.1),0),IF(+((W23-3)*1.5+(X23-3)*3.1)>0,+((W23-3)*1.5+(X23-3)*3.1),0))) -> 30 | AA23: =+Y23+Z23 -> 50 | AB23: =+((O23*P23*(R23-U23)/100)-S23-AA23+T23)*V23 -> 695.57908 | AC23: =+(S23-T23)*V23-'data 1'!$F$4 -> 52.276 | AD23: =+(Q23-P23)*(R23-U23)*L23*V23/100 -> 1.3287016 | AE23: =+(Y23*V23-70)+V23*(Z23-IF(D23="UNTUCA",IF(+((W23-3)*2.5+(X23-3)*3.1)>0,+((W23-3)*1.5+(X23-3)*3.1),0),IF(+((W23-3)*1.5+(X23-3)*3.1)>0,+((W23-3)*1.5+(X23-3)*3.1),0))) -> -14.885 | AF23: =(L23-O23)*(R23-U23)*Q23*V23/100 -> 36.953542 | AG23: =+IF(D23="RONALD WILLIAN GARIBAY ESCUDERO",AC23+AD23+AE23+AF23+70,AC23+AD23+AE23+AF23)+70-53 -> 92.673244 | AH23: =31.1035*L23*Q23*1.1023*K23/100 -> 60.505248 | AI23: =+((+$AI$2-R23+U23)*L23*Q23*V23)/100 -> 84.325355 | AJ23: =31.1035*1.1023*K23*P23*O23/100 -> 57.994334 | AL23: =+IF(AB23*K23>0,AB23*K23,0) -> 3902.4351
A24: IP-1123 | B24: 45703 | C24: 45682 | D24: J_M SOLUCIONES MINERAS E.I.R.L | E24: {=XLOOKUP(D24,RUC!$B$3:$B$79,RUC!$D$3:$D$79)} -> 20611329556 | G24: 90 | H24: MINERAL | I24: 8.48 | J24: 1.1 | K24: =+I24-(I24*(J24/100)) -> 8.38672 | L24: 0.261 | M24: 0.251 | N24: 0.251 | O24: =+ROUND((M24+N24)/2,3) -> 0.251 | P24: 90 | Q24: 90.12 | R24: 2756.8 | S24: 100 | U24: 100 | V24: 1.1023 | Z24: =IF(IF(D24="UNTUCA",IF(+((W24-3)*1.5+(X24-3)*3.1)>0,+((W24-3)*1.5+(X24-3)*3.1),0),IF(+((W24-3)*1.5+(X24-3)*3.1)>0,+((W24-3)*1.5+(X24-3)*3.1),0))<30,30,IF(D24="UNTUCA",IF(+((W24-3)*1.5+(X24-3)*3.1)>0,+((W24-3)*1.5+(X24-3)*3.1),0),IF(+((W24-3)*1.5+(X24-3)*3.1)>0,+((W24-3)*1.5+(X24-3)*3.1),0))) -> 30 | AA24: =+Y24+Z24 -> 30 | AB24: =+((O24*P24*(R24-U24)/100)-S24-AA24+T24)*V24 -> 518.26963 | AC24: =+(S24-T24)*V24-'data 1'!$F$4 -> 30.23 | AD24: =+(Q24-P24)*(R24-U24)*L24*V24/100 -> 0.91723459 | AE24: =+(Y24*V24-70)+V24*(Z24-IF(D24="UNTUCA",IF(+((W24-3)*2.5+(X24-3)*3.1)>0,+((W24-3)*1.5+(X24-3)*3.1),0),IF(+((W24-3)*1.5+(X24-3)*3.1)>0,+((W24-3)*1.5+(X24-3)*3.1),0))) -> -36.931 | AF24: =(L24-O24)*(R24-U24)*Q24*V24/100 -> 26.392459 | AG24: =+IF(D24="RONALD WILLIAN GARIBAY ESCUDERO",AC24+AD24+AE24+AF24+70,AC24+AD24+AE24+AF24)+70-53 -> 37.608693 | AH24: =31.1035*L24*Q24*1.1023*K24/100 -> 67.633662 | AI24: =+((+$AI$2-R24+U24)*L24*Q24*V24)/100 -> 63.055804 | AJ24: =31.1035*1.1023*K24*P24*O24/100 -> 64.955726 | AL24: =+IF(AB24*K24>0,AB24*K24,0) -> 4346.5822
A25: IP-1124 | B25: 45703 | C25: 45682 | D25: J_M SOLUCIONES MINERAS E.I.R.L | E25: {=XLOOKUP(D25,RUC!$B$3:$B$79,RUC!$D$3:$D$79)} -> 20611329556 | G25: 318 | H25: MINERAL | I25: 29.4 | J25: 1.2 | K25: =+I25-(I25*(J25/100)) -> 29.0472 | L25: 0.317 | M25: 0.304 | N25: 0.304 | O25: =+ROUND((M25+N25)/2,3) -> 0.304 | P25: 90 | Q25: 90.2 | R25: 2756.8 | S25: 110 | U25: 100 | V25: 1.1023 | Z25: =IF(IF(D25="UNTUCA",IF(+((W25-3)*1.5+(X25-3)*3.1)>0,+((W25-3)*1.5+(X25-3)*3.1),0),IF(+((W25-3)*1.5+(X25-3)*3.1)>0,+((W25-3)*1.5+(X25-3)*3.1),0))<30,30,IF(D25="UNTUCA",IF(+((W25-3)*1.5+(X25-3)*3.1)>0,+((W25-3)*1.5+(X25-3)*3.1),0),IF(+((W25-3)*1.5+(X25-3)*3.1)>0,+((W25-3)*1.5+(X25-3)*3.1),0))) -> 30 | AA25: =+Y25+Z25 -> 30 | AB25: =+((O25*P25*(R25-U25)/100)-S25-AA25+T25)*V25 -> 646.9404 | AC25: =+(S25-T25)*V25-'data 1'!$F$4 -> 41.253 | AD25: =+(Q25-P25)*(R25-U25)*L25*V25/100 -> 1.8567265 | AE25: =+(Y25*V25-70)+V25*(Z25-IF(D25="UNTUCA",IF(+((W25-3)*2.5+(X25-3)*3.1)>0,+((W25-3)*1.5+(X25-3)*3.1),0),IF(+((W25-3)*1.5+(X25-3)*3.1)>0,+((W25-3)*1.5+(X25-3)*3.1),0))) -> -36.931 | AF25: =(L25-O25)*(R25-U25)*Q25*V25/100 -> 34.340654 | AG25: =+IF(D25="RONALD WILLIAN GARIBAY ESCUDERO",AC25+AD25+AE25+AF25+70,AC25+AD25+AE25+AF25)+70-53 -> 57.51938 | AH25: =31.1035*L25*Q25*1.1023*K25/100 -> 284.7601 | AI25: =+((+$AI$2-R25+U25)*L25*Q25*V25)/100 -> 76.653004 | AJ25: =31.1035*1.1023*K25*P25*O25/100 -> 272.47674 | AL25: =+IF(AB25*K25>0,AB25*K25,0) -> 18791.807
A26: IP-1125 | B26: 45687 | C26: 45682 | D26: LLASA YUCRA YOLANDA | E26: {=XLOOKUP(D26,RUC!$B$3:$B$79,RUC!$D$3:$D$79)} -> #N/A | G26: 100 | H26: MINERAL | I26: 8.79 | J26: 1.8 | K26: =+I26-(I26*(J26/100)) -> 8.63178 | L26: 0.523 | M26: 0.502 | N26: 0.502 | O26: =+ROUND((M26+N26)/2,3) -> 0.502 | P26: 90 | Q26: 90.17 | R26: 2756.8 | S26: =IF((90+ROUNDDOWN(O26,1)*100)<95,95,(90+ROUNDDOWN(O26,1)*100)) -> 140 | U26: 120 | V26: 1.1023 | Y26: 20 | Z26: =IF(IF(D26="UNTUCA",IF(+((W26-3)*1.5+(X26-3)*3.1)>0,+((W26-3)*1.5+(X26-3)*3.1),0),IF(+((W26-3)*1.5+(X26-3)*3.1)>0,+((W26-3)*1.5+(X26-3)*3.1),0))<30,30,IF(D26="UNTUCA",IF(+((W26-3)*1.5+(X26-3)*3.1)>0,+((W26-3)*1.5+(X26-3)*3.1),0),IF(+((W26-3)*1.5+(X26-3)*3.1)>0,+((W26-3)*1.5+(X26-3)*3.1),0))) -> 30 | AA26: =+Y26+Z26 -> 50 | AB26: =+((O26*P26*(R26-U26)/100)-S26-AA26+T26)*V26 -> 1103.7399 | AC26: =+(S26-T26)*V26-'data 1'!$F$4 -> 74.322 | AD26: =+(Q26-P26)*(R26-U26)*L26*V26/100 -> 2.5842088 | AE26: =+(Y26*V26-70)+V26*(Z26-IF(D26="UNTUCA",IF(+((W26-3)*2.5+(X26-3)*3.1)>0,+((W26-3)*1.5+(X26-3)*3.1),0),IF(+((W26-3)*1.5+(X26-3)*3.1)>0,+((W26-3)*1.5+(X26-3)*3.1),0))) -> -14.885 | AF26: =(L26-O26)*(R26-U26)*Q26*V26/100 -> 55.037457 | AG26: =+IF(D26="RONALD WILLIAN GARIBAY ESCUDERO",AC26+AD26+AE26+AF26+70,AC26+AD26+AE26+AF26)+70-53 -> 134.05867 | AH26: =31.1035*L26*Q26*1.1023*K26/100 -> 139.56393 | AI26: =+((+$AI$2-R26+U26)*L26*Q26*V26)/100 -> 136.81996 | AJ26: =31.1035*1.1023*K26*P26*O26/100 -> 133.70747 | AL26: =+IF(AB26*K26>0,AB26*K26,0) -> 9527.2397
A27: IP-1126 | B27: 45686 | C27: 45684 | D27: LIMBER EDISON MONTALVO QUISPE | E27: {=XLOOKUP(D27,RUC!$B$3:$B$79,RUC!$D$3:$D$79)} -> 10479968131 | G27: 53 | H27: M.LLAMPO | I27: 4.44 | J27: 12 | K27: =+I27-(I27*(J27/100)) -> 3.9072 | L27: 0.259 | M27: 0.248 | N27: 0.248 | O27: =+ROUND((M27+N27)/2,3) -> 0.248 | P27: 90 | Q27: 90.22 | R27: 2742.4 | S27: =IF((90+ROUNDDOWN(O27,1)*100)<95,95,(90+ROUNDDOWN(O27,1)*100)) -> 110 | U27: 120 | V27: 1.1023 | Y27: 20 | Z27: =IF(IF(D27="UNTUCA",IF(+((W27-3)*1.5+(X27-3)*3.1)>0,+((W27-3)*1.5+(X27-3)*3.1),0),IF(+((W27-3)*1.5+(X27-3)*3.1)>0,+((W27-3)*1.5+(X27-3)*3.1),0))<30,30,IF(D27="UNTUCA",IF(+((W27-3)*1.5+(X27-3)*3.1)>0,+((W27-3)*1.5+(X27-3)*3.1),0),IF(+((W27-3)*1.5+(X27-3)*3.1)>0,+((W27-3)*1.5+(X27-3)*3.1),0))) -> 30 | AA27: =+Y27+Z27 -> 50 | AB27: =+((O27*P27*(R27-U27)/100)-S27-AA27+T27)*V27 -> 468.82988 | AC27: =+(S27-T27)*V27-'data 1'!$F$4 -> 41.253 | AD27: =+(Q27-P27)*(R27-U27)*L27*V27/100 -> 1.6471046 | AE27: =+(Y27*V27-70)+V27*(Z27-IF(D27="UNTUCA",IF(+((W27-3)*2.5+(X27-3)*3.1)>0,+((W27-3)*1.5+(X27-3)*3.1),0),IF(+((W27-3)*1.5+(X27-3)*3.1)>0,+((W27-3)*1.5+(X27-3)*3.1),0))) -> -14.885 | AF27: =(L27-O27)*(R27-U27)*Q27*V27/100 -> 28.687602 | AG27: =+IF(D27="RONALD WILLIAN GARIBAY ESCUDERO",AC27+AD27+AE27+AF27+70,AC27+AD27+AE27+AF27)+70-53 -> 73.702707 | AH27: =31.1035*L27*Q27*1.1023*K27/100 -> 31.302376 | AI27: =+((+$AI$2-R27+U27)*L27*Q27*V27)/100 -> 71.502604 | AJ27: =31.1035*1.1023*K27*P27*O27/100 -> 29.899843 | AL27: =+IF(AB27*K27>0,AB27*K27,0) -> 1831.8121
A28: IP-1127 | C28: 45684 | D28: LIMBER EDISON MONTALVO QUISPE | E28: {=XLOOKUP(D28,RUC!$B$3:$B$79,RUC!$D$3:$D$79)} -> 10479968131 | G28: 53 | H28: M.LLAMPO | I28: 4.5 | J28: 13 | K28: =+I28-(I28*(J28/100)) -> 3.915 | L28: 0.175 | M28: 0.165 | N28: 0.165 | O28: =+ROUND((M28+N28)/2,3) -> 0.165 | P28: 90 | Q28: 90.12 | R28: 2742.4 | S28: =IF((90+ROUNDDOWN(O28,1)*100)<95,95,(90+ROUNDDOWN(O28,1)*100)) -> 100 | U28: 120 | V28: 1.1023 | Y28: 20 | Z28: =IF(IF(D28="UNTUCA",IF(+((W28-3)*1.5+(X28-3)*3.1)>0,+((W28-3)*1.5+(X28-3)*3.1),0),IF(+((W28-3)*1.5+(X28-3)*3.1)>0,+((W28-3)*1.5+(X28-3)*3.1),0))<30,30,IF(D28="UNTUCA",IF(+((W28-3)*1.5+(X28-3)*3.1)>0,+((W28-3)*1.5+(X28-3)*3.1),0),IF(+((W28-3)*1.5+(X28-3)*3.1)>0,+((W28-3)*1.5+(X28-3)*3.1),0))) -> 30 | AA28: =+Y28+Z28 -> 50 | AB28: =+((O28*P28*(R28-U28)/100)-S28-AA28+T28)*V28 -> 263.91972 | AC28: =+(S28-T28)*V28-'data 1'!$F$4 -> 30.23 | AD28: =+(Q28-P28)*(R28-U28)*L28*V28/100 -> 0.60704102 | AE28: =+(Y28*V28-70)+V28*(Z28-IF(D28="UNTUCA",IF(+((W28-3)*2.5+(X28-3)*3.1)>0,+((W28-3)*1.5+(X28-3)*3.1),0),IF(+((W28-3)*1.5+(X28-3)*3.1)>0,+((W28-3)*1.5+(X28-3)*3.1),0))) -> -14.885 | AF28: =(L28-O28)*(R28-U28)*Q28*V28/100 -> 26.050732 | AG28: =+IF(D28="RONALD WILLIAN GARIBAY ESCUDERO",AC28+AD28+AE28+AF28+70,AC28+AD28+AE28+AF28)+70-53 -> 59.002773 | AH28: =31.1035*L28*Q28*1.1023*K28/100 -> 21.168987 | AI28: =+((+$AI$2-R28+U28)*L28*Q28*V28)/100 -> 48.25902 | AJ28: =31.1035*1.1023*K28*P28*O28/100 -> 19.932753 | AL28: =+IF(AB28*K28>0,AB28*K28,0) -> 1033.2457
A29: IP-1128 | B29: 45686 | C29: 45684 | D29: LIMBER EDISON MONTALVO QUISPE | E29: {=XLOOKUP(D29,RUC!$B$3:$B$79,RUC!$D$3:$D$79)} -> 10479968131 | G29: 44 | H29: M.LLAMPO | I29: 3.59 | J29: 12.85 | K29: =+I29-(I29*(J29/100)) -> 3.128685 | L29: 0.155 | M29: 0.145 | N29: 0.145 | O29: =+ROUND((M29+N29)/2,3) -> 0.145 | P29: 85 | Q29: 90.07 | R29: 2742.4 | S29: =IF((90+ROUNDDOWN(O29,1)*100)<95,95,(90+ROUNDDOWN(O29,1)*100)) -> 100 | U29: 120 | V29: 1.1023 | Y29: 20 | Z29: =IF(IF(D29="UNTUCA",IF(+((W29-3)*1.5+(X29-3)*3.1)>0,+((W29-3)*1.5+(X29-3)*3.1),0),IF(+((W29-3)*1.5+(X29-3)*3.1)>0,+((W29-3)*1.5+(X29-3)*3.1),0))<30,30,IF(D29="UNTUCA",IF(+((W29-3)*1.5+(X29-3)*3.1)>0,+((W29-3)*1.5+(X29-3)*3.1),0),IF(+((W29-3)*1.5+(X29-3)*3.1)>0,+((W29-3)*1.5+(X29-3)*3.1),0))) -> 30 | AA29: =+Y29+Z29 -> 50 | AB29: =+((O29*P29*(R29-U29)/100)-S29-AA29+T29)*V29 -> 190.93026 | AC29: =+(S29-T29)*V29-'data 1'!$F$4 -> 30.23 | AD29: =+(Q29-P29)*(R29-U29)*L29*V29/100 -> 22.716342 | AE29: =+(Y29*V29-70)+V29*(Z29-IF(D29="UNTUCA",IF(+((W29-3)*2.5+(X29-3)*3.1)>0,+((W29-3)*1.5+(X29-3)*3.1),0),IF(+((W29-3)*1.5+(X29-3)*3.1)>0,+((W29-3)*1.5+(X29-3)*3.1),0))) -> -14.885 | AF29: =(L29-O29)*(R29-U29)*Q29*V29/100 -> 26.036278 | AG29: =+IF(D29="RONALD WILLIAN GARIBAY ESCUDERO",AC29+AD29+AE29+AF29+70,AC29+AD29+AE29+AF29)+70-53 -> 81.097621 | AH29: =31.1035*L29*Q29*1.1023*K29/100 -> 14.97555 | AI29: =+((+$AI$2-R29+U29)*L29*Q29*V29)/100 -> 42.719989 | AJ29: =31.1035*1.1023*K29*P29*O29/100 -> 13.220803 | AL29: =+IF(AB29*K29>0,AB29*K29,0) -> 597.36066
A30: IP-1129 | B30: 45686 | C30: 45684 | D30: LIMBER EDISON MONTALVO QUISPE | E30: {=XLOOKUP(D30,RUC!$B$3:$B$79,RUC!$D$3:$D$79)} -> 10479968131 | G30: 31 | H30: M.LLAMPO | I30: 2.34 | J30: 11.2 | K30: =+I30-(I30*(J30/100)) -> 2.07792 | L30: 0.298 | M30: 0.286 | N30: 0.286 | O30: =+ROUND((M30+N30)/2,3) -> 0.286 | P30: 90 | Q30: 90.19 | R30: 2742.4 | S30: =IF((90+ROUNDDOWN(O30,1)*100)<95,95,(90+ROUNDDOWN(O30,1)*100)) -> 110 | U30: 120 | V30: 1.1023 | Y30: 20 | Z30: =IF(IF(D30="UNTUCA",IF(+((W30-3)*1.5+(X30-3)*3.1)>0,+((W30-3)*1.5+(X30-3)*3.1),0),IF(+((W30-3)*1.5+(X30-3)*3.1)>0,+((W30-3)*1.5+(X30-3)*3.1),0))<30,30,IF(D30="UNTUCA",IF(+((W30-3)*1.5+(X30-3)*3.1)>0,+((W30-3)*1.5+(X30-3)*3.1),0),IF(+((W30-3)*1.5+(X30-3)*3.1)>0,+((W30-3)*1.5+(X30-3)*3.1),0))) -> 30 | AA30: =+Y30+Z30 -> 50 | AB30: =+((O30*P30*(R30-U30)/100)-S30-AA30+T30)*V30 -> 567.69085 | AC30: =+(S30-T30)*V30-'data 1'!$F$4 -> 41.253 | AD30: =+(Q30-P30)*(R30-U30)*L30*V30/100 -> 1.6366982 | AE30: =+(Y30*V30-70)+V30*(Z30-IF(D30="UNTUCA",IF(+((W30-3)*2.5+(X30-3)*3.1)>0,+((W30-3)*1.5+(X30-3)*3.1),0),IF(+((W30-3)*1.5+(X30-3)*3.1)>0,+((W30-3)*1.5+(X30-3)*3.1),0))) -> -14.885 | AF30: =(L30-O30)*(R30-U30)*Q30*V30/100 -> 31.28516 | AG30: =+IF(D30="RONALD WILLIAN GARIBAY ESCUDERO",AC30+AD30+AE30+AF30+70,AC30+AD30+AE30+AF30)+70-53 -> 76.289858 | AH30: =31.1035*L30*Q30*1.1023*K30/100 -> 19.147521 | AI30: =+((+$AI$2-R30+U30)*L30*Q30*V30)/100 -> 82.242049 | AJ30: =31.1035*1.1023*K30*P30*O30/100 -> 18.337766 | AL30: =+IF(AB30*K30>0,AB30*K30,0) -> 1179.6162
A31: IP-1130 | B31: 45689 | C31: 45685 | D31: PIMENTEL BATALLANOS JUAN CRISOSTOMO | E31: {=XLOOKUP(D31,RUC!$B$3:$B$79,RUC!$D$3:$D$79)} -> 10306762465 | G31: 98 | H31: MINERAL | I31: 8.31 | J31: 1.1 | K31: =+I31-(I31*(J31/100)) -> 8.21859 | L31: 0.132 | M31: 0.127 | N31: 0.127 | O31: =+ROUND((M31+N31)/2,3) -> 0.127 | P31: 90 | Q31: 90.22 | R31: 2756.3 | S31: =IF((90+ROUNDDOWN(O31,1)*100)<95,95,(90+ROUNDDOWN(O31,1)*100)) -> 100 | U31: 120 | V31: 1.1023 | Y31: 20 | Z31: =IF(IF(D31="UNTUCA",IF(+((W31-3)*1.5+(X31-3)*3.1)>0,+((W31-3)*1.5+(X31-3)*3.1),0),IF(+((W31-3)*1.5+(X31-3)*3.1)>0,+((W31-3)*1.5+(X31-3)*3.1),0))<30,30,IF(D31="UNTUCA",IF(+((W31-3)*1.5+(X31-3)*3.1)>0,+((W31-3)*1.5+(X31-3)*3.1),0),IF(+((W31-3)*1.5+(X31-3)*3.1)>0,+((W31-3)*1.5+(X31-3)*3.1),0))) -> 30 | AA31: =+Y31+Z31 -> 50 | AB31: =+((O31*P31*(R31-U31)/100)-S31-AA31+T31)*V31 -> 166.81006 | AC31: =+(S31-T31)*V31-'data 1'!$F$4 -> 30.23 | AD31: =+(Q31-P31)*(R31-U31)*L31*V31/100 -> 0.84390051 | AE31: =+(Y31*V31-70)+V31*(Z31-IF(D31="UNTUCA",IF(+((W31-3)*2.5+(X31-3)*3.1)>0,+((W31-3)*1.5+(X31-3)*3.1),0),IF(+((W31-3)*1.5+(X31-3)*3.1)>0,+((W31-3)*1.5+(X31-3)*3.1),0))) -> -14.885 | AF31: =(L31-O31)*(R31-U31)*Q31*V31/100 -> 13.108937 | AG31: =+IF(D31="RONALD WILLIAN GARIBAY ESCUDERO",AC31+AD31+AE31+AF31+70,AC31+AD31+AE31+AF31)+70-53 -> 46.297837 | AH31: =31.1035*L31*Q31*1.1023*K31/100 -> 33.557001 | AI31: =+((+$AI$2-R31+U31)*L31*Q31*V31)/100 -> 34.616782 | AJ31: =31.1035*1.1023*K31*P31*O31/100 -> 32.207174 | AL31: =+IF(AB31*K31>0,AB31*K31,0) -> 1370.9435
A32: IP-1131 | B32: 45692 | C32: 45686 | D32: EMPRESA MINERA MARKATA CAS S.A.C. | E32: {=XLOOKUP(D32,RUC!$B$3:$B$79,RUC!$D$3:$D$79)} -> 20606526599 | G32: 90 | H32: MINERAL | I32: 7.31 | J32: 1.1 | K32: =+I32-(I32*(J32/100)) -> 7.22959 | L32: 0.207 | M32: 0.197 | N32: 0.252 | O32: =+ROUND((M32+N32)/2,3) -> 0.225 | P32: 90 | Q32: 90.03 | R32: 2756.3 | S32: =IF((90+ROUNDDOWN(O32,1)*100)<95,95,(90+ROUNDDOWN(O32,1)*100)) -> 110 | U32: 120 | V32: 1.1023 | Y32: 20 | Z32: =IF(IF(D32="UNTUCA",IF(+((W32-3)*1.5+(X32-3)*3.1)>0,+((W32-3)*1.5+(X32-3)*3.1),0),IF(+((W32-3)*1.5+(X32-3)*3.1)>0,+((W32-3)*1.5+(X32-3)*3.1),0))<30,30,IF(D32="UNTUCA",IF(+((W32-3)*1.5+(X32-3)*3.1)>0,+((W32-3)*1.5+(X32-3)*3.1),0),IF(+((W32-3)*1.5+(X32-3)*3.1)>0,+((W32-3)*1.5+(X32-3)*3.1),0))) -> 30 | AA32: =+Y32+Z32 -> 50 | AB32: =+((O32*P32*(R32-U32)/100)-S32-AA32+T32)*V32 -> 412.09568 | AC32: =+(S32-T32)*V32-'data 1'!$F$4 -> 41.253 | AD32: =+(Q32-P32)*(R32-U32)*L32*V32/100 -> 0.1804622 | AE32: =+(Y32*V32-70)+V32*(Z32-IF(D32="UNTUCA",IF(+((W32-3)*2.5+(X32-3)*3.1)>0,+((W32-3)*1.5+(X32-3)*3.1),0),IF(+((W32-3)*1.5+(X32-3)*3.1)>0,+((W32-3)*1.5+(X32-3)*3.1),0))) -> -14.885 | AF32: =(L32-O32)*(R32-U32)*Q32*V32/100 -> -47.092787 | AG32: =+IF(D32="RONALD WILLIAN GARIBAY ESCUDERO",AC32+AD32+AE32+AF32+70,AC32+AD32+AE32+AF32)+70-53 -> -3.5443247 | AH32: =31.1035*L32*Q32*1.1023*K32/100 -> 46.193443 | AI32: =+((+$AI$2-R32+U32)*L32*Q32*V32)/100 -> 54.171085 | AJ32: =31.1035*1.1023*K32*P32*O32/100 -> 50.193533 | AL32: =+IF(AB32*K32>0,AB32*K32,0) -> 2979.2828
A33: IP-1132 | B33: 45694 | C33: 45686 | D33: EMPRESA MINERA MARKATA CAS S.A.C. | E33: {=XLOOKUP(D33,RUC!$B$3:$B$79,RUC!$D$3:$D$79)} -> 20606526599 | G33: 69 | H33: MINERAL | I33: 5.88 | J33: 1.2 | K33: =+I33-(I33*(J33/100)) -> 5.80944 | L33: 0.472 | M33: 0.453 | N33: 0.453 | O33: =+ROUND((M33+N33)/2,3) -> 0.453 | P33: 90 | Q33: 89.96 | R33: 2756.3 | S33: =IF((90+ROUNDDOWN(O33,1)*100)<95,95,(90+ROUNDDOWN(O33,1)*100)) -> 130 | U33: 120 | V33: 1.1023 | Y33: 20 | Z33: =IF(IF(D33="UNTUCA",IF(+((W33-3)*1.5+(X33-3)*3.1)>0,+((W33-3)*1.5+(X33-3)*3.1),0),IF(+((W33-3)*1.5+(X33-3)*3.1)>0,+((W33-3)*1.5+(X33-3)*3.1),0))<30,30,IF(D33="UNTUCA",IF(+((W33-3)*1.5+(X33-3)*3.1)>0,+((W33-3)*1.5+(X33-3)*3.1),0),IF(+((W33-3)*1.5+(X33-3)*3.1)>0,+((W33-3)*1.5+(X33-3)*3.1),0))) -> 30 | AA33: =+Y33+Z33 -> 50 | AB33: =+((O33*P33*(R33-U33)/100)-S33-AA33+T33)*V33 -> 986.35955 | AC33: =+(S33-T33)*V33-'data 1'!$F$4 -> 63.299 | AD33: =+(Q33-P33)*(R33-U33)*L33*V33/100 -> -0.54865157 | AE33: =+(Y33*V33-70)+V33*(Z33-IF(D33="UNTUCA",IF(+((W33-3)*2.5+(X33-3)*3.1)>0,+((W33-3)*1.5+(X33-3)*3.1),0),IF(+((W33-3)*1.5+(X33-3)*3.1)>0,+((W33-3)*1.5+(X33-3)*3.1),0))) -> -14.885 | AF33: =(L33-O33)*(R33-U33)*Q33*V33/100 -> 49.670403 | AG33: =+IF(D33="RONALD WILLIAN GARIBAY ESCUDERO",AC33+AD33+AE33+AF33+70,AC33+AD33+AE33+AF33)+70-53 -> 114.53575 | AH33: =31.1035*L33*Q33*1.1023*K33/100 -> 84.573594 | AI33: =+((+$AI$2-R33+U33)*L33*Q33*V33)/100 -> 123.4245 | AJ33: =31.1035*1.1023*K33*P33*O33/100 -> 81.205239 | AL33: =+IF(AB33*K33>0,AB33*K33,0) -> 5730.1966
A34: IP-1133 | B34: 45689 | C34: 45687 | D34: ACS MINERA KORICANCHAQ I E.I.R.L | E34: {=XLOOKUP(D34,RUC!$B$3:$B$79,RUC!$D$3:$D$79)} -> 20603329059 | G34: 16 | H34: M.LLAMPO | I34: 1.06 | J34: 1.1 | K34: =+I34-(I34*(J34/100)) -> 1.04834 | L34: 0.455 | M34: 0.437 | N34: 0.437 | O34: =+ROUND((M34+N34)/2,3) -> 0.437 | P34: 90 | Q34: 89.9 | R34: 2787.25 | S34: =IF((80+ROUNDDOWN(O34,1)*100)<95,95,(80+ROUNDDOWN(O34,1)*100)) -> 120 | U34: 100 | V34: 1.1023 | Z34: =IF(IF(D34="UNTUCA",IF(+((W34-3)*1.5+(X34-3)*3.1)>0,+((W34-3)*1.5+(X34-3)*3.1),0),IF(+((W34-3)*1.5+(X34-3)*3.1)>0,+((W34-3)*1.5+(X34-3)*3.1),0))<30,30,IF(D34="UNTUCA",IF(+((W34-3)*1.5+(X34-3)*3.1)>0,+((W34-3)*1.5+(X34-3)*3.1),0),IF(+((W34-3)*1.5+(X34-3)*3.1)>0,+((W34-3)*1.5+(X34-3)*3.1),0))) -> 30 | AA34: =+Y34+Z34 -> 30 | AB34: =+((O34*P34*(R34-U34)/100)-S34-AA34+T34)*V34 -> 999.67083 | AC34: =+(S34-T34)*V34-'data 1'!$F$4 -> 52.276 | AD34: =+(Q34-P34)*(R34-U34)*L34*V34/100 -> -1.3477808 | AE34: =+(Y34*V34-70)+V34*(Z34-IF(D34="UNTUCA",IF(+((W34-3)*2.5+(X34-3)*3.1)>0,+((W34-3)*1.5+(X34-3)*3.1),0),IF(+((W34-3)*1.5+(X34-3)*3.1)>0,+((W34-3)*1.5+(X34-3)*3.1),0))) -> -36.931 | AF34: =(L34-O34)*(R34-U34)*Q34*V34/100 -> 47.933603 | AG34: =+IF(D34="RONALD WILLIAN GARIBAY ESCUDERO",AC34+AD34+AE34+AF34+70,AC34+AD34+AE34+AF34)+70-53 -> 78.930822 | AH34: =31.1035*L34*Q34*1.1023*K34/100 -> 14.7022 | AI34: =+((+$AI$2-R34+U34)*L34*Q34*V34)/100 -> 95.926912 | AJ34: =31.1035*1.1023*K34*P34*O34/100 -> 14.136281 | AL34: =+IF(AB34*K34>0,AB34*K34,0) -> 1047.9949
A35: IP-1134 | B35: 45696 | C35: 45687 | D35: ACS MINERA KORICANCHAQ I E.I.R.L | E35: {=XLOOKUP(D35,RUC!$B$3:$B$79,RUC!$D$3:$D$79)} -> 20603329059 | G35: 17 | H35: M.LLAMPO | I35: 1.13 | J35: 1.2 | K35: =+I35-(I35*(J35/100)) -> 1.11644 | L35: 0.85 | M35: 0.816 | N35: 0.816 | O35: =+ROUND((M35+N35)/2,3) -> 0.816 | P35: 90 | Q35: 89.74 | R35: 2787.25 | S35: =IF((80+ROUNDDOWN(O35,1)*100)<95,95,(80+ROUNDDOWN(O35,1)*100)) -> 160 | U35: 100 | V35: 1.1023 | Z35: =IF(IF(D35="UNTUCA",IF(+((W35-3)*1.5+(X35-3)*3.1)>0,+((W35-3)*1.5+(X35-3)*3.1),0),IF(+((W35-3)*1.5+(X35-3)*3.1)>0,+((W35-3)*1.5+(X35-3)*3.1),0))<30,30,IF(D35="UNTUCA",IF(+((W35-3)*1.5+(X35-3)*3.1)>0,+((W35-3)*1.5+(X35-3)*3.1),0),IF(+((W35-3)*1.5+(X35-3)*3.1)>0,+((W35-3)*1.5+(X35-3)*3.1),0))) -> 30 | AA35: =+Y35+Z35 -> 30 | AB35: =+((O35*P35*(R35-U35)/100)-S35-AA35+T35)*V35 -> 1965.9701 | AC35: =+(S35-T35)*V35-'data 1'!$F$4 -> 96.368 | AD35: =+(Q35-P35)*(R35-U35)*L35*V35/100 -> -6.546364 | AE35: =+(Y35*V35-70)+V35*(Z35-IF(D35="UNTUCA",IF(+((W35-3)*2.5+(X35-3)*3.1)>0,+((W35-3)*1.5+(X35-3)*3.1),0),IF(+((W35-3)*1.5+(X35-3)*3.1)>0,+((W35-3)*1.5+(X35-3)*3.1),0))) -> -36.931 | AF35: =(L35-O35)*(R35-U35)*Q35*V35/100 -> 90.380109 | AG35: =+IF(D35="RONALD WILLIAN GARIBAY ESCUDERO",AC35+AD35+AE35+AF35+70,AC35+AD35+AE35+AF35)+70-53 -> 160.27075 | AH35: =31.1035*L35*Q35*1.1023*K35/100 -> 29.197754 | AI35: =+((+$AI$2-R35+U35)*L35*Q35*V35)/100 -> 178.88518 | AJ35: =31.1035*1.1023*K35*P35*O35/100 -> 28.111054 | AL35: =+IF(AB35*K35>0,AB35*K35,0) -> 2194.8877
A36: IP-1135 | B36: 45696 | C36: 45687 | D36: ACS MINERA KORICANCHAQ I E.I.R.L | E36: {=XLOOKUP(D36,RUC!$B$3:$B$79,RUC!$D$3:$D$79)} -> 20603329059 | G36: 18 | H36: M.LLAMPO | I36: 1.21 | J36: 1.3 | K36: =+I36-(I36*(J36/100)) -> 1.19427 | L36: 0.529 | M36: 0.507 | N36: 0.507 | O36: =+ROUND((M36+N36)/2,3) -> 0.507 | P36: 90 | Q36: 89.91 | R36: 2787.25 | S36: =IF((80+ROUNDDOWN(O36,1)*100)<95,95,(80+ROUNDDOWN(O36,1)*100)) -> 130 | U36: 100 | V36: 1.1023 | Z36: =IF(IF(D36="UNTUCA",IF(+((W36-3)*1.5+(X36-3)*3.1)>0,+((W36-3)*1.5+(X36-3)*3.1),0),IF(+((W36-3)*1.5+(X36-3)*3.1)>0,+((W36-3)*1.5+(X36-3)*3.1),0))<30,30,IF(D36="UNTUCA",IF(+((W36-3)*1.5+(X36-3)*3.1)>0,+((W36-3)*1.5+(X36-3)*3.1),0),IF(+((W36-3)*1.5+(X36-3)*3.1)>0,+((W36-3)*1.5+(X36-3)*3.1),0))) -> 30 | AA36: =+Y36+Z36 -> 30 | AB36: =+((O36*P36*(R36-U36)/100)-S36-AA36+T36)*V36 -> 1175.2636 | AC36: =+(S36-T36)*V36-'data 1'!$F$4 -> 63.299 | AD36: =+(Q36-P36)*(R36-U36)*L36*V36/100 -> -1.4102823 | AE36: =+(Y36*V36-70)+V36*(Z36-IF(D36="UNTUCA",IF(+((W36-3)*2.5+(X36-3)*3.1)>0,+((W36-3)*1.5+(X36-3)*3.1),0),IF(+((W36-3)*1.5+(X36-3)*3.1)>0,+((W36-3)*1.5+(X36-3)*3.1),0))) -> -36.931 | AF36: =(L36-O36)*(R36-U36)*Q36*V36/100 -> 58.592032 | AG36: =+IF(D36="RONALD WILLIAN GARIBAY ESCUDERO",AC36+AD36+AE36+AF36+70,AC36+AD36+AE36+AF36)+70-53 -> 100.54975 | AH36: =31.1035*L36*Q36*1.1023*K36/100 -> 19.474901 | AI36: =+((+$AI$2-R36+U36)*L36*Q36*V36)/100 -> 111.54062 | AJ36: =31.1035*1.1023*K36*P36*O36/100 -> 18.683665 | AL36: =+IF(AB36*K36>0,AB36*K36,0) -> 1403.5821
A37: IP-1136 | B37: 45696 | C37: 45687 | D37: ACS MINERA KORICANCHAQ I E.I.R.L | E37: {=XLOOKUP(D37,RUC!$B$3:$B$79,RUC!$D$3:$D$79)} -> 20603329059 | G37: 17 | H37: M.LLAMPO | I37: 1.12 | J37: 1.4 | K37: =+I37-(I37*(J37/100)) -> 1.10432 | L37: 0.936 | M37: 0.899 | N37: 0.977 | O37: =+ROUND((M37+N37)/2,3) -> 0.938 | P37: 90 | Q37: 89.88 | R37: 2787.25 | S37: =IF((80+ROUNDDOWN(O37,1)*100)<95,95,(80+ROUNDDOWN(O37,1)*100)) -> 170 | U37: 100 | V37: 1.1023 | Z37: =IF(IF(D37="UNTUCA",IF(+((W37-3)*1.5+(X37-3)*3.1)>0,+((W37-3)*1.5+(X37-3)*3.1),0),IF(+((W37-3)*1.5+(X37-3)*3.1)>0,+((W37-3)*1.5+(X37-3)*3.1),0))<30,30,IF(D37="UNTUCA",IF(+((W37-3)*1.5+(X37-3)*3.1)>0,+((W37-3)*1.5+(X37-3)*3.1),0),IF(+((W37-3)*1.5+(X37-3)*3.1)>0,+((W37-3)*1.5+(X37-3)*3.1),0))) -> 30 | AA37: =+Y37+Z37 -> 30 | AB37: =+((O37*P37*(R37-U37)/100)-S37-AA37+T37)*V37 -> 2280.1918 | AC37: =+(S37-T37)*V37-'data 1'!$F$4 -> 107.391 | AD37: =+(Q37-P37)*(R37-U37)*L37*V37/100 -> -3.3270933 | AE37: =+(Y37*V37-70)+V37*(Z37-IF(D37="UNTUCA",IF(+((W37-3)*2.5+(X37-3)*3.1)>0,+((W37-3)*1.5+(X37-3)*3.1),0),IF(+((W37-3)*1.5+(X37-3)*3.1)>0,+((W37-3)*1.5+(X37-3)*3.1),0))) -> -36.931 | AF37: =(L37-O37)*(R37-U37)*Q37*V37/100 -> -5.324771 | AG37: =+IF(D37="RONALD WILLIAN GARIBAY ESCUDERO",AC37+AD37+AE37+AF37+70,AC37+AD37+AE37+AF37)+70-53 -> 78.808136 | AH37: =31.1035*L37*Q37*1.1023*K37/100 -> 31.852456 | AI37: =+((+$AI$2-R37+U37)*L37*Q37*V37)/100 -> 197.29146 | AJ37: =31.1035*1.1023*K37*P37*O37/100 -> 31.963134 | AL37: =+IF(AB37*K37>0,AB37*K37,0) -> 2518.0614
A38: IP-1137 | B38: 45696 | C38: 45687 | D38: ACS MINERA KORICANCHAQ I E.I.R.L | E38: {=XLOOKUP(D38,RUC!$B$3:$B$79,RUC!$D$3:$D$79)} -> 20603329059 | G38: 19 | H38: M.LLAMPO | I38: 1.32 | J38: 1.5 | K38: =+I38-(I38*(J38/100)) -> 1.3002 | L38: 0.579 | M38: 0.556 | N38: 0.776 | O38: =+ROUND((M38+N38)/2,3) -> 0.666 | P38: 90 | Q38: 89.78 | R38: 2787.25 | S38: =IF((80+ROUNDDOWN(O38,1)*100)<95,95,(80+ROUNDDOWN(O38,1)*100)) -> 140 | U38: 100 | V38: 1.1023 | Z38: =IF(IF(D38="UNTUCA",IF(+((W38-3)*1.5+(X38-3)*3.1)>0,+((W38-3)*1.5+(X38-3)*3.1),0),IF(+((W38-3)*1.5+(X38-3)*3.1)>0,+((W38-3)*1.5+(X38-3)*3.1),0))<30,30,IF(D38="UNTUCA",IF(+((W38-3)*1.5+(X38-3)*3.1)>0,+((W38-3)*1.5+(X38-3)*3.1),0),IF(+((W38-3)*1.5+(X38-3)*3.1)>0,+((W38-3)*1.5+(X38-3)*3.1),0))) -> 30 | AA38: =+Y38+Z38 -> 30 | AB38: =+((O38*P38*(R38-U38)/100)-S38-AA38+T38)*V38 -> 1588.1251 | AC38: =+(S38-T38)*V38-'data 1'!$F$4 -> 74.322 | AD38: =+(Q38-P38)*(R38-U38)*L38*V38/100 -> -3.7731939 | AE38: =+(Y38*V38-70)+V38*(Z38-IF(D38="UNTUCA",IF(+((W38-3)*2.5+(X38-3)*3.1)>0,+((W38-3)*1.5+(X38-3)*3.1),0),IF(+((W38-3)*1.5+(X38-3)*3.1)>0,+((W38-3)*1.5+(X38-3)*3.1),0))) -> -36.931 | AF38: =(L38-O38)*(R38-U38)*Q38*V38/100 -> -231.36983 | AG38: =+IF(D38="RONALD WILLIAN GARIBAY ESCUDERO",AC38+AD38+AE38+AF38+70,AC38+AD38+AE38+AF38)+70-53 -> -180.75203 | AH38: =31.1035*L38*Q38*1.1023*K38/100 -> 23.17274 | AI38: =+((+$AI$2-R38+U38)*L38*Q38*V38)/100 -> 121.90669 | AJ38: =31.1035*1.1023*K38*P38*O38/100 -> 26.71997 | AL38: =+IF(AB38*K38>0,AB38*K38,0) -> 2064.8803
A39: IP-1138 | B39: 45696 | C39: 45687 | D39: ACS MINERA KORICANCHAQ I E.I.R.L | E39: {=XLOOKUP(D39,RUC!$B$3:$B$79,RUC!$D$3:$D$79)} -> 20603329059 | G39: 17 | H39: M.LLAMPO | I39: 1.2 | J39: 1.6 | K39: =+I39-(I39*(J39/100)) -> 1.1808 | L39: 0.527 | M39: 0.506 | N39: 0.57 | O39: =+ROUND((M39+N39)/2,3) -> 0.538 | P39: 90 | Q39: 89.97 | R39: 2787.25 | S39: =IF((80+ROUNDDOWN(O39,1)*100)<95,95,(80+ROUNDDOWN(O39,1)*100)) -> 130 | U39: 100 | V39: 1.1023 | Z39: =IF(IF(D39="UNTUCA",IF(+((W39-3)*1.5+(X39-3)*3.1)>0,+((W39-3)*1.5+(X39-3)*3.1),0),IF(+((W39-3)*1.5+(X39-3)*3.1)>0,+((W39-3)*1.5+(X39-3)*3.1),0))<30,30,IF(D39="UNTUCA",IF(+((W39-3)*1.5+(X39-3)*3.1)>0,+((W39-3)*1.5+(X39-3)*3.1),0),IF(+((W39-3)*1.5+(X39-3)*3.1)>0,+((W39-3)*1.5+(X39-3)*3.1),0))) -> 30 | AA39: =+Y39+Z39 -> 30 | AB39: =+((O39*P39*(R39-U39)/100)-S39-AA39+T39)*V39 -> 1257.9078 | AC39: =+(S39-T39)*V39-'data 1'!$F$4 -> 63.299 | AD39: =+(Q39-P39)*(R39-U39)*L39*V39/100 -> -0.46831681 | AE39: =+(Y39*V39-70)+V39*(Z39-IF(D39="UNTUCA",IF(+((W39-3)*2.5+(X39-3)*3.1)>0,+((W39-3)*1.5+(X39-3)*3.1),0),IF(+((W39-3)*1.5+(X39-3)*3.1)>0,+((W39-3)*1.5+(X39-3)*3.1),0))) -> -36.931 | AF39: =(L39-O39)*(R39-U39)*Q39*V39/100 -> -29.315566 | AG39: =+IF(D39="RONALD WILLIAN GARIBAY ESCUDERO",AC39+AD39+AE39+AF39+70,AC39+AD39+AE39+AF39)+70-53 -> 13.584117 | AH39: =31.1035*L39*Q39*1.1023*K39/100 -> 19.195249 | AI39: =+((+$AI$2-R39+U39)*L39*Q39*V39)/100 -> 111.19307 | AJ39: =31.1035*1.1023*K39*P39*O39/100 -> 19.602443 | AL39: =+IF(AB39*K39>0,AB39*K39,0) -> 1485.3375
A40: IP-1139 | B40: 45691 | C40: 45687 | D40: SOTOMAYOR CORAZAO WISTHERMUNDO | E40: {=XLOOKUP(D40,RUC!$B$3:$B$79,RUC!$D$3:$D$79)} -> 10416085884 | G40: AGRANEL | H40: MINERAL | I40: 32.83 | J40: 8.6 | K40: =+I40-(I40*(J40/100)) -> 30.00662 | L40: 0.118 | M40: 0.108 | N40: 0.111 | O40: =+ROUND((M40+N40)/2,3) -> 0.11 | P40: 85 | Q40: 90.33 | R40: 2756.3 | S40: 110 | U40: 90 | V40: 1.1023 | Z40: =IF(IF(D40="UNTUCA",IF(+((W40-3)*1.5+(X40-3)*3.1)>0,+((W40-3)*1.5+(X40-3)*3.1),0),IF(+((W40-3)*1.5+(X40-3)*3.1)>0,+((W40-3)*1.5+(X40-3)*3.1),0))<30,30,IF(D40="UNTUCA",IF(+((W40-3)*1.5+(X40-3)*3.1)>0,+((W40-3)*1.5+(X40-3)*3.1),0),IF(+((W40-3)*1.5+(X40-3)*3.1)>0,+((W40-3)*1.5+(X40-3)*3.1),0))) -> 30 | AA40: =+Y40+Z40 -> 30 | AB40: =+((O40*P40*(R40-U40)/100)-S40-AA40+T40)*V40 -> 120.48034 | AC40: =+(S40-T40)*V40-'data 1'!$F$4 -> 41.253 | AD40: =+(Q40-P40)*(R40-U40)*L40*V40/100 -> 18.48494 | AE40: =+(Y40*V40-70)+V40*(Z40-IF(D40="UNTUCA",IF(+((W40-3)*2.5+(X40-3)*3.1)>0,+((W40-3)*1.5+(X40-3)*3.1),0),IF(+((W40-3)*1.5+(X40-3)*3.1)>0,+((W40-3)*1.5+(X40-3)*3.1),0))) -> -36.931 | AF40: =(L40-O40)*(R40-U40)*Q40*V40/100 -> 21.238841 | AG40: =+IF(D40="RONALD WILLIAN GARIBAY ESCUDERO",AC40+AD40+AE40+AF40+70,AC40+AD40+AE40+AF40)+70-53 -> 61.045781 | AH40: =31.1035*L40*Q40*1.1023*K40/100 -> 109.65796 | AI40: =+((+$AI$2-R40+U40)*L40*Q40*V40)/100 -> 27.45823 | AJ40: =31.1035*1.1023*K40*P40*O40/100 -> 96.191735 | AL40: =+IF(AB40*K40>0,AB40*K40,0) -> 3615.2079
A41: IP-1140 | B41: 45691 | C41: 45687 | D41: SOTOMAYOR CORAZAO WISTHERMUNDO | E41: {=XLOOKUP(D41,RUC!$B$3:$B$79,RUC!$D$3:$D$79)} -> 10416085884 | G41: AGRANEL | H41: MINERAL | I41: 24.64 | J41: 4.75 | K41: =+I41-(I41*(J41/100)) -> 23.4696 | L41: 0.512 | M41: 0.491 | N41: 0.522 | O41: =+ROUND((M41+N41)/2,3) -> 0.507 | P41: 90 | Q41: 89.98 | R41: 2756.3 | S41: 120 | U41: 90 | V41: 1.1023 | Z41: 15 | AA41: =+Y41+Z41 -> 15 | AB41: =+((O41*P41*(R41-U41)/100)-S41-AA41+T41)*V41 -> 1192.2837 | AC41: =+(S41-T41)*V41-'data 1'!$F$4 -> 52.276 | AD41: =+(Q41-P41)*(R41-U41)*L41*V41/100 -> -0.30096 | AE41: =+(Y41*V41-70)+V41*(Z41-IF(D41="UNTUCA",IF(+((W41-3)*2.5+(X41-3)*3.1)>0,+((W41-3)*1.5+(X41-3)*3.1),0),IF(+((W41-3)*1.5+(X41-3)*3.1)>0,+((W41-3)*1.5+(X41-3)*3.1),0))) -> -53.4655 | AF41: =(L41-O41)*(R41-U41)*Q41*V41/100 -> 13.222842 | AG41: =+IF(D41="RONALD WILLIAN GARIBAY ESCUDERO",AC41+AD41+AE41+AF41+70,AC41+AD41+AE41+AF41)+70-53 -> 28.732382 | AH41: =31.1035*L41*Q41*1.1023*K41/100 -> 370.70693 | AI41: =+((+$AI$2-R41+U41)*L41*Q41*V41)/100 -> 118.67916 | AJ41: =31.1035*1.1023*K41*P41*O41/100 -> 367.16834 | AL41: =+IF(AB41*K41>0,AB41*K41,0) -> 27982.422
A42: IP-1141 | B42: 45690 | C42: 45687 | D42: EMPRESA MINERA MARKATA CAS S.A.C. | E42: {=XLOOKUP(D42,RUC!$B$3:$B$79,RUC!$D$3:$D$79)} -> 20606526599 | G42: 90 | H42: MINERAL | I42: 7.51 | J42: 1.6 | K42: =+I42-(I42*(J42/100)) -> 7.38984 | L42: 0.187 | M42: 0.177 | N42: 0.177 | O42: =+ROUND((M42+N42)/2,3) -> 0.177 | P42: 90 | Q42: 90.23 | R42: 2787.25 | S42: =IF((80+ROUNDDOWN(O42,1)*100)<95,95,(80+ROUNDDOWN(O42,1)*100)) -> 95 | U42: 120 | V42: 1.1023 | Z42: =IF(IF(D42="UNTUCA",IF(+((W42-3)*1.5+(X42-3)*3.1)>0,+((W42-3)*1.5+(X42-3)*3.1),0),IF(+((W42-3)*1.5+(X42-3)*3.1)>0,+((W42-3)*1.5+(X42-3)*3.1),0))<30,30,IF(D42="UNTUCA",IF(+((W42-3)*1.5+(X42-3)*3.1)>0,+((W42-3)*1.5+(X42-3)*3.1),0),IF(+((W42-3)*1.5+(X42-3)*3.1)>0,+((W42-3)*1.5+(X42-3)*3.1),0))) -> 30 | AA42: =+Y42+Z42 -> 30 | AB42: =+((O42*P42*(R42-U42)/100)-S42-AA42+T42)*V42 -> 330.57197 | AC42: =+(S42-T42)*V42-'data 1'!$F$4 -> 24.7185 | AD42: =+(Q42-P42)*(R42-U42)*L42*V42/100 -> 1.2645412 | AE42: =+(Y42*V42-70)+V42*(Z42-IF(D42="UNTUCA",IF(+((W42-3)*2.5+(X42-3)*3.1)>0,+((W42-3)*1.5+(X42-3)*3.1),0),IF(+((W42-3)*1.5+(X42-3)*3.1)>0,+((W42-3)*1.5+(X42-3)*3.1),0))) -> -36.931 | AF42: =(L42-O42)*(R42-U42)*Q42*V42/100 -> 26.52861 | AG42: =+IF(D42="RONALD WILLIAN GARIBAY ESCUDERO",AC42+AD42+AE42+AF42+70,AC42+AD42+AE42+AF42)+70-53 -> 32.580651 | AH42: =31.1035*L42*Q42*1.1023*K42/100 -> 42.750054 | AI42: =+((+$AI$2-R42+U42)*L42*Q42*V42)/100 -> 43.289449 | AJ42: =31.1035*1.1023*K42*P42*O42/100 -> 40.360811 | AL42: =+IF(AB42*K42>0,AB42*K42,0) -> 2442.874
A43: IP-1142 | B43: 45690 | C43: 45687 | D43: EMPRESA MINERA MARKATA CAS S.A.C. | E43: {=XLOOKUP(D43,RUC!$B$3:$B$79,RUC!$D$3:$D$79)} -> 20606526599 | G43: 70 | H43: MINERAL | I43: 5.54 | J43: 1.5 | K43: =+I43-(I43*(J43/100)) -> 5.4569 | L43: 0.323 | M43: 0.31 | N43: 0.31 | O43: =+ROUND((M43+N43)/2,3) -> 0.31 | P43: 90 | Q43: 90.1 | R43: 2787.25 | S43: =IF((80+ROUNDDOWN(O43,1)*100)<95,95,(80+ROUNDDOWN(O43,1)*100)) -> 110 | U43: 120 | V43: 1.1023 | Z43: =IF(IF(D43="UNTUCA",IF(+((W43-3)*1.5+(X43-3)*3.1)>0,+((W43-3)*1.5+(X43-3)*3.1),0),IF(+((W43-3)*1.5+(X43-3)*3.1)>0,+((W43-3)*1.5+(X43-3)*3.1),0))<30,30,IF(D43="UNTUCA",IF(+((W43-3)*1.5+(X43-3)*3.1)>0,+((W43-3)*1.5+(X43-3)*3.1),0),IF(+((W43-3)*1.5+(X43-3)*3.1)>0,+((W43-3)*1.5+(X43-3)*3.1),0))) -> 30 | AA43: =+Y43+Z43 -> 30 | AB43: =+((O43*P43*(R43-U43)/100)-S43-AA43+T43)*V43 -> 665.9686 | AC43: =+(S43-T43)*V43-'data 1'!$F$4 -> 41.253 | AD43: =+(Q43-P43)*(R43-U43)*L43*V43/100 -> 0.94965542 | AE43: =+(Y43*V43-70)+V43*(Z43-IF(D43="UNTUCA",IF(+((W43-3)*2.5+(X43-3)*3.1)>0,+((W43-3)*1.5+(X43-3)*3.1),0),IF(+((W43-3)*1.5+(X43-3)*3.1)>0,+((W43-3)*1.5+(X43-3)*3.1),0))) -> -36.931 | AF43: =(L43-O43)*(R43-U43)*Q43*V43/100 -> 34.437505 | AG43: =+IF(D43="RONALD WILLIAN GARIBAY ESCUDERO",AC43+AD43+AE43+AF43+70,AC43+AD43+AE43+AF43)+70-53 -> 56.70916 | AH43: =31.1035*L43*Q43*1.1023*K43/100 -> 54.448056 | AI43: =+((+$AI$2-R43+U43)*L43*Q43*V43)/100 -> 74.664955 | AJ43: =31.1035*1.1023*K43*P43*O43/100 -> 52.19865 | AL43: =+IF(AB43*K43>0,AB43*K43,0) -> 3634.124
A44: IP-1143 (1207) | O44: =+ROUND((M44+N44)/2,3) -> 0 | P44: 90 | R44: 2812.05 | S44: =IF((90+ROUNDDOWN(O44,1)*100)<95,95,(90+ROUNDDOWN(O44,1)*100)) -> 95 | U44: 120 | V44: 1.1023 | Z44: =IF(IF(D44="UNTUCA",IF(+((W44-3)*1.5+(X44-3)*3.1)>0,+((W44-3)*1.5+(X44-3)*3.1),0),IF(+((W44-3)*1.5+(X44-3)*3.1)>0,+((W44-3)*1.5+(X44-3)*3.1),0))<30,30,IF(D44="UNTUCA",IF(+((W44-3)*1.5+(X44-3)*3.1)>0,+((W44-3)*1.5+(X44-3)*3.1),0),IF(+((W44-3)*1.5+(X44-3)*3.1)>0,+((W44-3)*1.5+(X44-3)*3.1),0))) -> 30 | AA44: =+Y44+Z44 -> 30 | AB44: =+((O44*P44*(R44-U44)/100)-S44-AA44+T44)*V44 -> -137.7875 | AC44: =+(S44-T44)*V44-'data 1'!$F$4 -> 24.7185 | AD44: =+(Q44-P44)*(R44-U44)*L44*V44/100 -> 0 | AE44: =+(Y44*V44-70)+V44*(Z44-IF(D44="UNTUCA",IF(+((W44-3)*2.5+(X44-3)*3.1)>0,+((W44-3)*1.5+(X44-3)*3.1),0),IF(+((W44-3)*1.5+(X44-3)*3.1)>0,+((W44-3)*1.5+(X44-3)*3.1),0))) -> -36.931 | AF44: =(L44-O44)*(R44-U44)*Q44*V44/100 -> 0 | AG44: =+IF(D44="RONALD WILLIAN GARIBAY ESCUDERO",AC44+AD44+AE44+AF44+70,AC44+AD44+AE44+AF44)+70-53 -> 4.7875 | AH44: =31.1035*L44*Q44*1.1023*K44/100 -> 0 | AI44: =+((+$AI$2-R44+U44)*L44*Q44*V44)/100 -> 0 | AJ44: =31.1035*1.1023*K44*P44*O44/100 -> 0 | AL44: =+IF(AB44*K44>0,AB44*K44,0) -> 0
A45: IP-1144 (1208) | O45: =+ROUND((M45+N45)/2,3) -> 0 | P45: 90 | R45: 2812.05 | S45: =IF((90+ROUNDDOWN(O45,1)*100)<95,95,(90+ROUNDDOWN(O45,1)*100)) -> 95 | U45: 120 | V45: 1.1023 | Z45: =IF(IF(D45="UNTUCA",IF(+((W45-3)*1.5+(X45-3)*3.1)>0,+((W45-3)*1.5+(X45-3)*3.1),0),IF(+((W45-3)*1.5+(X45-3)*3.1)>0,+((W45-3)*1.5+(X45-3)*3.1),0))<30,30,IF(D45="UNTUCA",IF(+((W45-3)*1.5+(X45-3)*3.1)>0,+((W45-3)*1.5+(X45-3)*3.1),0),IF(+((W45-3)*1.5+(X45-3)*3.1)>0,+((W45-3)*1.5+(X45-3)*3.1),0))) -> 30 | AA45: =+Y45+Z45 -> 30 | AB45: =+((O45*P45*(R45-U45)/100)-S45-AA45+T45)*V45 -> -137.7875 | AC45: =+(S45-T45)*V45-'data 1'!$F$4 -> 24.7185 | AD45: =+(Q45-P45)*(R45-U45)*L45*V45/100 -> 0 | AE45: =+(Y45*V45-70)+V45*(Z45-IF(D45="UNTUCA",IF(+((W45-3)*2.5+(X45-3)*3.1)>0,+((W45-3)*1.5+(X45-3)*3.1),0),IF(+((W45-3)*1.5+(X45-3)*3.1)>0,+((W45-3)*1.5+(X45-3)*3.1),0))) -> -36.931 | AF45: =(L45-O45)*(R45-U45)*Q45*V45/100 -> 0 | AG45: =+IF(D45="RONALD WILLIAN GARIBAY ESCUDERO",AC45+AD45+AE45+AF45+70,AC45+AD45+AE45+AF45)+70-53 -> 4.7875 | AH45: =31.1035*L45*Q45*1.1023*K45/100 -> 0 | AI45: =+((+$AI$2-R45+U45)*L45*Q45*V45)/100 -> 0 | AJ45: =31.1035*1.1023*K45*P45*O45/100 -> 0 | AL45: =+IF(AB45*K45>0,AB45*K45,0) -> 0
A46: IP-1145 | B46: 45692 | C46: 45689 | D46: MELCHOR AGUSTIN VERA PACHECO | E46: {=XLOOKUP(D46,RUC!$B$3:$B$79,RUC!$D$3:$D$79)} -> 10082235774 | G46: 46 | H46: MINERAL | I46: 4.62 | J46: 1.6 | K46: =+I46-(I46*(J46/100)) -> 4.54608 | L46: 0.4 | M46: 0.394 | N46: 0.394 | O46: =+ROUND((M46+N46)/2,3) -> 0.394 | P46: 90 | Q46: 89.89 | R46: 2812.05 | S46: 110 | U46: 80 | V46: 1.1023 | Z46: 10 | AA46: =+Y46+Z46 -> 10 | AB46: =+((O46*P46*(R46-U46)/100)-S46-AA46+T46)*V46 -> 935.61563 | AC46: =+(S46-T46)*V46-'data 1'!$F$4 -> 41.253 | AD46: =+(Q46-P46)*(R46-U46)*L46*V46/100 -> -1.325077 | AE46: =+(Y46*V46-70)+V46*(Z46-IF(D46="UNTUCA",IF(+((W46-3)*2.5+(X46-3)*3.1)>0,+((W46-3)*1.5+(X46-3)*3.1),0),IF(+((W46-3)*1.5+(X46-3)*3.1)>0,+((W46-3)*1.5+(X46-3)*3.1),0))) -> -58.977 | AF46: =(L46-O46)*(R46-U46)*Q46*V46/100 -> 16.242433 | AG46: =+IF(D46="RONALD WILLIAN GARIBAY ESCUDERO",AC46+AD46+AE46+AF46+70,AC46+AD46+AE46+AF46)+70 -> 67.193356 | AH46: =31.1035*L46*Q46*1.1023*K46/100 -> 56.042502 | AI46: =+((+$AI$2-R46+U46)*L46*Q46*V46)/100 -> 66.565805 | AJ46: =31.1035*1.1023*K46*P46*O46/100 -> 55.269416 | AL46: =+IF(AB46*K46>0,AB46*K46,0) -> 4253.3835
A47: IP-1146 | B47: 45692 | C47: 45689 | D47: MELCHOR AGUSTIN VERA PACHECO | E47: {=XLOOKUP(D47,RUC!$B$3:$B$79,RUC!$D$3:$D$79)} -> 10082235774 | G47: 44 | H47: MINERAL | I47: 4.34 | J47: 1.7 | K47: =+I47-(I47*(J47/100)) -> 4.26622 | L47: 0.195 | M47: 0.192 | N47: 0.192 | O47: =+ROUND((M47+N47)/2,3) -> 0.192 | P47: 85 | Q47: 90.22 | R47: 2812.05 | S47: 95 | U47: 80 | V47: 1.1023 | Z47: 10 | AA47: =+Y47+Z47 -> 10 | AB47: =+((O47*P47*(R47-U47)/100)-S47-AA47+T47)*V47 -> 375.74162 | AC47: =+(S47-T47)*V47-'data 1'!$F$4 -> 24.7185 | AD47: =+(Q47-P47)*(R47-U47)*L47*V47/100 -> 30.654453 | AE47: =+(Y47*V47-70)+V47*(Z47-IF(D47="UNTUCA",IF(+((W47-3)*2.5+(X47-3)*3.1)>0,+((W47-3)*1.5+(X47-3)*3.1),0),IF(+((W47-3)*1.5+(X47-3)*3.1)>0,+((W47-3)*1.5+(X47-3)*3.1),0))) -> -58.977 | AF47: =(L47-O47)*(R47-U47)*Q47*V47/100 -> 8.1510307 | AG47: =+IF(D47="RONALD WILLIAN GARIBAY ESCUDERO",AC47+AD47+AE47+AF47+70,AC47+AD47+AE47+AF47)+70 -> 74.546983 | AH47: =31.1035*L47*Q47*1.1023*K47/100 -> 25.73296 | AI47: =+((+$AI$2-R47+U47)*L47*Q47*V47)/100 -> 32.569962 | AJ47: =31.1035*1.1023*K47*P47*O47/100 -> 23.871102 | AL47: =+IF(AB47*K47>0,AB47*K47,0) -> 1602.9964
A48: IP-1147 | B48: 45692 | C48: 45689 | D48: MELCHOR AGUSTIN VERA PACHECO | E48: {=XLOOKUP(D48,RUC!$B$3:$B$79,RUC!$D$3:$D$79)} -> 10082235774 | G48: 41 | H48: MINERAL | I48: 4.02 | J48: 1.8 | K48: =+I48-(I48*(J48/100)) -> 3.94764 | L48: 0.228 | M48: 0.225 | N48: 0.225 | O48: =+ROUND((M48+N48)/2,3) -> 0.225 | P48: 90 | Q48: 90.16 | R48: 2812.05 | S48: 105 | U48: 80 | V48: 1.1023 | Z48: 10 | AA48: =+Y48+Z48 -> 10 | AB48: =+((O48*P48*(R48-U48)/100)-S48-AA48+T48)*V48 -> 483.07209 | AC48: =+(S48-T48)*V48-'data 1'!$F$4 -> 35.7415 | AD48: =+(Q48-P48)*(R48-U48)*L48*V48/100 -> 1.0986093 | AE48: =+(Y48*V48-70)+V48*(Z48-IF(D48="UNTUCA",IF(+((W48-3)*2.5+(X48-3)*3.1)>0,+((W48-3)*1.5+(X48-3)*3.1),0),IF(+((W48-3)*1.5+(X48-3)*3.1)>0,+((W48-3)*1.5+(X48-3)*3.1),0))) -> -58.977 | AF48: =(L48-O48)*(R48-U48)*Q48*V48/100 -> 8.1456099 | AG48: =+IF(D48="RONALD WILLIAN GARIBAY ESCUDERO",AC48+AD48+AE48+AF48+70,AC48+AD48+AE48+AF48)+70 -> 56.008719 | AH48: =31.1035*L48*Q48*1.1023*K48/100 -> 27.822449 | AI48: =+((+$AI$2-R48+U48)*L48*Q48*V48)/100 -> 38.056476 | AJ48: =31.1035*1.1023*K48*P48*O48/100 -> 27.40764 | AL48: =+IF(AB48*K48>0,AB48*K48,0) -> 1906.9947
A49: IP-1148 | B49: 45692 | C49: 45689 | D49: MELCHOR AGUSTIN VERA PACHECO | E49: {=XLOOKUP(D49,RUC!$B$3:$B$79,RUC!$D$3:$D$79)} -> 10082235774 | G49: 43 | H49: MINERAL | I49: 4.25 | J49: 1.7 | K49: =+I49-(I49*(J49/100)) -> 4.17775 | L49: 0.238 | M49: 0.234 | N49: 0.234 | O49: =+ROUND((M49+N49)/2,3) -> 0.234 | P49: 90 | Q49: 90.13 | R49: 2812.05 | S49: 105 | U49: 80 | V49: 1.1023 | Z49: 10 | AA49: =+Y49+Z49 -> 10 | AB49: =+((O49*P49*(R49-U49)/100)-S49-AA49+T49)*V49 -> 507.46555 | AC49: =+(S49-T49)*V49-'data 1'!$F$4 -> 35.7415 | AD49: =+(Q49-P49)*(R49-U49)*L49*V49/100 -> 0.93177008 | AE49: =+(Y49*V49-70)+V49*(Z49-IF(D49="UNTUCA",IF(+((W49-3)*2.5+(X49-3)*3.1)>0,+((W49-3)*1.5+(X49-3)*3.1),0),IF(+((W49-3)*1.5+(X49-3)*3.1)>0,+((W49-3)*1.5+(X49-3)*3.1),0))) -> -58.977 | AF49: =(L49-O49)*(R49-U49)*Q49*V49/100 -> 10.857199 | AG49: =+IF(D49="RONALD WILLIAN GARIBAY ESCUDERO",AC49+AD49+AE49+AF49+70,AC49+AD49+AE49+AF49)+70 -> 58.553469 | AH49: =31.1035*L49*Q49*1.1023*K49/100 -> 30.725421 | AI49: =+((+$AI$2-R49+U49)*L49*Q49*V49)/100 -> 39.712401 | AJ49: =31.1035*1.1023*K49*P49*O49/100 -> 30.165455 | AL49: =+IF(AB49*K49>0,AB49*K49,0) -> 2120.0642
A50: IP-1149 | B50: 45692 | C50: 45689 | D50: MELCHOR AGUSTIN VERA PACHECO | E50: {=XLOOKUP(D50,RUC!$B$3:$B$79,RUC!$D$3:$D$79)} -> 10082235774 | G50: 46 | H50: MINERAL | I50: 4.74 | J50: 1.6 | K50: =+I50-(I50*(J50/100)) -> 4.66416 | L50: 0.458 | M50: 0.451 | N50: 0.451 | O50: =+ROUND((M50+N50)/2,3) -> 0.451 | P50: 90 | Q50: 90.06 | R50: 2812.05 | S50: 115 | U50: 80 | V50: 1.1023 | Z50: 10 | AA50: =+Y50+Z50 -> 10 | AB50: =+((O50*P50*(R50-U50)/100)-S50-AA50+T50)*V50 -> 1084.5961 | AC50: =+(S50-T50)*V50-'data 1'!$F$4 -> 46.7645 | AD50: =+(Q50-P50)*(R50-U50)*L50*V50/100 -> 0.82757084 | AE50: =+(Y50*V50-70)+V50*(Z50-IF(D50="UNTUCA",IF(+((W50-3)*2.5+(X50-3)*3.1)>0,+((W50-3)*1.5+(X50-3)*3.1),0),IF(+((W50-3)*1.5+(X50-3)*3.1)>0,+((W50-3)*1.5+(X50-3)*3.1),0))) -> -58.977 | AF50: =(L50-O50)*(R50-U50)*Q50*V50/100 -> 18.985342 | AG50: =+IF(D50="RONALD WILLIAN GARIBAY ESCUDERO",AC50+AD50+AE50+AF50+70,AC50+AD50+AE50+AF50)+70 -> 77.600413 | AH50: =31.1035*L50*Q50*1.1023*K50/100 -> 65.959891 | AI50: =+((+$AI$2-R50+U50)*L50*Q50*V50)/100 -> 76.36199 | AJ50: =31.1035*1.1023*K50*P50*O50/100 -> 64.908498 | AL50: =+IF(AB50*K50>0,AB50*K50,0) -> 5058.7296
A51: IP-1150 | B51: 45692 | C51: 45689 | D51: MELCHOR AGUSTIN VERA PACHECO | E51: {=XLOOKUP(D51,RUC!$B$3:$B$79,RUC!$D$3:$D$79)} -> 10082235774 | G51: 34 | H51: MINERAL | I51: 3.31 | J51: 1.8 | K51: =+I51-(I51*(J51/100)) -> 3.25042 | L51: 0.163 | M51: 0.161 | N51: 0.161 | O51: =+ROUND((M51+N51)/2,3) -> 0.161 | P51: 85 | Q51: 90.2 | R51: 2812.05 | S51: 95 | U51: 80 | V51: 1.1023 | Z51: 10 | AA51: =+Y51+Z51 -> 10 | AB51: =+((O51*P51*(R51-U51)/100)-S51-AA51+T51)*V51 -> 296.38757 | AC51: =+(S51-T51)*V51-'data 1'!$F$4 -> 24.7185 | AD51: =+(Q51-P51)*(R51-U51)*L51*V51/100 -> 25.525802 | AE51: =+(Y51*V51-70)+V51*(Z51-IF(D51="UNTUCA",IF(+((W51-3)*2.5+(X51-3)*3.1)>0,+((W51-3)*1.5+(X51-3)*3.1),0),IF(+((W51-3)*1.5+(X51-3)*3.1)>0,+((W51-3)*1.5+(X51-3)*3.1),0))) -> -58.977 | AF51: =(L51-O51)*(R51-U51)*Q51*V51/100 -> 5.4328158 | AG51: =+IF(D51="RONALD WILLIAN GARIBAY ESCUDERO",AC51+AD51+AE51+AF51+70,AC51+AD51+AE51+AF51)+70 -> 66.700118 | AH51: =31.1035*L51*Q51*1.1023*K51/100 -> 16.384858 | AI51: =+((+$AI$2-R51+U51)*L51*Q51*V51)/100 -> 27.219112 | AJ51: =31.1035*1.1023*K51*P51*O51/100 -> 15.250826 | AL51: =+IF(AB51*K51>0,AB51*K51,0) -> 963.3841
A52: IP-1151 | B52: 45692 | C52: 45689 | D52: COMPAÑÍA MINERA CIKAM PERU SAC | E52: {=XLOOKUP(D52,RUC!$B$3:$B$79,RUC!$D$3:$D$79)} -> 20517242919 | G52: 42 | H52: MINERAL | I52: 4.25 | J52: 1.6 | K52: =+I52-(I52*(J52/100)) -> 4.182 | L52: 0.439 | M52: 0.432 | N52: 0.432 | O52: =+ROUND((M52+N52)/2,3) -> 0.432 | P52: 90 | Q52: 89.92 | R52: 2812.05 | S52: 115 | U52: 80 | V52: 1.1023 | Z52: 10 | AA52: =+Y52+Z52 -> 10 | AB52: =+((O52*P52*(R52-U52)/100)-S52-AA52+T52)*V52 -> 1033.0988 | AC52: =+(S52-T52)*V52-'data 1'!$F$4 -> 46.7645 | AD52: =+(Q52-P52)*(R52-U52)*L52*V52/100 -> -1.0576524 | AE52: =+(Y52*V52-70)+V52*(Z52-IF(D52="UNTUCA",IF(+((W52-3)*2.5+(X52-3)*3.1)>0,+((W52-3)*1.5+(X52-3)*3.1),0),IF(+((W52-3)*1.5+(X52-3)*3.1)>0,+((W52-3)*1.5+(X52-3)*3.1),0))) -> -58.977 | AF52: =(L52-O52)*(R52-U52)*Q52*V52/100 -> 18.955829 | AG52: =+IF(D52="RONALD WILLIAN GARIBAY ESCUDERO",AC52+AD52+AE52+AF52+70,AC52+AD52+AE52+AF52)+70 -> 75.685677 | AH52: =31.1035*L52*Q52*1.1023*K52/100 -> 56.599672 | AI52: =+((+$AI$2-R52+U52)*L52*Q52*V52)/100 -> 73.080353 | AJ52: =31.1035*1.1023*K52*P52*O52/100 -> 55.746724 | AL52: =+IF(AB52*K52>0,AB52*K52,0) -> 4320.419
A53: IP-1152 | B53: 45692 | C53: 45689 | D53: COMPAÑÍA MINERA CIKAM PERU SAC | E53: {=XLOOKUP(D53,RUC!$B$3:$B$79,RUC!$D$3:$D$79)} -> 20517242919 | G53: 38 | H53: MINERAL | I53: 3.96 | J53: 1.7 | K53: =+I53-(I53*(J53/100)) -> 3.89268 | L53: 0.562 | M53: 0.553 | N53: 0.553 | O53: =+ROUND((M53+N53)/2,3) -> 0.553 | P53: 90 | Q53: 89.84 | R53: 2812.05 | S53: 120 | U53: 80 | V53: 1.1023 | Z53: 10 | AA53: =+Y53+Z53 -> 10 | AB53: =+((O53*P53*(R53-U53)/100)-S53-AA53+T53)*V53 -> 1355.5438 | AC53: =+(S53-T53)*V53-'data 1'!$F$4 -> 52.276 | AD53: =+(Q53-P53)*(R53-U53)*L53*V53/100 -> -2.7079756 | AE53: =+(Y53*V53-70)+V53*(Z53-IF(D53="UNTUCA",IF(+((W53-3)*2.5+(X53-3)*3.1)>0,+((W53-3)*1.5+(X53-3)*3.1),0),IF(+((W53-3)*1.5+(X53-3)*3.1)>0,+((W53-3)*1.5+(X53-3)*3.1),0))) -> -58.977 | AF53: =(L53-O53)*(R53-U53)*Q53*V53/100 -> 24.350097 | AG53: =+IF(D53="RONALD WILLIAN GARIBAY ESCUDERO",AC53+AD53+AE53+AF53+70,AC53+AD53+AE53+AF53)+70 -> 84.941122 | AH53: =31.1035*L53*Q53*1.1023*K53/100 -> 67.385093 | AI53: =+((+$AI$2-R53+U53)*L53*Q53*V53)/100 -> 93.472934 | AJ53: =31.1035*1.1023*K53*P53*O53/100 -> 66.424059 | AL53: =+IF(AB53*K53>0,AB53*K53,0) -> 5276.6983
A54: IP-1153 | B54: 45692 | C54: 45689 | D54: COMPAÑÍA MINERA CIKAM PERU SAC | E54: {=XLOOKUP(D54,RUC!$B$3:$B$79,RUC!$D$3:$D$79)} -> 20517242919 | G54: 28 | H54: MINERAL | I54: 2.61 | J54: 1.2 | K54: =+I54-(I54*(J54/100)) -> 2.57868 | L54: 0.165 | M54: 0.163 | N54: 0.163 | O54: =+ROUND((M54+N54)/2,3) -> 0.163 | P54: 85 | Q54: 90.33 | R54: 2812.05 | S54: 95 | U54: 80 | V54: 1.1023 | Z54: 10 | AA54: =+Y54+Z54 -> 10 | AB54: =+((O54*P54*(R54-U54)/100)-S54-AA54+T54)*V54 -> 301.50719 | AC54: =+(S54-T54)*V54-'data 1'!$F$4 -> 24.7185 | AD54: =+(Q54-P54)*(R54-U54)*L54*V54/100 -> 26.484977 | AE54: =+(Y54*V54-70)+V54*(Z54-IF(D54="UNTUCA",IF(+((W54-3)*2.5+(X54-3)*3.1)>0,+((W54-3)*1.5+(X54-3)*3.1),0),IF(+((W54-3)*1.5+(X54-3)*3.1)>0,+((W54-3)*1.5+(X54-3)*3.1),0))) -> -58.977 | AF54: =(L54-O54)*(R54-U54)*Q54*V54/100 -> 5.4406458 | AG54: =+IF(D54="RONALD WILLIAN GARIBAY ESCUDERO",AC54+AD54+AE54+AF54+70,AC54+AD54+AE54+AF54)+70 -> 67.667123 | AH54: =31.1035*L54*Q54*1.1023*K54/100 -> 13.17718 | AI54: =+((+$AI$2-R54+U54)*L54*Q54*V54)/100 -> 27.5928 | AJ54: =31.1035*1.1023*K54*P54*O54/100 -> 12.24935 | AL54: =+IF(AB54*K54>0,AB54*K54,0) -> 777.49056
A55: IP-1154 | B55: 45692 | C55: 45689 | D55: COMPAÑÍA MINERA CIKAM PERU SAC | E55: {=XLOOKUP(D55,RUC!$B$3:$B$79,RUC!$D$3:$D$79)} -> 20517242919 | G55: 40 | H55: MINERAL | I55: 3.97 | J55: 1.7 | K55: =+I55-(I55*(J55/100)) -> 3.90251 | L55: 0.299 | M55: 0.295 | N55: 0.295 | O55: =+ROUND((M55+N55)/2,3) -> 0.295 | P55: 90 | Q55: 90.13 | R55: 2812.05 | S55: 105 | U55: 80 | V55: 1.1023 | Z55: 10 | AA55: =+Y55+Z55 -> 10 | AB55: =+((O55*P55*(R55-U55)/100)-S55-AA55+T55)*V55 -> 672.79903 | AC55: =+(S55-T55)*V55-'data 1'!$F$4 -> 35.7415 | AD55: =+(Q55-P55)*(R55-U55)*L55*V55/100 -> 1.1705851 | AE55: =+(Y55*V55-70)+V55*(Z55-IF(D55="UNTUCA",IF(+((W55-3)*2.5+(X55-3)*3.1)>0,+((W55-3)*1.5+(X55-3)*3.1),0),IF(+((W55-3)*1.5+(X55-3)*3.1)>0,+((W55-3)*1.5+(X55-3)*3.1),0))) -> -58.977 | AF55: =(L55-O55)*(R55-U55)*Q55*V55/100 -> 10.857199 | AG55: =+IF(D55="RONALD WILLIAN GARIBAY ESCUDERO",AC55+AD55+AE55+AF55+70,AC55+AD55+AE55+AF55)+70 -> 58.792284 | AH55: =31.1035*L55*Q55*1.1023*K55/100 -> 36.057337 | AI55: =+((+$AI$2-R55+U55)*L55*Q55*V55)/100 -> 49.890789 | AJ55: =31.1035*1.1023*K55*P55*O55/100 -> 35.523653 | AL55: =+IF(AB55*K55>0,AB55*K55,0) -> 2625.6049
A56: IP-1155 | B56: 45695 | C56: 45689 | D56: LLASA YUCRA YOLANDA | E56: {=XLOOKUP(D56,RUC!$B$3:$B$79,RUC!$D$3:$D$79)} -> #N/A | G56: 110 | H56: MINERAL | I56: 8.54 | J56: 1.3 | K56: =+I56-(I56*(J56/100)) -> 8.42898 | L56: 0.337 | M56: 0.323 | N56: 0.367 | O56: =+ROUND((M56+N56)/2,3) -> 0.345 | P56: 90 | Q56: 90.21 | R56: 2812.05 | S56: =IF((90+ROUNDDOWN(O56,1)*100)<95,95,(90+ROUNDDOWN(O56,1)*100)) -> 120 | U56: 120 | V56: 1.1023 | Y56: 20 | Z56: =IF(IF(D56="UNTUCA",IF(+((W56-3)*1.5+(X56-3)*3.1)>0,+((W56-3)*1.5+(X56-3)*3.1),0),IF(+((W56-3)*1.5+(X56-3)*3.1)>0,+((W56-3)*1.5+(X56-3)*3.1),0))<30,30,IF(D56="UNTUCA",IF(+((W56-3)*1.5+(X56-3)*3.1)>0,+((W56-3)*1.5+(X56-3)*3.1),0),IF(+((W56-3)*1.5+(X56-3)*3.1)>0,+((W56-3)*1.5+(X56-3)*3.1),0))) -> 30 | AA56: =+Y56+Z56 -> 50 | AB56: =+((O56*P56*(R56-U56)/100)-S56-AA56+T56)*V56 -> 734.00121 | AC56: =+(S56-T56)*V56-'data 1'!$F$4 -> 52.276 | AD56: =+(Q56-P56)*(R56-U56)*L56*V56/100 -> 2.100062 | AE56: =+(Y56*V56-70)+V56*(Z56-IF(D56="UNTUCA",IF(+((W56-3)*2.5+(X56-3)*3.1)>0,+((W56-3)*1.5+(X56-3)*3.1),0),IF(+((W56-3)*1.5+(X56-3)*3.1)>0,+((W56-3)*1.5+(X56-3)*3.1),0))) -> -14.885 | AF56: =(L56-O56)*(R56-U56)*Q56*V56/100 -> -21.415469 | AG56: =+IF(D56="RONALD WILLIAN GARIBAY ESCUDERO",AC56+AD56+AE56+AF56+70,AC56+AD56+AE56+AF56)+70-53 -> 35.075593 | AH56: =31.1035*L56*Q56*1.1023*K56/100 -> 87.855444 | AI56: =+((+$AI$2-R56+U56)*L56*Q56*V56)/100 -> 69.685644 | AJ56: =31.1035*1.1023*K56*P56*O56/100 -> 89.731659 | AL56: =+IF(AB56*K56>0,AB56*K56,0) -> 6186.8815
A57: IP-1158 | B57: 45692 | C57: 45690 | D57: RONALD WILLIAN GARIBAY ESCUDERO | E57: {=XLOOKUP(D57,RUC!$B$3:$B$79,RUC!$D$3:$D$79)} -> #N/A | G57: 36 | H57: MINERAL | I57: 3.61 | J57: 1.1 | K57: =+I57-(I57*(J57/100)) -> 3.57029 | L57: 0.438 | M57: 0.42 | N57: 0.42 | O57: =+ROUND((M57+N57)/2,3) -> 0.42 | P57: 90 | Q57: 89.94 | R57: 2826.1 | S57: =IF((80+ROUNDDOWN(O57,1)*100)<95,95,(80+ROUNDDOWN(O57,1)*100)) -> 120 | U57: 100 | V57: 1.1023 | Z57: =IF(IF(D57="UNTUCA",IF(+((W57-3)*1.5+(X57-3)*3.1)>0,+((W57-3)*1.5+(X57-3)*3.1),0),IF(+((W57-3)*1.5+(X57-3)*3.1)>0,+((W57-3)*1.5+(X57-3)*3.1),0))<30,30,IF(D57="UNTUCA",IF(+((W57-3)*1.5+(X57-3)*3.1)>0,+((W57-3)*1.5+(X57-3)*3.1),0),IF(+((W57-3)*1.5+(X57-3)*3.1)>0,+((W57-3)*1.5+(X57-3)*3.1),0))) -> 30 | AA57: =+Y57+Z57 -> 30 | AB57: =+((O57*P57*(R57-U57)/100)-S57-AA57+T57)*V57 -> 970.53745 | AC57: =+(S57-T57)*V57-'data 1'!$F$4 -> 52.276 | AD57: =+(Q57-P57)*(R57-U57)*L57*V57/100 -> -0.78970875 | AE57: =+(Y57*V57-70)+V57*(Z57-IF(D57="UNTUCA",IF(+((W57-3)*2.5+(X57-3)*3.1)>0,+((W57-3)*1.5+(X57-3)*3.1),0),IF(+((W57-3)*1.5+(X57-3)*3.1)>0,+((W57-3)*1.5+(X57-3)*3.1),0))) -> -36.931 | AF57: =(L57-O57)*(R57-U57)*Q57*V57/100 -> 48.648223 | AG57: =+IF(D57="RONALD WILLIAN GARIBAY ESCUDERO",AC57+AD57+AE57+AF57+70,AC57+AD57+AE57+AF57)+70-10 -> 193.20351 | AH57: =31.1035*L57*Q57*1.1023*K57/100 -> 48.221371 | AI57: =+((+$AI$2-R57+U57)*L57*Q57*V57)/100 -> 75.51381 | AJ57: =31.1035*1.1023*K57*P57*O57/100 -> 46.270518 | AL57: =+IF(AB57*K57>0,AB57*K57,0) -> 3465.1002
A58: IP-1160 | B58: 45692 | C58: 45690 | D58: RONALD WILLIAN GARIBAY ESCUDERO | E58: {=XLOOKUP(D58,RUC!$B$3:$B$79,RUC!$D$3:$D$79)} -> #N/A | G58: 60 | H58: MINERAL | I58: 2.71 | J58: 1.2 | K58: =+I58-(I58*(J58/100)) -> 2.67748 | L58: 0.192 | M58: 0.182 | N58: 0.182 | O58: =+ROUND((M58+N58)/2,3) -> 0.182 | P58: 90 | Q58: 90.11 | R58: 2826.1 | S58: =IF((80+ROUNDDOWN(O58,1)*100)<95,95,(80+ROUNDDOWN(O58,1)*100)) -> 95 | U58: 100 | V58: 1.1023 | Z58: =IF(IF(D58="UNTUCA",IF(+((W58-3)*1.5+(X58-3)*3.1)>0,+((W58-3)*1.5+(X58-3)*3.1),0),IF(+((W58-3)*1.5+(X58-3)*3.1)>0,+((W58-3)*1.5+(X58-3)*3.1),0))<30,30,IF(D58="UNTUCA",IF(+((W58-3)*1.5+(X58-3)*3.1)>0,+((W58-3)*1.5+(X58-3)*3.1),0),IF(+((W58-3)*1.5+(X58-3)*3.1)>0,+((W58-3)*1.5+(X58-3)*3.1),0))) -> 30 | AA58: =+Y58+Z58 -> 30 | AB58: =+((O58*P58*(R58-U58)/100)-S58-AA58+T58)*V58 -> 354.42823 | AC58: =+(S58-T58)*V58-'data 1'!$F$4 -> 24.7185 | AD58: =+(Q58-P58)*(R58-U58)*L58*V58/100 -> 0.63465178 | AE58: =+(Y58*V58-70)+V58*(Z58-IF(D58="UNTUCA",IF(+((W58-3)*2.5+(X58-3)*3.1)>0,+((W58-3)*1.5+(X58-3)*3.1),0),IF(+((W58-3)*1.5+(X58-3)*3.1)>0,+((W58-3)*1.5+(X58-3)*3.1),0))) -> -36.931 | AF58: =(L58-O58)*(R58-U58)*Q58*V58/100 -> 27.077875 | AG58: =+IF(D58="RONALD WILLIAN GARIBAY ESCUDERO",AC58+AD58+AE58+AF58+70,AC58+AD58+AE58+AF58)+70-10 -> 145.50003 | AH58: =31.1035*L58*Q58*1.1023*K58/100 -> 15.882158 | AI58: =+((+$AI$2-R58+U58)*L58*Q58*V58)/100 -> 33.164512 | AJ58: =31.1035*1.1023*K58*P58*O58/100 -> 15.036585 | AL58: =+IF(AB58*K58>0,AB58*K58,0) -> 948.97449
A59: IP-1167 | B59: 45695 | C59: 45690 | D59: MINERA SOFI GOLD S.A.C. | E59: {=XLOOKUP(D59,RUC!$B$3:$B$79,RUC!$D$3:$D$79)} -> 20548542422 | G59: 62 | H59: MINERAL | I59: 4 | J59: 1.1 | K59: =+I59-(I59*(J59/100)) -> 3.956 | L59: 1.223 | M59: 1.174 | N59: 1.235 | O59: =+ROUND((M59+N59)/2,3) -> 1.205 | P59: 90 | Q59: 89.74 | R59: 2826.1 | S59: 195 | U59: 100 | V59: 1.1023 | Z59: =IF(IF(D59="UNTUCA",IF(+((W59-3)*1.5+(X59-3)*3.1)>0,+((W59-3)*1.5+(X59-3)*3.1),0),IF(+((W59-3)*1.5+(X59-3)*3.1)>0,+((W59-3)*1.5+(X59-3)*3.1),0))<30,30,IF(D59="UNTUCA",IF(+((W59-3)*1.5+(X59-3)*3.1)>0,+((W59-3)*1.5+(X59-3)*3.1),0),IF(+((W59-3)*1.5+(X59-3)*3.1)>0,+((W59-3)*1.5+(X59-3)*3.1),0))) -> 30 | AA59: =+Y59+Z59 -> 30 | AB59: =+((O59*P59*(R59-U59)/100)-S59-AA59+T59)*V59 -> 3010.8833 | AC59: =+(S59-T59)*V59-'data 1'!$F$4 -> 134.9485 | AD59: =+(Q59-P59)*(R59-U59)*L59*V59/100 -> -9.5552355 | AE59: =+(Y59*V59-70)+V59*(Z59-IF(D59="UNTUCA",IF(+((W59-3)*2.5+(X59-3)*3.1)>0,+((W59-3)*1.5+(X59-3)*3.1),0),IF(+((W59-3)*1.5+(X59-3)*3.1)>0,+((W59-3)*1.5+(X59-3)*3.1),0))) -> -36.931 | AF59: =(L59-O59)*(R59-U59)*Q59*V59/100 -> 48.540043 | AG59: =+IF(D59="RONALD WILLIAN GARIBAY ESCUDERO",AC59+AD59+AE59+AF59+70,AC59+AD59+AE59+AF59)+70-53 -> 154.00231 | AH59: =31.1035*L59*Q59*1.1023*K59/100 -> 148.85995 | AI59: =+((+$AI$2-R59+U59)*L59*Q59*V59)/100 -> 210.38361 | AJ59: =31.1035*1.1023*K59*P59*O59/100 -> 147.09398 | AL59: =+IF(AB59*K59>0,AB59*K59,0) -> 11911.055
A60: IP-1168 | B60: 45701 | C60: 45691 | D60: LIMBER EDISON MONTALVO QUISPE | E60: {=XLOOKUP(D60,RUC!$B$3:$B$79,RUC!$D$3:$D$79)} -> 10479968131 | G60: 68 | H60: MINERAL | I60: 5.84 | J60: 1.3 | K60: =+I60-(I60*(J60/100)) -> 5.76408 | L60: 0.74 | M60: 0.71 | N60: 0.74 | O60: =+ROUND((M60+N60)/2,3) -> 0.725 | P60: 90 | Q60: 90.03 | R60: 2838.95 | S60: =IF((90+ROUNDDOWN(O60,1)*100)<95,95,(90+ROUNDDOWN(O60,1)*100)) -> 160 | U60: 120 | V60: 1.1023 | Y60: 20 | Z60: =IF(IF(D60="UNTUCA",IF(+((W60-3)*1.5+(X60-3)*3.1)>0,+((W60-3)*1.5+(X60-3)*3.1),0),IF(+((W60-3)*1.5+(X60-3)*3.1)>0,+((W60-3)*1.5+(X60-3)*3.1),0))<30,30,IF(D60="UNTUCA",IF(+((W60-3)*1.5+(X60-3)*3.1)>0,+((W60-3)*1.5+(X60-3)*3.1),0),IF(+((W60-3)*1.5+(X60-3)*3.1)>0,+((W60-3)*1.5+(X60-3)*3.1),0))) -> 30 | AA60: =+Y60+Z60 -> 50 | AB60: =+((O60*P60*(R60-U60)/100)-S60-AA60+T60)*V60 -> 1724.1238 | AC60: =+(S60-T60)*V60-'data 1'!$F$4 -> 96.368 | AD60: =+(Q60-P60)*(R60-U60)*L60*V60/100 -> 0.66535589 | AE60: =+(Y60*V60-70)+V60*(Z60-IF(D60="UNTUCA",IF(+((W60-3)*2.5+(X60-3)*3.1)>0,+((W60-3)*1.5+(X60-3)*3.1),0),IF(+((W60-3)*1.5+(X60-3)*3.1)>0,+((W60-3)*1.5+(X60-3)*3.1),0))) -> -14.885 | AF60: =(L60-O60)*(R60-U60)*Q60*V60/100 -> 40.474318 | AG60: =+IF(D60="RONALD WILLIAN GARIBAY ESCUDERO",AC60+AD60+AE60+AF60+70,AC60+AD60+AE60+AF60)+70-53 -> 139.62267 | AH60: =31.1035*L60*Q60*1.1023*K60/100 -> 131.66127 | AI60: =+((+$AI$2-R60+U60)*L60*Q60*V60)/100 -> 132.95887 | AJ60: =31.1035*1.1023*K60*P60*O60/100 -> 128.94948 | AL60: =+IF(AB60*K60>0,AB60*K60,0) -> 9937.9877
A61: IP-1169 | B61: 45696 | C61: 45691 | D61: LIMBER EDISON MONTALVO QUISPE | E61: {=XLOOKUP(D61,RUC!$B$3:$B$79,RUC!$D$3:$D$79)} -> 10479968131 | G61: 43 | H61: MINERAL | I61: 3.71 | J61: 1.3 | K61: =+I61-(I61*(J61/100)) -> 3.66177 | L61: 0.703 | M61: 0.674 | N61: 0.722 | O61: =+ROUND((M61+N61)/2,3) -> 0.698 | P61: 90 | Q61: 89.88 | R61: 2838.95 | S61: =IF((90+ROUNDDOWN(O61,1)*100)<95,95,(90+ROUNDDOWN(O61,1)*100)) -> 150 | U61: 120 | V61: 1.1023 | Y61: 20 | Z61: =IF(IF(D61="UNTUCA",IF(+((W61-3)*1.5+(X61-3)*3.1)>0,+((W61-3)*1.5+(X61-3)*3.1),0),IF(+((W61-3)*1.5+(X61-3)*3.1)>0,+((W61-3)*1.5+(X61-3)*3.1),0))<30,30,IF(D61="UNTUCA",IF(+((W61-3)*1.5+(X61-3)*3.1)>0,+((W61-3)*1.5+(X61-3)*3.1),0),IF(+((W61-3)*1.5+(X61-3)*3.1)>0,+((W61-3)*1.5+(X61-3)*3.1),0))) -> 30 | AA61: =+Y61+Z61 -> 50 | AB61: =+((O61*P61*(R61-U61)/100)-S61-AA61+T61)*V61 -> 1662.3173 | AC61: =+(S61-T61)*V61-'data 1'!$F$4 -> 85.345 | AD61: =+(Q61-P61)*(R61-U61)*L61*V61/100 -> -2.5283524 | AE61: =+(Y61*V61-70)+V61*(Z61-IF(D61="UNTUCA",IF(+((W61-3)*2.5+(X61-3)*3.1)>0,+((W61-3)*1.5+(X61-3)*3.1),0),IF(+((W61-3)*1.5+(X61-3)*3.1)>0,+((W61-3)*1.5+(X61-3)*3.1),0))) -> -14.885 | AF61: =(L61-O61)*(R61-U61)*Q61*V61/100 -> 13.468961 | AG61: =+IF(D61="RONALD WILLIAN GARIBAY ESCUDERO",AC61+AD61+AE61+AF61+70,AC61+AD61+AE61+AF61)+70-53 -> 98.400609 | AH61: =31.1035*L61*Q61*1.1023*K61/100 -> 79.326542 | AI61: =+((+$AI$2-R61+U61)*L61*Q61*V61)/100 -> 126.10048 | AJ61: =31.1035*1.1023*K61*P61*O61/100 -> 78.867498 | AL61: =+IF(AB61*K61>0,AB61*K61,0) -> 6087.0237
A62: IP-1170 | B62: 45695 | C62: 45692 | D62: PIMENTEL BATALLANOS JUAN CRISOSTOMO | E62: {=XLOOKUP(D62,RUC!$B$3:$B$79,RUC!$D$3:$D$79)} -> 10306762465 | G62: 100 | H62: MINERAL | I62: 8.61 | J62: 1.2 | K62: =+I62-(I62*(J62/100)) -> 8.50668 | L62: 0.267 | M62: 0.256 | N62: 0.256 | O62: =+ROUND((M62+N62)/2,3) -> 0.256 | P62: 90 | Q62: 90.14 | R62: 2843.55 | S62: =IF((90+ROUNDDOWN(O62,1)*100)<95,95,(90+ROUNDDOWN(O62,1)*100)) -> 110 | U62: 120 | V62: 1.1023 | Y62: 20 | Z62: =IF(IF(D62="UNTUCA",IF(+((W62-3)*1.5+(X62-3)*3.1)>0,+((W62-3)*1.5+(X62-3)*3.1),0),IF(+((W62-3)*1.5+(X62-3)*3.1)>0,+((W62-3)*1.5+(X62-3)*3.1),0))<30,30,IF(D62="UNTUCA",IF(+((W62-3)*1.5+(X62-3)*3.1)>0,+((W62-3)*1.5+(X62-3)*3.1),0),IF(+((W62-3)*1.5+(X62-3)*3.1)>0,+((W62-3)*1.5+(X62-3)*3.1),0))) -> 30 | AA62: =+Y62+Z62 -> 50 | AB62: =+((O62*P62*(R62-U62)/100)-S62-AA62+T62)*V62 -> 515.33178 | AC62: =+(S62-T62)*V62-'data 1'!$F$4 -> 41.253 | AD62: =+(Q62-P62)*(R62-U62)*L62*V62/100 -> 1.1222108 | AE62: =+(Y62*V62-70)+V62*(Z62-IF(D62="UNTUCA",IF(+((W62-3)*2.5+(X62-3)*3.1)>0,+((W62-3)*1.5+(X62-3)*3.1),0),IF(+((W62-3)*1.5+(X62-3)*3.1)>0,+((W62-3)*1.5+(X62-3)*3.1),0))) -> -14.885 | AF62: =(L62-O62)*(R62-U62)*Q62*V62/100 -> 29.767708 | AG62: =+IF(D62="RONALD WILLIAN GARIBAY ESCUDERO",AC62+AD62+AE62+AF62+70,AC62+AD62+AE62+AF62)+70-53 -> 74.257919 | AH62: =31.1035*L62*Q62*1.1023*K62/100 -> 70.193675 | AI62: =+((+$AI$2-R62+U62)*L62*Q62*V62)/100 -> 46.811255 | AJ62: =31.1035*1.1023*K62*P62*O62/100 -> 67.197272 | AL62: =+IF(AB62*K62>0,AB62*K62,0) -> 4383.7625
A63: IP-1181 | B63: 45699 | C63: 45692 | D63: MINERA AURIFERA 2 DE DICIEMBRE CALPA RENACE S.A. | E63: {=XLOOKUP(D63,RUC!$B$3:$B$79,RUC!$D$3:$D$79)} -> #N/A | G63: 110 | H63: LLAMPO | I63: 5.95 | J63: 30 | K63: =+I63-(I63*(J63/100)) -> 4.165 | L63: 0.159 | M63: 0.149 | N63: 0.207 | O63: =+ROUND((M63+N63)/2,3) -> 0.178 | P63: 90 | Q63: 90.22 | R63: 2843.55 | S63: =IF((85+ROUNDDOWN(O63,1)*100)<95,95,(85+ROUNDDOWN(O63,1)*100)) -> 95 | U63: 90 | V63: 1.1023 | Z63: 25 | AA63: =+Y63+Z63 -> 25 | AB63: =+((O63*P63*(R63-U63)/100)-S63-AA63+T63)*V63 -> 353.96915 | AC63: =+(S63-T63)*V63-'data 1'!$F$4 -> 24.7185 | AD63: =+(Q63-P63)*(R63-U63)*L63*V63/100 -> 1.0617263 | AE63: =+(Y63*V63-70)+V63*(Z63-IF(D63="UNTUCA",IF(+((W63-3)*2.5+(X63-3)*3.1)>0,+((W63-3)*1.5+(X63-3)*3.1),0),IF(+((W63-3)*1.5+(X63-3)*3.1)>0,+((W63-3)*1.5+(X63-3)*3.1),0))) -> -42.4425 | AF63: =(L63-O63)*(R63-U63)*Q63*V63/100 -> -52.029446 | AG63: =+IF(D63="RONALD WILLIAN GARIBAY ESCUDERO",AC63+AD63+AE63+AF63+70,AC63+AD63+AE63+AF63)+70-53 -> -51.691719 | AH63: =31.1035*L63*Q63*1.1023*K63/100 -> 20.484437 | AI63: =+((+$AI$2-R63+U63)*L63*Q63*V63)/100 -> 23.157364 | AJ63: =31.1035*1.1023*K63*P63*O63/100 -> 22.876342 | AL63: =+IF(AB63*K63>0,AB63*K63,0) -> 1474.2815
